Workbook
Name LL_COR_BE_SEC_ACT: #REF!
Name LL_COR_BE_SEC_ACT: #REF!
Name LL_COR_BE_SEC_PLAN: #REF!
Name LL_COR_BE_SEC_PLAN: #REF!
Name LL_COR_BE_SEC_PREV: #REF!
Name LL_COR_BE_YTD_ACT: #REF!
Name LL_COR_BE_YTD_PLAN: #REF!
Name LL_COR_BE_YTD_PREV: #REF!
Name LL_COR_BR_SEC: #REF!
Name LL_COR_BR_SEC_PLAN: #REF!
Name LL_COR_BR_SEC_PREV: #REF!
Name LL_COR_BR_YTD: #REF!
Name LL_COR_BR_YTD_PLAN: #REF!
Name LL_COR_BR_YTD_PREV: #REF!
Name LL_COR_UA_SEC: #REF!
Name LL_COR_UA_SEC_PLAN: #REF!
Name LL_COR_UA_SEC_PREV: #REF!
Name LL_COR_UA_YTD: #REF!
Name LL_COR_UA_YTD_PLAN: #REF!
Name LL_COR_UA_YTD_PREV: #REF!
Name LL_FLE_BR_SEC: #REF!
Name LL_FLE_BR_SEC_PLAN: #REF!
Name LL_FLE_BR_SEC_PREV: #REF!
Name LL_FLE_BR_YTD: #REF!
Name LL_FLE_BR_YTD_PLAN: #REF!
Name LL_FLE_BR_YTD_PREV: #REF!
Name LL_FLE_UA_SEC: #REF!
Name LL_FLE_UA_SEC_PLAN: #REF!
Name LL_FLE_UA_SEC_PREV: #REF!
Name LL_FLE_UA_YTD: #REF!
Name LL_FLE_UA_YTD_PLAN: #REF!
Name LL_FLE_UA_YTD_PREV: #REF!
Name LL_IBNR_COR_BE_SEC_ACT: #REF!
Name LL_IBNR_COR_BE_SEC_PLAN: #REF!
Name LL_IBNR_COR_BE_SEC_PREV: #REF!
Name LL_IBNR_COR_BE_YTD_ACT: #REF!
Name LL_IBNR_COR_BE_YTD_PLAN: #REF!
Name LL_IBNR_COR_BE_YTD_PREV: #REF!
Name LL_IBNR_COR_BR_SEC: #REF!
Name LL_IBNR_COR_BR_SEC_PLAN: #REF!
Name LL_IBNR_COR_BR_SEC_PREV: #REF!
Name LL_IBNR_COR_BR_YTD: #REF!
Name LL_IBNR_COR_BR_YTD_PLAN: #REF!
Name LL_IBNR_COR_BR_YTD_PREV: #REF!
Name LL_IBNR_COR_UA_SEC: #REF!
Name LL_IBNR_COR_UA_SEC_PLAN: #REF!
Name LL_IBNR_COR_UA_SEC_PREV: #REF!
Name LL_IBNR_COR_UA_YTD: #REF!
Name LL_IBNR_COR_UA_YTD_PLAN: #REF!
Name LL_IBNR_COR_UA_YTD_PREV: #REF!
Name LL_IBNR_FLE_BR_SEC: #REF!
Name LL_IBNR_FLE_BR_SEC_PLAN: #REF!
Name LL_IBNR_FLE_BR_SEC_PREV: #REF!
Name LL_IBNR_FLE_BR_YTD: #REF!
Name LL_IBNR_FLE_BR_YTD_PLAN: #REF!
Name LL_IBNR_FLE_BR_YTD_PREV: #REF!
Name LL_IBNR_FLE_UA_SEC: #REF!
Name LL_IBNR_FLE_UA_SEC_PLAN: #REF!
Name LL_IBNR_FLE_UA_SEC_PREV: #REF!
Name LL_IBNR_FLE_UA_YTD: #REF!

Sheet Matrix Flash Report
B1: Financial results P&C per LoB - May 2024 - IFRS9/17 - excluding Quota Share AZSE and Holdings
B3: May 2024 -YTD | F3: The Netherlands | AL3: =B3 -> May 2024 -YTD | AP3: Belgium | BR3: Benelux
F4: Broker ex UWA | J4: Retail | N4: SME | R4: Midcorp | V4: MGA | Z4: Bancassurance | AD4: Other1 | AH4: Total | AP4: Broker ex UWA | AT4: Retail Broker | AX4: SME | BB4: Midcorp | BF4: UWA | BJ4: Other1 | BN4: Total | BR4: Total
F6: Actual | G6: Previous | H6: Plan | J6: Actual | K6: Previous | L6: Plan | N6: Actual | O6: Previous | P6: Plan | R6: Actual | S6: Previous | T6: Plan | V6: Actual | W6: Previous | X6: Plan | Z6: Actual | AA6: Previous | AB6: Plan | AD6: Actual | AE6: Previous | AF6: Plan | AH6: Actual | AI6: Previous | AJ6: Plan | AP6: Actual | AQ6: Previous | AR6: Plan | AT6: Actual | AU6: Previous | AV6: Plan | AX6: Actual | AY6: Previous | AZ6: Plan | BB6: Actual | BC6: Previous | BD6: Plan | BF6: Actual | BG6: Previous | BH6: Plan | BJ6: Actual | BK6: Previous | BL6: Plan | BN6: Actual | BO6: Previous | BP6: Plan | BR6: Actual | BS6: Previous | BT6: Plan
B9: Motor | D9: GWP | J9: =+[1]Retail!$C$29/1000 -> 1.5563908 | K9: =+[1]Retail!$C$30/1000 -> 1.9777291 | L9: =+[1]Retail!$C$31/1000 -> 0 | N9: =+[1]SME!$C$29/1000 -> 24.717281 | O9: =+[1]SME!$C$30/1000 -> 26.269872 | P9: =+[1]SME!$C$31/1000 -> 26.09868 | R9: =+[1]MidCorp!$C$29/1000 -> 88.71968 | S9: =+[1]MidCorp!$C$30/1000 -> 83.060786 | T9: =+[1]MidCorp!$C$31/1000 -> 86.51 | V9: =+[1]MGA!$C$29/1000 -> 34.64386 | W9: =+[1]MGA!$C$30/1000 -> 30.203168 | X9: =+[1]MGA!$C$31/1000 -> 33.01402 | Z9: =+[1]Bancassurance!$C$29/1000 -> 0.04775279 | AA9: =+[1]Bancassurance!$C$30/1000 -> 0 | AB9: =+[1]Bancassurance!$C$31/1000 -> 0 | AD9: =+[1]Specials!$C$29/1000 -> 0.22730861 | AE9: =+[1]Specials!$C$30/1000 -> 0.1526518 | AF9: =+[1]Specials!$C$31/1000 -> 0 | AH9: =+'[1]Total P&C'!$C$29/1000 -> 149.91227 | AI9: =+'[1]Total P&C'!$C$30/1000 -> 141.66421 | AJ9: =+'[1]Total P&C'!$C$31/1000 -> 145.6227 | AL9: Motor | AN9: GWP | AT9: =+[2]Retail!$C$29/1000 -> 13.385938 | AU9: =+[2]Retail!$C$30/1000 -> 13.556885 | AV9: =+[2]Retail!$C$31/1000 -> 15.051035 | AX9: =+[2]SME!$C$29/1000 -> 4.8422735 | AY9: =+[2]SME!$C$30/1000 -> 5.0260385 | AZ9: =+[2]SME!$C$31/1000 -> 5.1908403 | BB9: =+[2]MidCorp!$C$29/1000 -> 12.202893 | BC9: =+[2]MidCorp!$C$30/1000 -> 14.601782 | BD9: =+[2]MidCorp!$C$31/1000 -> 12.683401 | BJ9: =+[2]Specials!$C$29/1000 -> 0 | BK9: =+[2]Specials!$C$30/1000 -> 0 | BL9: =+[2]Specials!$C$31/1000 -> 0 | BN9: =+'[2]Total P&C'!$C$29/1000 -> 30.431104 | BO9: =+'[2]Total P&C'!$C$30/1000 -> 33.184705 | BP9: =+'[2]Total P&C'!$C$31/1000 -> 32.925277 | BR9: =+'[3]Total P&C'!$C$29/1000 -> 180.34338 | BS9: =+'[3]Total P&C'!$C$30/1000 -> 174.84891 | BT9: =+'[3]Total P&C'!$C$31/1000 -> 178.54798
D10: Insurance Service Revenue | J10: =+[1]Retail!$N$29/1000 -> 1.5321743 | K10: =+[1]Retail!$N$30/1000 -> 1.9449421 | L10: =+[1]Retail!$N$31/1000 -> 0 | N10: =+[1]SME!$N$29/1000 -> 15.290361 | O10: =+[1]SME!$N$30/1000 -> 16.305078 | P10: =+[1]SME!$N$31/1000 -> 16.131751 | R10: =+[1]MidCorp!$N$29/1000 -> 72.115851 | S10: =+[1]MidCorp!$N$30/1000 -> 65.510598 | T10: =+[1]MidCorp!$N$31/1000 -> 67.80625 | V10: =+[1]MGA!$N$29/1000 -> 28.361353 | W10: =+[1]MGA!$N$30/1000 -> 24.950295 | X10: =+[1]MGA!$N$31/1000 -> 30.189168 | Z10: =+[1]Bancassurance!$N$29/1000 -> 0.04395041 | AA10: =+[1]Bancassurance!$N$30/1000 -> 0 | AB10: =+[1]Bancassurance!$N$31/1000 -> 0 | AD10: =+[1]Specials!$N$29/1000 -> 0.0769724 | AE10: =+[1]Specials!$N$30/1000 -> 0.01878516 | AF10: =+[1]Specials!$N$31/1000 -> 0 | AH10: =+'[1]Total P&C'!$N$29/1000 -> 117.42066 | AI10: =+'[1]Total P&C'!$N$30/1000 -> 108.7297 | AJ10: =+'[1]Total P&C'!$N$31/1000 -> 114.12717 | AN10: Insurance Service Revenue | AT10: =+[2]Retail!$N$29/1000 -> 12.935799 | AU10: =+[2]Retail!$N$30/1000 -> 12.847086 | AV10: =+[2]Retail!$N$31/1000 -> 13.886397 | AX10: =+[2]SME!$N$29/1000 -> 4.0515994 | AY10: =+[2]SME!$N$30/1000 -> 4.1866977 | AZ10: =+[2]SME!$N$31/1000 -> 4.3052088 | BB10: =+[2]MidCorp!$N$29/1000 -> 8.0085514 | BC10: =+[2]MidCorp!$N$30/1000 -> 9.1735504 | BD10: =+[2]MidCorp!$N$31/1000 -> 7.9935288 | BJ10: =+[2]Specials!$N$29/1000 -> 0 | BK10: =+[2]Specials!$N$30/1000 -> 0 | BL10: =+[2]Specials!$N$31/1000 -> 0 | BN10: =+'[2]Total P&C'!$N$29/1000 -> 24.99595 | BO10: =+'[2]Total P&C'!$N$30/1000 -> 26.207334 | BP10: =+'[2]Total P&C'!$N$31/1000 -> 26.185134 | BR10: =+'[3]Total P&C'!$N$29/1000 -> 142.41661 | BS10: =+'[3]Total P&C'!$N$30/1000 -> 134.93703 | BT10: =+'[3]Total P&C'!$N$31/1000 -> 140.3123
D11: CoR | J11: =+J12+J17+J18+J19+J20 -> 0.99473412 | K11: =+K12+K17+K18+K19+K20 -> 0.7097323 | L11: =+L12+L17+L18+L19+L20 -> #DIV/0! | N11: =+N12+N17+N18+N19+N20 -> 0.90659368 | O11: =+O12+O17+O18+O19+O20 -> 1.0028137 | P11: =+P12+P17+P18+P19+P20 -> 0.91904973 | R11: =+R12+R17+R18+R19+R20 -> 0.98964589 | S11: =+S12+S17+S18+S19+S20 -> 0.92857687 | T11: =+T12+T17+T18+T19+T20 -> 0.96500341 | V11: =+V12+V17+V18+V19+V20 -> 0.9828153 | W11: =+W12+W17+W18+W19+W20 -> 0.92239117 | X11: =+X12+X17+X18+X19+X20 -> 0.96018478 | Z11: =+Z12+Z17+Z18+Z19+Z20 -> 0.15005275 | AA11: =+AA12+AA17+AA18+AA19+AA20 -> #DIV/0! | AB11: =+AB12+AB17+AB18+AB19+AB20 -> #DIV/0! | AD11: =+AD12+AD17+AD18+AD19+AD20 -> -7.2095916 | AE11: =+AE12+AE17+AE18+AE19+AE20 -> -30.095166 | AF11: =+AF12+AF17+AF18+AF19+AF20 -> #DIV/0! | AH11: =+AH12+AH17+AH18+AH19+AH20 -> 0.97155843 | AI11: =+AI12+AI17+AI18+AI19+AI20 -> 0.9292444 | AJ11: =+AJ12+AJ17+AJ18+AJ19+AJ20 -> 0.95579617 | AN11: CoR | AT11: =+AT12+AT17+AT18+AT19+AT20 -> 0.89813125 | AU11: =+AU12+AU17+AU18+AU19+AU20 -> 0.74489036 | AV11: =+AV12+AV17+AV18+AV19+AV20 -> 0.97887741 | AX11: =+AX12+AX17+AX18+AX19+AX20 -> 1.1016911 | AY11: =+AY12+AY17+AY18+AY19+AY20 -> 0.91191067 | AZ11: =+AZ12+AZ17+AZ18+AZ19+AZ20 -> 1.1263427 | BB11: =+BB12+BB17+BB18+BB19+BB20 -> 1.1423509 | BC11: =+BC12+BC17+BC18+BC19+BC20 -> 1.5009576 | BD11: =+BD12+BD17+BD18+BD19+BD20 -> 1.1733336 | BJ11: =+BJ12+BJ17+BJ18+BJ19+BJ20 -> #DIV/0! | BK11: =+BK12+BK17+BK18+BK19+BK20 -> #DIV/0! | BL11: =+BL12+BL17+BL18+BL19+BL20 -> #DIV/0! | BN11: =+BN12+BN17+BN18+BN19+BN20 -> 1.0093728 | BO11: =+BO12+BO17+BO18+BO19+BO20 -> 1.0362242 | BP11: =+BP12+BP17+BP18+BP19+BP20 -> 1.0624844 | BR11: =+BR12+BR17+BR18+BR19+BR20 -> 0.97819534 | BS11: =+BS12+BS17+BS18+BS19+BS20 -> 0.95002192 | BT11: =+BT12+BT17+BT18+BT19+BT20 -> 0.97570636
D12: L.R + ReR AY | J12: =+J13+J14+J15+J16 -> 0.14029228 | K12: =+K13+K14+K15+K16 -> 1.6124657 | L12: =+L13+L14+L15+L16 -> #DIV/0! | N12: =+N13+N14+N15+N16 -> 0.71160839 | O12: =+O13+O14+O15+O16 -> 0.57099348 | P12: =+P13+P14+P15+P16 -> 0.66376763 | R12: =+R13+R14+R15+R16 -> 0.76560473 | S12: =+S13+S14+S15+S16 -> 0.74944335 | T12: =+T13+T14+T15+T16 -> 0.77241344 | V12: =+V13+V14+V15+V16 -> 0.72387673 | W12: =+W13+W14+W15+W16 -> 0.7140264 | X12: =+X13+X14+X15+X16 -> 0.690213 | Z12: =+Z13+Z14+Z15+Z16 -> 0 | AA12: =+AA13+AA14+AA15+AA16 -> #DIV/0! | AB12: =+AB13+AB14+AB15+AB16 -> #DIV/0! | AD12: =+AD13+AD14+AD15+AD16 -> -5.5344513 | AE12: =+AE13+AE14+AE15+AE16 -> -22.502497 | AF12: =+AF13+AF14+AF15+AF16 -> #DIV/0! | AH12: =+AH13+AH14+AH15+AH16 -> 0.7359187 | AI12: =+AI13+AI14+AI15+AI16 -> 0.7259763 | AJ12: =+AJ13+AJ14+AJ15+AJ16 -> 0.73622729 | AN12: L.R + ReR AY | AT12: =+AT13+AT14+AT15+AT16 -> 0.7276934 | AU12: =+AU13+AU14+AU15+AU16 -> 0.81545182 | AV12: =+AV13+AV14+AV15+AV16 -> 0.65439232 | AX12: =+AX13+AX14+AX15+AX16 -> 0.86225949 | AY12: =+AY13+AY14+AY15+AY16 -> 0.61403742 | AZ12: =+AZ13+AZ14+AZ15+AZ16 -> 0.7212415 | BB12: =+BB13+BB14+BB15+BB16 -> 1.0676187 | BC12: =+BC13+BC14+BC15+BC16 -> 0.94336598 | BD12: =+BD13+BD14+BD15+BD16 -> 0.87513257 | BJ12: =+BJ13+BJ14+BJ15+BJ16 -> #DIV/0! | BK12: =+BK13+BK14+BK15+BK16 -> #DIV/0! | BL12: =+BL13+BL14+BL15+BL16 -> #DIV/0! | BN12: =+BN13+BN14+BN15+BN16 -> 0.85841525 | BO12: =+BO13+BO14+BO15+BO16 -> 0.82805004 | BP12: =+BP13+BP14+BP15+BP16 -> 0.73276859 | BR12: =+BR13+BR14+BR15+BR16 -> 0.75741843 | BS12: =+BS13+BS14+BS15+BS16 -> 0.74580096 | BT12: =+BT13+BT14+BT15+BT16 -> 0.73558183
D13: Attritional | J13: =-SUM([1]Retail!$O$29,[1]Retail!$R$29:$V$29,[1]Retail!$Y$29,[1]Retail!$AB$29,[1]Retail!$AU$29,[1]Retail!$AX$29,[1]Retail!$BA$29,[1]Retail!$BD$29)/1000/J10 -> 0.061285319 | K13: =-SUM([1]Retail!$O$30,[1]Retail!$R$30:$V$30,[1]Retail!$Y$30,[1]Retail!$AB$30,[1]Retail!$AU$30,[1]Retail!$AX$30,[1]Retail!$BA$30,[1]Retail!$BD$30)/1000/K10 -> 0.86744515 | L13: =-SUM([1]Retail!$O$31,[1]Retail!$R$31:$V$31,[1]Retail!$Y$31,[1]Retail!$AB$31,[1]Retail!$AU$31,[1]Retail!$AX$31,[1]Retail!$BA$31,[1]Retail!$BD$31)/1000/L10 -> #DIV/0! | N13: =-SUM([1]SME!$O$29,[1]SME!$R$29:$V$29,[1]SME!$Y$29,[1]SME!$AB$29,[1]SME!$AU$29,[1]SME!$AX$29,[1]SME!$BA$29,[1]SME!$BD$29)/1000/N10 -> 0.60795808 | O13: =-SUM([1]SME!$O$30,[1]SME!$R$30:$V$30,[1]SME!$Y$30,[1]SME!$AB$30,[1]SME!$AU$30,[1]SME!$AX$30,[1]SME!$BA$30,[1]SME!$BD$30)/1000/O10 -> 0.52107185 | P13: =-SUM([1]SME!$O$31,[1]SME!$R$31:$V$31,[1]SME!$Y$31,[1]SME!$AB$31,[1]SME!$AU$31,[1]SME!$AX$31,[1]SME!$BA$31,[1]SME!$BD$31)/1000/P10 -> 0.55247915 | R13: =-SUM([1]MidCorp!$O$29,[1]MidCorp!$R$29:$V$29,[1]MidCorp!$Y$29,[1]MidCorp!$AB$29,[1]MidCorp!$AU$29,[1]MidCorp!$AX$29,[1]MidCorp!$BA$29,[1]MidCorp!$BD$29)/1000/R10 -> 0.64185157 | S13: =-SUM([1]MidCorp!$O$30,[1]MidCorp!$R$30:$V$30,[1]MidCorp!$Y$30,[1]MidCorp!$AB$30,[1]MidCorp!$AU$30,[1]MidCorp!$AX$30,[1]MidCorp!$BA$30,[1]MidCorp!$BD$30)/1000/S10 -> 0.58438228 | T13: =-SUM([1]MidCorp!$O$31,[1]MidCorp!$R$31:$V$31,[1]MidCorp!$Y$31,[1]MidCorp!$AB$31,[1]MidCorp!$AU$31,[1]MidCorp!$AX$31,[1]MidCorp!$BA$31,[1]MidCorp!$BD$31)/1000/T10 -> 0.58771728 | V13: =-SUM([1]MGA!$O$29,[1]MGA!$R$29:$V$29,[1]MGA!$Y$29,[1]MGA!$AB$29,[1]MGA!$AU$29,[1]MGA!$AX$29,[1]MGA!$BA$29,[1]MGA!$BD$29)/1000/V10 -> 0.64391622 | W13: =-SUM([1]MGA!$O$30,[1]MGA!$R$30:$V$30,[1]MGA!$Y$30,[1]MGA!$AB$30,[1]MGA!$AU$30,[1]MGA!$AX$30,[1]MGA!$BA$30,[1]MGA!$BD$30)/1000/W10 -> 0.61171307 | X13: =-SUM([1]MGA!$O$31,[1]MGA!$R$31:$V$31,[1]MGA!$Y$31,[1]MGA!$AB$31,[1]MGA!$AU$31,[1]MGA!$AX$31,[1]MGA!$BA$31,[1]MGA!$BD$31)/1000/X10 -> 0.5825274 | Z13: =-SUM([1]Bancassurance!$O$29,[1]Bancassurance!$R$29:$V$29,[1]Bancassurance!$Y$29,[1]Bancassurance!$AB$29,[1]Bancassurance!$AU$29,[1]Bancassurance!$AX$29,[1]Bancassurance!$BA$29,[1]Bancassurance!$BD$29)/1000/Z10 -> 0 | AA13: =-SUM([1]Bancassurance!$O$30,[1]Bancassurance!$R$30:$V$30,[1]Bancassurance!$Y$30,[1]Bancassurance!$AB$30,[1]Bancassurance!$AU$30,[1]Bancassurance!$AX$30,[1]Bancassurance!$BA$30,[1]Bancassurance!$BD$30)/1000/AA10 -> #DIV/0! | AB13: =-SUM([1]Bancassurance!$O$31,[1]Bancassurance!$R$31:$V$31,[1]Bancassurance!$Y$31,[1]Bancassurance!$AB$31,[1]Bancassurance!$AU$31,[1]Bancassurance!$AX$31,[1]Bancassurance!$BA$31,[1]Bancassurance!$BD$31)/1000/AB10 -> #DIV/0! | AD13: =-SUM([1]Specials!$O$29,[1]Specials!$R$29:$V$29,[1]Specials!$Y$29,[1]Specials!$AB$29,[1]Specials!$AU$29,[1]Specials!$AX$29,[1]Specials!$BA$29,[1]Specials!$BD$29)/1000/AD10 -> 0 | AE13: =-SUM([1]Specials!$O$30,[1]Specials!$R$30:$V$30,[1]Specials!$Y$30,[1]Specials!$AB$30,[1]Specials!$AU$30,[1]Specials!$AX$30,[1]Specials!$BA$30,[1]Specials!$BD$30)/1000/AE10 -> 0.015278017 | AF13: =-SUM([1]Specials!$O$31,[1]Specials!$R$31:$V$31,[1]Specials!$Y$31,[1]Specials!$AB$31,[1]Specials!$AU$31,[1]Specials!$AX$31,[1]Specials!$BA$31,[1]Specials!$BD$31)/1000/AF10 -> #DIV/0! | AH13: =-SUM('[1]Total P&C'!$O$29,'[1]Total P&C'!$R$29:$V$29,'[1]Total P&C'!$Y$29,'[1]Total P&C'!$AB$29,'[1]Total P&C'!$AU$29,'[1]Total P&C'!$AX$29,'[1]Total P&C'!$BA$29,'[1]Total P&C'!$BD$29)/1000/AH10 -> 0.62970013 | AI13: =-SUM('[1]Total P&C'!$O$30,'[1]Total P&C'!$R$30:$V$30,'[1]Total P&C'!$Y$30,'[1]Total P&C'!$AB$30,'[1]Total P&C'!$AU$30,'[1]Total P&C'!$AX$30,'[1]Total P&C'!$BA$30,'[1]Total P&C'!$BD$30)/1000/AI10 -> 0.58612495 | AJ13: =-SUM('[1]Total P&C'!$O$31,'[1]Total P&C'!$R$31:$V$31,'[1]Total P&C'!$Y$31,'[1]Total P&C'!$AB$31,'[1]Total P&C'!$AU$31,'[1]Total P&C'!$AX$31,'[1]Total P&C'!$BA$31,'[1]Total P&C'!$BD$31)/1000/AJ10 -> 0.58227823 | AN13: Attritional | AT13: =-SUM([2]Retail!$O$29,[2]Retail!$R$29:$V$29,[2]Retail!$Y$29,[2]Retail!$AB$29,[2]Retail!$AU$29,[2]Retail!$AX$29,[2]Retail!$BA$29,[2]Retail!$BD$29)/1000/AT10 -> 0.65711188 | AU13: =-SUM([2]Retail!$O$30,[2]Retail!$R$30:$V$30,[2]Retail!$Y$30,[2]Retail!$AB$30,[2]Retail!$AU$30,[2]Retail!$AX$30,[2]Retail!$BA$30,[2]Retail!$BD$30)/1000/AU10 -> 0.69138911 | AV13: =-SUM([2]Retail!$O$31,[2]Retail!$R$31:$V$31,[2]Retail!$Y$31,[2]Retail!$AB$31,[2]Retail!$AU$31,[2]Retail!$AX$31,[2]Retail!$BA$31,[2]Retail!$BD$31)/1000/AV10 -> 0.56942389 | AX13: =-SUM([2]SME!$O$29,[2]SME!$R$29:$V$29,[2]SME!$Y$29,[2]SME!$AB$29,[2]SME!$AU$29,[2]SME!$AX$29,[2]SME!$BA$29,[2]SME!$BD$29)/1000/AX10 -> 0.7789166 | AY13: =-SUM([2]SME!$O$30,[2]SME!$R$30:$V$30,[2]SME!$Y$30,[2]SME!$AB$30,[2]SME!$AU$30,[2]SME!$AX$30,[2]SME!$BA$30,[2]SME!$BD$30)/1000/AY10 -> 0.55232458 | AZ13: =-SUM([2]SME!$O$31,[2]SME!$R$31:$V$31,[2]SME!$Y$31,[2]SME!$AB$31,[2]SME!$AU$31,[2]SME!$AX$31,[2]SME!$BA$31,[2]SME!$BD$31)/1000/AZ10 -> 0.63325558 | BB13: =-SUM([2]MidCorp!$O$29,[2]MidCorp!$R$29:$V$29,[2]MidCorp!$Y$29,[2]MidCorp!$AB$29,[2]MidCorp!$AU$29,[2]MidCorp!$AX$29,[2]MidCorp!$BA$29,[2]MidCorp!$BD$29)/1000/BB10 -> 0.91936447 | BC13: =-SUM([2]MidCorp!$O$30,[2]MidCorp!$R$30:$V$30,[2]MidCorp!$Y$30,[2]MidCorp!$AB$30,[2]MidCorp!$AU$30,[2]MidCorp!$AX$30,[2]MidCorp!$BA$30,[2]MidCorp!$BD$30)/1000/BC10 -> 0.84277604 | BD13: =-SUM([2]MidCorp!$O$31,[2]MidCorp!$R$31:$V$31,[2]MidCorp!$Y$31,[2]MidCorp!$AB$31,[2]MidCorp!$AU$31,[2]MidCorp!$AX$31,[2]MidCorp!$BA$31,[2]MidCorp!$BD$31)/1000/BD10 -> 0.66909069 | BJ13: =-SUM([2]Specials!$O$29,[2]Specials!$R$29:$V$29,[2]Specials!$Y$29,[2]Specials!$AB$29,[2]Specials!$AU$29,[2]Specials!$AX$29,[2]Specials!$BA$29,[2]Specials!$BD$29)/1000/BJ10 -> #DIV/0! | BK13: =-SUM([2]Specials!$O$30,[2]Specials!$R$30:$V$30,[2]Specials!$Y$30,[2]Specials!$AB$30,[2]Specials!$AU$30,[2]Specials!$AX$30,[2]Specials!$BA$30,[2]Specials!$BD$30)/1000/BK10 -> #DIV/0! | BL13: =-SUM([2]Specials!$O$31,[2]Specials!$R$31:$V$31,[2]Specials!$Y$31,[2]Specials!$AB$31,[2]Specials!$AU$31,[2]Specials!$AX$31,[2]Specials!$BA$31,[2]Specials!$BD$31)/1000/BL10 -> #DIV/0! | BN13: =-SUM('[2]Total P&C'!$O$29,'[2]Total P&C'!$R$29:$V$29,'[2]Total P&C'!$Y$29,'[2]Total P&C'!$AB$29,'[2]Total P&C'!$AU$29,'[2]Total P&C'!$AX$29,'[2]Total P&C'!$BA$29,'[2]Total P&C'!$BD$29)/1000/BN10 -> 0.76087938 | BO13: =-SUM('[2]Total P&C'!$O$30,'[2]Total P&C'!$R$30:$V$30,'[2]Total P&C'!$Y$30,'[2]Total P&C'!$AB$30,'[2]Total P&C'!$AU$30,'[2]Total P&C'!$AX$30,'[2]Total P&C'!$BA$30,'[2]Total P&C'!$BD$30)/1000/BO10 -> 0.72216426 | BP13: =-SUM('[2]Total P&C'!$O$31,'[2]Total P&C'!$R$31:$V$31,'[2]Total P&C'!$Y$31,'[2]Total P&C'!$AB$31,'[2]Total P&C'!$AU$31,'[2]Total P&C'!$AX$31,'[2]Total P&C'!$BA$31,'[2]Total P&C'!$BD$31)/1000/BP10 -> 0.61034398 | BR13: =-SUM('[3]Total P&C'!$O$29,'[3]Total P&C'!$R$29:$V$29,'[3]Total P&C'!$Y$29,'[3]Total P&C'!$AB$29,'[3]Total P&C'!$AU$29,'[3]Total P&C'!$AX$29,'[3]Total P&C'!$BA$29,'[3]Total P&C'!$BD$29)/1000/BR10 -> 0.65272377 | BS13: =-SUM('[3]Total P&C'!$O$30,'[3]Total P&C'!$R$30:$V$30,'[3]Total P&C'!$Y$30,'[3]Total P&C'!$AB$30,'[3]Total P&C'!$AU$30,'[3]Total P&C'!$AX$30,'[3]Total P&C'!$BA$30,'[3]Total P&C'!$BD$30)/1000/BS10 -> 0.61254636 | BT13: =-SUM('[3]Total P&C'!$O$31,'[3]Total P&C'!$R$31:$V$31,'[3]Total P&C'!$Y$31,'[3]Total P&C'!$AB$31,'[3]Total P&C'!$AU$31,'[3]Total P&C'!$AX$31,'[3]Total P&C'!$BA$31,'[3]Total P&C'!$BD$31)/1000/BT10 -> 0.58751587
D14: Nat Cat | J14: =-([1]Retail!$P$29+[1]Retail!$W$29+[1]Retail!$AV$29+[1]Retail!$AY$29)/1000/J10 -> 0 | K14: =-([1]Retail!$P$30+[1]Retail!$W$30+[1]Retail!$AV$30+[1]Retail!$AY$30)/1000/K10 -> 0 | L14: =-([1]Retail!$P$31+[1]Retail!$W$31+[1]Retail!$AV$31+[1]Retail!$AY$31)/1000/L10 -> #DIV/0! | N14: =-([1]SME!$P$29+[1]SME!$W$29+[1]SME!$AV$29+[1]SME!$AY$29)/1000/N10 -> 0 | O14: =-([1]SME!$P$30+[1]SME!$W$30+[1]SME!$AV$30+[1]SME!$AY$30)/1000/O10 -> 0 | P14: =-([1]SME!$P$31+[1]SME!$W$31+[1]SME!$AV$31+[1]SME!$AY$31)/1000/P10 -> 0.011985147 | R14: =-([1]MidCorp!$P$29+[1]MidCorp!$W$29+[1]MidCorp!$AV$29+[1]MidCorp!$AY$29)/1000/R10 -> 0 | S14: =-([1]MidCorp!$P$30+[1]MidCorp!$W$30+[1]MidCorp!$AV$30+[1]MidCorp!$AY$30)/1000/S10 -> 0 | T14: =-([1]MidCorp!$P$31+[1]MidCorp!$W$31+[1]MidCorp!$AV$31+[1]MidCorp!$AY$31)/1000/T10 -> 0.0095937088 | V14: =-([1]MGA!$P$29+[1]MGA!$W$29+[1]MGA!$AV$29+[1]MGA!$AY$29)/1000/V10 -> 8.9911084e-05 | W14: =-([1]MGA!$P$30+[1]MGA!$W$30+[1]MGA!$AV$30+[1]MGA!$AY$30)/1000/W10 -> 0 | X14: =-([1]MGA!$P$31+[1]MGA!$W$31+[1]MGA!$AV$31+[1]MGA!$AY$31)/1000/X10 -> 0.013029692 | Z14: =-([1]Bancassurance!$P$29+[1]Bancassurance!$W$29+[1]Bancassurance!$AV$29+[1]Bancassurance!$AY$29)/1000/Z10 -> 0 | AA14: =-([1]Bancassurance!$P$30+[1]Bancassurance!$W$30+[1]Bancassurance!$AV$30+[1]Bancassurance!$AY$30)/1000/AA10 -> #DIV/0! | AB14: =-([1]Bancassurance!$P$31+[1]Bancassurance!$W$31+[1]Bancassurance!$AV$31+[1]Bancassurance!$AY$31)/1000/AB10 -> #DIV/0! | AD14: =-([1]Specials!$P$29+[1]Specials!$W$29+[1]Specials!$AV$29+[1]Specials!$AY$29)/1000/AD10 -> 0 | AE14: =-([1]Specials!$P$30+[1]Specials!$W$30+[1]Specials!$AV$30+[1]Specials!$AY$30)/1000/AE10 -> 0 | AF14: =-([1]Specials!$P$31+[1]Specials!$W$31+[1]Specials!$AV$31+[1]Specials!$AY$31)/1000/AF10 -> #DIV/0! | AH14: =-('[1]Total P&C'!$P$29+'[1]Total P&C'!$W$29+'[1]Total P&C'!$AV$29+'[1]Total P&C'!$AY$29)/1000/AH10 -> 2.1716791e-05 | AI14: =-('[1]Total P&C'!$P$30+'[1]Total P&C'!$W$30+'[1]Total P&C'!$AV$30+'[1]Total P&C'!$AY$30)/1000/AI10 -> 0 | AJ14: =-('[1]Total P&C'!$P$31+'[1]Total P&C'!$W$31+'[1]Total P&C'!$AV$31+'[1]Total P&C'!$AY$31)/1000/AJ10 -> 0.01084063 | AN14: Nat Cat | AT14: =-([2]Retail!$P$29+[2]Retail!$W$29+[2]Retail!$AV$29+[2]Retail!$AY$29)/1000/AT10 -> 0.00064228579 | AU14: =-([2]Retail!$P$30+[2]Retail!$W$30+[2]Retail!$AV$30+[2]Retail!$AY$30)/1000/AU10 -> 0 | AV14: =-([2]Retail!$P$31+[2]Retail!$W$31+[2]Retail!$AV$31+[2]Retail!$AY$31)/1000/AV10 -> 0.0089138567 | AX14: =-([2]SME!$P$29+[2]SME!$W$29+[2]SME!$AV$29+[2]SME!$AY$29)/1000/AX10 -> 0.0029749042 | AY14: =-([2]SME!$P$30+[2]SME!$W$30+[2]SME!$AV$30+[2]SME!$AY$30)/1000/AY10 -> 0 | AZ14: =-([2]SME!$P$31+[2]SME!$W$31+[2]SME!$AV$31+[2]SME!$AY$31)/1000/AZ10 -> 0.012201748 | BB14: =-([2]MidCorp!$P$29+[2]MidCorp!$W$29+[2]MidCorp!$AV$29+[2]MidCorp!$AY$29)/1000/BB10 -> 0.00044565363 | BC14: =-([2]MidCorp!$P$30+[2]MidCorp!$W$30+[2]MidCorp!$AV$30+[2]MidCorp!$AY$30)/1000/BC10 -> 0 | BD14: =-([2]MidCorp!$P$31+[2]MidCorp!$W$31+[2]MidCorp!$AV$31+[2]MidCorp!$AY$31)/1000/BD10 -> 0.010818402 | BJ14: =-([2]Specials!$P$29+[2]Specials!$W$29+[2]Specials!$AV$29+[2]Specials!$AY$29)/1000/BJ10 -> #DIV/0! | BK14: =-([2]Specials!$P$30+[2]Specials!$W$30+[2]Specials!$AV$30+[2]Specials!$AY$30)/1000/BK10 -> #DIV/0! | BL14: =-([2]Specials!$P$31+[2]Specials!$W$31+[2]Specials!$AV$31+[2]Specials!$AY$31)/1000/BL10 -> #DIV/0! | BN14: =-('[2]Total P&C'!$P$29+'[2]Total P&C'!$W$29+'[2]Total P&C'!$AV$29+'[2]Total P&C'!$AY$29)/1000/BN10 -> 0.0009573807 | BO14: =-('[2]Total P&C'!$P$30+'[2]Total P&C'!$W$30+'[2]Total P&C'!$AV$30+'[2]Total P&C'!$AY$30)/1000/BO10 -> 0 | BP14: =-('[2]Total P&C'!$P$31+'[2]Total P&C'!$W$31+'[2]Total P&C'!$AV$31+'[2]Total P&C'!$AY$31)/1000/BP10 -> 0.010035833 | BR14: =-('[3]Total P&C'!$P$29+'[3]Total P&C'!$W$29+'[3]Total P&C'!$AV$29+'[3]Total P&C'!$AY$29)/1000/BR10 -> 0.00018593786 | BS14: =-('[3]Total P&C'!$P$30+'[3]Total P&C'!$W$30+'[3]Total P&C'!$AV$30+'[3]Total P&C'!$AY$30)/1000/BS10 -> 0 | BT14: =-('[3]Total P&C'!$P$31+'[3]Total P&C'!$W$31+'[3]Total P&C'!$AV$31+'[3]Total P&C'!$AY$31)/1000/BT10 -> 0.010690438
D15: Large Losses | J15: =-([1]Retail!$Q$29+[1]Retail!$X$29+[1]Retail!$AW$29+[1]Retail!$AZ$29)/1000/J10 -> 0 | K15: =-([1]Retail!$Q$30+[1]Retail!$X$30+[1]Retail!$AW$30+[1]Retail!$AZ$30)/1000/K10 -> 0.654453 | L15: =-([1]Retail!$Q$31+[1]Retail!$X$31+[1]Retail!$AW$31+[1]Retail!$AZ$31)/1000/L10 -> #DIV/0! | N15: =-([1]SME!$Q$29+[1]SME!$X$29-[1]SME!$AW$29+[1]SME!$AZ$29)/1000/N10 -> 0.079414014 | O15: =-([1]SME!$Q$30+[1]SME!$X$30+[1]SME!$AW$30+[1]SME!$AZ$30)/1000/O10 -> 0.025017484 | P15: =-([1]SME!$Q$31+[1]SME!$X$31+[1]SME!$AW$31+[1]SME!$AZ$31)/1000/P10 -> 0.07701123 | R15: =-([1]MidCorp!$Q$29+[1]MidCorp!$X$29+[1]MidCorp!$AW$29+[1]MidCorp!$AZ$29)/1000/R10 -> 0.098017172 | S15: =-([1]MidCorp!$Q$30+[1]MidCorp!$X$30+[1]MidCorp!$AW$30+[1]MidCorp!$AZ$30)/1000/S10 -> 0.0895594 | T15: =-([1]MidCorp!$Q$31+[1]MidCorp!$X$31+[1]MidCorp!$AW$31+[1]MidCorp!$AZ$31)/1000/T10 -> 0.083244052 | V15: =-([1]MGA!$Q$29+[1]MGA!$X$29+[1]MGA!$AW$29+[1]MGA!$AZ$29)/1000/V10 -> 0.063195476 | W15: =-([1]MGA!$Q$30+[1]MGA!$X$30+[1]MGA!$AW$30+[1]MGA!$AZ$30)/1000/W10 -> 0.081869222 | X15: =-([1]MGA!$Q$31+[1]MGA!$X$31+[1]MGA!$AW$31+[1]MGA!$AZ$31)/1000/X10 -> 0.068896058 | Z15: =-([1]Bancassurance!$Q$29+[1]Bancassurance!$X$29+[1]Bancassurance!$AW$29+[1]Bancassurance!$AZ$29)/1000/Z10 -> 0 | AA15: =-([1]Bancassurance!$Q$30+[1]Bancassurance!$X$30+[1]Bancassurance!$AW$30+[1]Bancassurance!$AZ$30)/1000/AA10 -> #DIV/0! | AB15: =-([1]Bancassurance!$Q$31+[1]Bancassurance!$X$31+[1]Bancassurance!$AW$31+[1]Bancassurance!$AZ$31)/1000/AB10 -> #DIV/0! | AD15: =-([1]Specials!$Q$29+[1]Specials!$X$29+[1]Specials!$AW$29+[1]Specials!$AZ$29)/1000/AD10 -> 0 | AE15: =-([1]Specials!$Q$30+[1]Specials!$X$30+[1]Specials!$AW$30+[1]Specials!$AZ$30)/1000/AE10 -> 0 | AF15: =-([1]Specials!$Q$31+[1]Specials!$X$31+[1]Specials!$AW$31+[1]Specials!$AZ$31)/1000/AF10 -> #DIV/0! | AH15: =-('[1]Total P&C'!$Q$29+'[1]Total P&C'!$X$29+'[1]Total P&C'!$AW$29+'[1]Total P&C'!$AZ$29)/1000/AH10 -> 0.085804063 | AI15: =-('[1]Total P&C'!$Q$30+'[1]Total P&C'!$X$30+'[1]Total P&C'!$AW$30+'[1]Total P&C'!$AZ$30)/1000/AI10 -> 0.088205306 | AJ15: =-('[1]Total P&C'!$Q$31+'[1]Total P&C'!$X$31+'[1]Total P&C'!$AW$31+'[1]Total P&C'!$AZ$31)/1000/AJ10 -> 0.078567687 | AN15: Large Losses | AT15: =-([2]Retail!$Q$29+[2]Retail!$X$29+[2]Retail!$AW$29+[2]Retail!$AZ$29)/1000/AT10 -> 0.050869014 | AU15: =-([2]Retail!$Q$30+[2]Retail!$X$30+[2]Retail!$AW$30+[2]Retail!$AZ$30)/1000/AU10 -> 0.066791024 | AV15: =-([2]Retail!$Q$31+[2]Retail!$X$31+[2]Retail!$AW$31+[2]Retail!$AZ$31)/1000/AV10 -> 0.04593048 | AX15: =-([2]SME!$Q$29+[2]SME!$X$29-[2]SME!$AW$29+[2]SME!$AZ$29)/1000/AX10 -> 0.065168147 | AY15: =-([2]SME!$Q$30+[2]SME!$X$30+[2]SME!$AW$30+[2]SME!$AZ$30)/1000/AY10 -> 0.041247306 | AZ15: =-([2]SME!$Q$31+[2]SME!$X$31+[2]SME!$AW$31+[2]SME!$AZ$31)/1000/AZ10 -> 0.059445083 | BB15: =-([2]MidCorp!$Q$29+[2]MidCorp!$X$29+[2]MidCorp!$AW$29+[2]MidCorp!$AZ$29)/1000/BB10 -> 0.068561243 | BC15: =-([2]MidCorp!$Q$30+[2]MidCorp!$X$30+[2]MidCorp!$AW$30+[2]MidCorp!$AZ$30)/1000/BC10 -> 0.035598213 | BD15: =-([2]MidCorp!$Q$31+[2]MidCorp!$X$31+[2]MidCorp!$AW$31+[2]MidCorp!$AZ$31)/1000/BD10 -> 0.076820009 | BJ15: =-([2]Specials!$Q$29+[2]Specials!$X$29+[2]Specials!$AW$29+[2]Specials!$AZ$29)/1000/BJ10 -> #DIV/0! | BK15: =-([2]Specials!$Q$30+[2]Specials!$X$30+[2]Specials!$AW$30+[2]Specials!$AZ$30)/1000/BK10 -> #DIV/0! | BL15: =-([2]Specials!$Q$31+[2]Specials!$X$31+[2]Specials!$AW$31+[2]Specials!$AZ$31)/1000/BL10 -> #DIV/0! | BN15: =-('[2]Total P&C'!$Q$29+'[2]Total P&C'!$X$29+'[2]Total P&C'!$AW$29+'[2]Total P&C'!$AZ$29)/1000/BN10 -> 0.058855247 | BO15: =-('[2]Total P&C'!$Q$30+'[2]Total P&C'!$X$30+'[2]Total P&C'!$AW$30+'[2]Total P&C'!$AZ$30)/1000/BO10 -> 0.051791686 | BP15: =-('[2]Total P&C'!$Q$31+'[2]Total P&C'!$X$31+'[2]Total P&C'!$AW$31+'[2]Total P&C'!$AZ$31)/1000/BP10 -> 0.057582111 | BR15: =-('[3]Total P&C'!$Q$29+'[3]Total P&C'!$X$29+'[3]Total P&C'!$AW$29+'[3]Total P&C'!$AZ$29)/1000/BR10 -> 0.081074199 | BS15: =-('[3]Total P&C'!$Q$30+'[3]Total P&C'!$X$30+'[3]Total P&C'!$AW$30+'[3]Total P&C'!$AZ$30)/1000/BS10 -> 0.08113309 | BT15: =-('[3]Total P&C'!$Q$31+'[3]Total P&C'!$X$31+'[3]Total P&C'!$AW$31+'[3]Total P&C'!$AZ$31)/1000/BT10 -> 0.074651351
D16: Others | J16: =-[1]Retail!$AT$29/1000/J10 -> 0.079006958 | K16: =-[1]Retail!$AT$30/1000/K10 -> 0.090567581 | L16: =-[1]Retail!$AT$31/1000/L10 -> #DIV/0! | N16: =-[1]SME!$AT$29/1000/N10 -> 0.024236296 | O16: =-[1]SME!$AT$30/1000/O10 -> 0.024904146 | P16: =-[1]SME!$AT$31/1000/P10 -> 0.022292102 | R16: =-[1]MidCorp!$AT$29/1000/R10 -> 0.025735987 | S16: =-[1]MidCorp!$AT$30/1000/S10 -> 0.075501677 | T16: =-[1]MidCorp!$AT$31/1000/T10 -> 0.091858398 | V16: =-[1]MGA!$AT$29/1000/V10 -> 0.016675129 | W16: =-[1]MGA!$AT$30/1000/W10 -> 0.020444108 | X16: =-[1]MGA!$AT$31/1000/X10 -> 0.025759851 | Z16: =-[1]Bancassurance!$AT$29/1000/Z10 -> 0 | AA16: =-[1]Bancassurance!$AT$30/1000/AA10 -> #DIV/0! | AB16: =-[1]Bancassurance!$AT$31/1000/AB10 -> #DIV/0! | AD16: =-[1]Specials!$AT$29/1000/AD10 -> -5.5344513 | AE16: =-[1]Specials!$AT$30/1000/AE10 -> -22.517775 | AF16: =-[1]Specials!$AT$31/1000/AF10 -> #DIV/0! | AH16: =-'[1]Total P&C'!$AT$29/1000/AH10 -> 0.020392799 | AI16: =-'[1]Total P&C'!$AT$30/1000/AI10 -> 0.051646049 | AJ16: =-'[1]Total P&C'!$AT$31/1000/AJ10 -> 0.064540746 | AN16: Others | AT16: =-[2]Retail!$AT$29/1000/AT10 -> 0.019070219 | AU16: =-[2]Retail!$AT$30/1000/AU10 -> 0.057271679 | AV16: =-[2]Retail!$AT$31/1000/AV10 -> 0.030124093 | AX16: =-[2]SME!$AT$29/1000/AX10 -> 0.015199834 | AY16: =-[2]SME!$AT$30/1000/AY10 -> 0.020465533 | AZ16: =-[2]SME!$AT$31/1000/AZ10 -> 0.016339088 | BB16: =-[2]MidCorp!$AT$29/1000/BB10 -> 0.079247301 | BC16: =-[2]MidCorp!$AT$30/1000/BC10 -> 0.064991725 | BD16: =-[2]MidCorp!$AT$31/1000/BD10 -> 0.11840346 | BJ16: =-[2]Specials!$AT$29/1000/BJ10 -> #DIV/0! | BK16: =-[2]Specials!$AT$30/1000/BK10 -> #DIV/0! | BL16: =-[2]Specials!$AT$31/1000/BL10 -> #DIV/0! | BN16: =-'[2]Total P&C'!$AT$29/1000/BN10 -> 0.037723241 | BO16: =-'[2]Total P&C'!$AT$30/1000/BO10 -> 0.054094097 | BP16: =-'[2]Total P&C'!$AT$31/1000/BP10 -> 0.054806661 | BR16: =-'[3]Total P&C'!$AT$29/1000/BR10 -> 0.023434515 | BS16: =-'[3]Total P&C'!$AT$30/1000/BS10 -> 0.052121506 | BT16: =-'[3]Total P&C'!$AT$31/1000/BT10 -> 0.062724167
D17: Discounting a.y. | J17: =-([1]Retail!$Z$29+[1]Retail!$AA$29+[1]Retail!$BB$29+[1]Retail!$BC$29)/1000/J10 -> -0.0099639839 | K17: =-([1]Retail!$Z$30+[1]Retail!$AA$30+[1]Retail!$BB$30+[1]Retail!$BC$30)/1000/K10 -> -0.082072747 | L17: =-([1]Retail!$Z$31+[1]Retail!$AA$31+[1]Retail!$BB$31+[1]Retail!$BC$31)/1000/L10 -> #DIV/0! | N17: =-([1]SME!$Z$29+[1]SME!$AA$29+[1]SME!$BB$29+[1]SME!$BC$29)/1000/N10 -> -0.037544493 | O17: =-([1]SME!$Z$30+[1]SME!$AA$30+[1]SME!$BB$30+[1]SME!$BC$30)/1000/O10 -> -0.02132255 | P17: =-([1]SME!$Z$31+[1]SME!$AA$31+[1]SME!$BB$31+[1]SME!$BC$31)/1000/P10 -> -0.022956172 | R17: =-([1]MidCorp!$Z$29+[1]MidCorp!$AA$29+[1]MidCorp!$BB$29+[1]MidCorp!$BC$29)/1000/R10 -> -0.048980363 | S17: =-([1]MidCorp!$Z$30+[1]MidCorp!$AA$30+[1]MidCorp!$BB$30+[1]MidCorp!$BC$30)/1000/S10 -> -0.03682943 | T17: =-([1]MidCorp!$Z$31+[1]MidCorp!$AA$31+[1]MidCorp!$BB$31+[1]MidCorp!$BC$31)/1000/T10 -> -0.024368918 | V17: =-([1]MGA!$Z$29+[1]MGA!$AA$29+[1]MGA!$BB$29+[1]MGA!$BC$29)/1000/V10 -> -0.030589031 | W17: =-([1]MGA!$Z$30+[1]MGA!$AA$30+[1]MGA!$BB$30+[1]MGA!$BC$30)/1000/W10 -> -0.033686976 | X17: =-([1]MGA!$Z$31+[1]MGA!$AA$31+[1]MGA!$BB$31+[1]MGA!$BC$31)/1000/X10 -> -0.027968701 | Z17: =-([1]Bancassurance!$Z$29+[1]Bancassurance!$AA$29+[1]Bancassurance!$BB$29+[1]Bancassurance!$BC$29)/1000/Z10 -> 0 | AA17: =-([1]Bancassurance!$Z$30+[1]Bancassurance!$AA$30+[1]Bancassurance!$BB$30+[1]Bancassurance!$BC$30)/1000/AA10 -> #DIV/0! | AB17: =-([1]Bancassurance!$Z$31+[1]Bancassurance!$AA$31+[1]Bancassurance!$BB$31+[1]Bancassurance!$BC$31)/1000/AB10 -> #DIV/0! | AD17: =-([1]Specials!$Z$29+[1]Specials!$AA$29+[1]Specials!$BB$29+[1]Specials!$BC$29)/1000/AD10 -> 0 | AE17: =-([1]Specials!$Z$30+[1]Specials!$AA$30+[1]Specials!$BB$30+[1]Specials!$BC$30)/1000/AE10 -> 0 | AF17: =-([1]Specials!$Z$31+[1]Specials!$AA$31+[1]Specials!$BB$31+[1]Specials!$BC$31)/1000/AF10 -> #DIV/0! | AH17: =-('[1]Total P&C'!$Z$29+'[1]Total P&C'!$AA$29+'[1]Total P&C'!$BB$29+'[1]Total P&C'!$BC$29)/1000/AH10 -> -0.042489475 | AI17: =-('[1]Total P&C'!$Z$30+'[1]Total P&C'!$AA$30+'[1]Total P&C'!$BB$30+'[1]Total P&C'!$BC$30)/1000/AI10 -> -0.034585864 | AJ17: =-('[1]Total P&C'!$Z$31+'[1]Total P&C'!$AA$31+'[1]Total P&C'!$BB$31+'[1]Total P&C'!$BC$31)/1000/AJ10 -> -0.025121451 | AN17: Discounting a.y. | AT17: =-([2]Retail!$Z$29+[2]Retail!$AA$29+[2]Retail!$BB$29+[2]Retail!$BC$29)/1000/AT10 -> -0.043734096 | AU17: =-([2]Retail!$Z$30+[2]Retail!$AA$30+[2]Retail!$BB$30+[2]Retail!$BC$30)/1000/AU10 -> -0.031585955 | AV17: =-([2]Retail!$Z$31+[2]Retail!$AA$31+[2]Retail!$BB$31+[2]Retail!$BC$31)/1000/AV10 -> -0.017551049 | AX17: =-([2]SME!$Z$29+[2]SME!$AA$29+[2]SME!$BB$29+[2]SME!$BC$29)/1000/AX10 -> -0.034793711 | AY17: =-([2]SME!$Z$30+[2]SME!$AA$30+[2]SME!$BB$30+[2]SME!$BC$30)/1000/AY10 -> -0.023938378 | AZ17: =-([2]SME!$Z$31+[2]SME!$AA$31+[2]SME!$BB$31+[2]SME!$BC$31)/1000/AZ10 -> -0.019477821 | BB17: =-([2]MidCorp!$Z$29+[2]MidCorp!$AA$29+[2]MidCorp!$BB$29+[2]MidCorp!$BC$29)/1000/BB10 -> -0.054958187 | BC17: =-([2]MidCorp!$Z$30+[2]MidCorp!$AA$30+[2]MidCorp!$BB$30+[2]MidCorp!$BC$30)/1000/BC10 -> -0.036296283 | BD17: =-([2]MidCorp!$Z$31+[2]MidCorp!$AA$31+[2]MidCorp!$BB$31+[2]MidCorp!$BC$31)/1000/BD10 -> -0.024573048 | BJ17: =-([2]Specials!$Z$29+[2]Specials!$AA$29+[2]Specials!$BB$29+[2]Specials!$BC$29)/1000/BJ10 -> #DIV/0! | BK17: =-([2]Specials!$Z$30+[2]Specials!$AA$30+[2]Specials!$BB$30+[2]Specials!$BC$30)/1000/BK10 -> #DIV/0! | BL17: =-([2]Specials!$Z$31+[2]Specials!$AA$31+[2]Specials!$BB$31+[2]Specials!$BC$31)/1000/BL10 -> #DIV/0! | BN17: =-('[2]Total P&C'!$Z$29+'[2]Total P&C'!$AA$29+'[2]Total P&C'!$BB$29+'[2]Total P&C'!$BC$29)/1000/BN10 -> -0.045881078 | BO17: =-('[2]Total P&C'!$Z$30+'[2]Total P&C'!$AA$30+'[2]Total P&C'!$BB$30+'[2]Total P&C'!$BC$30)/1000/BO10 -> -0.032013024 | BP17: =-('[2]Total P&C'!$Z$31+'[2]Total P&C'!$AA$31+'[2]Total P&C'!$BB$31+'[2]Total P&C'!$BC$31)/1000/BP10 -> -0.020011441 | BR17: =-('[3]Total P&C'!$Z$29+'[3]Total P&C'!$AA$29+'[3]Total P&C'!$BB$29+'[3]Total P&C'!$BC$29)/1000/BR10 -> -0.043084745 | BS17: =-('[3]Total P&C'!$Z$30+'[3]Total P&C'!$AA$30+'[3]Total P&C'!$BB$30+'[3]Total P&C'!$BC$30)/1000/BS10 -> -0.03408617 | BT17: =-('[3]Total P&C'!$Z$31+'[3]Total P&C'!$AA$31+'[3]Total P&C'!$BB$31+'[3]Total P&C'!$BC$31)/1000/BT10 -> -0.024167819
D18: Run-off + ReR | J18: =-SUM([1]Retail!$AC$29:$AI$29,[1]Retail!$BE$29:$BG$29)/1000/J10 -> 0.18391495 | K18: =-SUM([1]Retail!$AC$30:$AI$30,[1]Retail!$BE$30:$BG$30)/1000/K10 -> -1.4278633 | L18: =-SUM([1]Retail!$AC$31:$AI$31,[1]Retail!$BE$31:$BG$31)/1000/L10 -> #DIV/0! | N18: =-SUM([1]SME!$AC$29:$AI$29,[1]SME!$BE$29:$BG$29)/1000/N10 -> -0.033712429 | O18: =-SUM([1]SME!$AC$30:$AI$30,[1]SME!$BE$30:$BG$30)/1000/O10 -> 0.18815306 | P18: =-SUM([1]SME!$AC$31:$AI$31,[1]SME!$BE$31:$BG$31)/1000/P10 -> -0.0072292083 | R18: =-SUM([1]MidCorp!$AC$29:$AI$29,[1]MidCorp!$BE$29:$BG$29)/1000/R10 -> 0.085719765 | S18: =-SUM([1]MidCorp!$AC$30:$AI$30,[1]MidCorp!$BE$30:$BG$30)/1000/S10 -> 0.0023897793 | T18: =-SUM([1]MidCorp!$AC$31:$AI$31,[1]MidCorp!$BE$31:$BG$31)/1000/T10 -> -0.0051062173 | V18: =-SUM([1]MGA!$AC$29:$AI$29,[1]MGA!$BE$29:$BG$29)/1000/V10 -> -0.15943284 | W18: =-SUM([1]MGA!$AC$30:$AI$30,[1]MGA!$BE$30:$BG$30)/1000/W10 -> 0.0073111524 | X18: =-SUM([1]MGA!$AC$31:$AI$31,[1]MGA!$BE$31:$BG$31)/1000/X10 -> -0.023379002 | Z18: =-SUM([1]Bancassurance!$AC$29:$AI$29,[1]Bancassurance!$BE$29:$BG$29)/1000/Z10 -> 0 | AA18: =-SUM([1]Bancassurance!$AC$30:$AI$30,[1]Bancassurance!$BE$30:$BG$30)/1000/AA10 -> #DIV/0! | AB18: =-SUM([1]Bancassurance!$AC$31:$AI$31,[1]Bancassurance!$BE$31:$BG$31)/1000/AB10 -> #DIV/0! | AD18: =-SUM([1]Specials!$AC$29:$AI$29,[1]Specials!$BE$29:$BG$29)/1000/AD10 -> -2.1424295 | AE18: =-SUM([1]Specials!$AC$30:$AI$30,[1]Specials!$BE$30:$BG$30)/1000/AE10 -> -5.6895911 | AF18: =-SUM([1]Specials!$AC$31:$AI$31,[1]Specials!$BE$31:$BG$31)/1000/AF10 -> #DIV/0! | AH18: =-SUM('[1]Total P&C'!$AC$29:$AI$29,'[1]Total P&C'!$BE$29:$BG$29)/1000/AH10 -> 0.010742823 | AI18: =-SUM('[1]Total P&C'!$AC$30:$AI$30,'[1]Total P&C'!$BE$30:$BG$30)/1000/AI10 -> 0.0048085321 | AJ18: =-SUM('[1]Total P&C'!$AC$31:$AI$31,'[1]Total P&C'!$BE$31:$BG$31)/1000/AJ10 -> -0.014620934 | AN18: Run-off + ReR | AT18: =-SUM([2]Retail!$AC$29:$AI$29,[2]Retail!$BE$29:$BG$29)/1000/AT10 -> 0.47776292 | AU18: =-SUM([2]Retail!$AC$30:$AI$30,[2]Retail!$BE$30:$BG$30)/1000/AU10 -> -0.33584829 | AV18: =-SUM([2]Retail!$AC$31:$AI$31,[2]Retail!$BE$31:$BG$31)/1000/AV10 -> 0.0053656086 | AX18: =-SUM([2]SME!$AC$29:$AI$29,[2]SME!$BE$29:$BG$29)/1000/AX10 -> 0.46355565 | AY18: =-SUM([2]SME!$AC$30:$AI$30,[2]SME!$BE$30:$BG$30)/1000/AY10 -> 0.011924534 | AZ18: =-SUM([2]SME!$AC$31:$AI$31,[2]SME!$BE$31:$BG$31)/1000/AZ10 -> 0.034684462 | BB18: =-SUM([2]MidCorp!$AC$29:$AI$29,[2]MidCorp!$BE$29:$BG$29)/1000/BB10 -> 0.13410523 | BC18: =-SUM([2]MidCorp!$AC$30:$AI$30,[2]MidCorp!$BE$30:$BG$30)/1000/BC10 -> 0.33922916 | BD18: =-SUM([2]MidCorp!$AC$31:$AI$31,[2]MidCorp!$BE$31:$BG$31)/1000/BD10 -> 0.015801103 | BJ18: =-SUM([2]Specials!$AC$29:$AI$29,[2]Specials!$BE$29:$BG$29)/1000/BJ10 -> #DIV/0! | BK18: =-SUM([2]Specials!$AC$30:$AI$30,[2]Specials!$BE$30:$BG$30)/1000/BK10 -> #DIV/0! | BL18: =-SUM([2]Specials!$AC$31:$AI$31,[2]Specials!$BE$31:$BG$31)/1000/BL10 -> #DIV/0! | BN18: =-SUM('[2]Total P&C'!$AC$29:$AI$29,'[2]Total P&C'!$BE$29:$BG$29)/1000/BN10 -> 0.36535421 | BO18: =-SUM('[2]Total P&C'!$AC$30:$AI$30,'[2]Total P&C'!$BE$30:$BG$30)/1000/BO10 -> -0.043988128 | BP18: =-SUM('[2]Total P&C'!$AC$31:$AI$31,'[2]Total P&C'!$BE$31:$BG$31)/1000/BP10 -> 0.013371686 | BR18: =-SUM('[3]Total P&C'!$AC$29:$AI$29,'[3]Total P&C'!$BE$29:$BG$29)/1000/BR10 -> 0.072981689 | BS18: =-SUM('[3]Total P&C'!$AC$30:$AI$30,'[3]Total P&C'!$BE$30:$BG$30)/1000/BS10 -> -0.0046687058 | BT18: =-SUM('[3]Total P&C'!$AC$31:$AI$31,'[3]Total P&C'!$BE$31:$BG$31)/1000/BT10 -> -0.0093969411
D19: Discounting Run-off | J19: =-SUM([1]Retail!$AJ$29:$AK$29,[1]Retail!$BH$29:$BI$29)/1000/J10 -> 0.33452729 | K19: =-SUM([1]Retail!$AJ$30:$AK$30,[1]Retail!$BH$30:$BI$30)/1000/K10 -> 0.061155615 | L19: =-SUM([1]Retail!$AJ$31:$AK$31,[1]Retail!$BH$31:$BI$31)/1000/L10 -> #DIV/0! | N19: =-SUM([1]SME!$AJ$29:$AK$29,[1]SME!$BH$29:$BI$29)/1000/N10 -> -0.013082522 | O19: =-SUM([1]SME!$AJ$30:$AK$30,[1]SME!$BH$30:$BI$30)/1000/O10 -> -0.01810219 | P19: =-SUM([1]SME!$AJ$31:$AK$31,[1]SME!$BH$31:$BI$31)/1000/P10 -> 0 | R19: =-SUM([1]MidCorp!$AJ$29:$AK$29,[1]MidCorp!$BH$29:$BI$29)/1000/R10 -> -0.0074097296 | S19: =-SUM([1]MidCorp!$AJ$30:$AK$30,[1]MidCorp!$BH$30:$BI$30)/1000/S10 -> 0.018929945 | T19: =-SUM([1]MidCorp!$AJ$31:$AK$31,[1]MidCorp!$BH$31:$BI$31)/1000/T10 -> 0 | V19: =-SUM([1]MGA!$AJ$29:$AK$29,[1]MGA!$BH$29:$BI$29)/1000/V10 -> 0.12006639 | W19: =-SUM([1]MGA!$AJ$30:$AK$30,[1]MGA!$BH$30:$BI$30)/1000/W10 -> -0.084584214 | X19: =-SUM([1]MGA!$AJ$31:$AK$31,[1]MGA!$BH$31:$BI$31)/1000/X10 -> 0 | Z19: =-SUM([1]Bancassurance!$AJ$29:$AK$29,[1]Bancassurance!$BH$29:$BI$29)/1000/Z10 -> 0 | AA19: =-SUM([1]Bancassurance!$AJ$30:$AK$30,[1]Bancassurance!$BH$30:$BI$30)/1000/AA10 -> #DIV/0! | AB19: =-SUM([1]Bancassurance!$AJ$31:$AK$31,[1]Bancassurance!$BH$31:$BI$31)/1000/AB10 -> #DIV/0! | AD19: =-SUM([1]Specials!$AJ$29:$AK$29,[1]Specials!$BH$29:$BI$29)/1000/AD10 -> 0.46728918 | AE19: =-SUM([1]Specials!$AJ$30:$AK$30,[1]Specials!$BH$30:$BI$30)/1000/AE10 -> -1.9030783 | AF19: =-SUM([1]Specials!$AJ$31:$AK$31,[1]Specials!$BH$31:$BI$31)/1000/AF10 -> #DIV/0! | AH19: =-SUM('[1]Total P&C'!$AJ$29:$AK$29,'[1]Total P&C'!$BH$29:$BI$29)/1000/AH10 -> 0.027417426 | AI19: =-SUM('[1]Total P&C'!$AJ$30:$AK$30,'[1]Total P&C'!$BH$30:$BI$30)/1000/AI10 -> -0.0099536025 | AJ19: =-SUM('[1]Total P&C'!$AJ$31:$AK$31,'[1]Total P&C'!$BH$31:$BI$31)/1000/AJ10 -> 0 | AN19: Discounting Run-off | AT19: =-SUM([2]Retail!$AJ$29:$AK$29,[2]Retail!$BH$29:$BI$29)/1000/AT10 -> -0.60839864 | AU19: =-SUM([2]Retail!$AJ$30:$AK$30,[2]Retail!$BH$30:$BI$30)/1000/AU10 -> -0.035545513 | AV19: =-SUM([2]Retail!$AJ$31:$AK$31,[2]Retail!$BH$31:$BI$31)/1000/AV10 -> 0 | AX19: =-SUM([2]SME!$AJ$29:$AK$29,[2]SME!$BH$29:$BI$29)/1000/AX10 -> -0.57658296 | AY19: =-SUM([2]SME!$AJ$30:$AK$30,[2]SME!$BH$30:$BI$30)/1000/AY10 -> -0.051957115 | AZ19: =-SUM([2]SME!$AJ$31:$AK$31,[2]SME!$BH$31:$BI$31)/1000/AZ10 -> 0 | BB19: =-SUM([2]MidCorp!$AJ$29:$AK$29,[2]MidCorp!$BH$29:$BI$29)/1000/BB10 -> -0.29942834 | BC19: =-SUM([2]MidCorp!$AJ$30:$AK$30,[2]MidCorp!$BH$30:$BI$30)/1000/BC10 -> -0.0078827691 | BD19: =-SUM([2]MidCorp!$AJ$31:$AK$31,[2]MidCorp!$BH$31:$BI$31)/1000/BD10 -> 0 | BJ19: =-SUM([2]Specials!$AJ$29:$AK$29,[2]Specials!$BH$29:$BI$29)/1000/BJ10 -> #DIV/0! | BK19: =-SUM([2]Specials!$AJ$30:$AK$30,[2]Specials!$BH$30:$BI$30)/1000/BK10 -> #DIV/0! | BL19: =-SUM([2]Specials!$AJ$31:$AK$31,[2]Specials!$BH$31:$BI$31)/1000/BL10 -> #DIV/0! | BN19: =-SUM('[2]Total P&C'!$AJ$29:$AK$29,'[2]Total P&C'!$BH$29:$BI$29)/1000/BN10 -> -0.50424941 | BO19: =-SUM('[2]Total P&C'!$AJ$30:$AK$30,'[2]Total P&C'!$BH$30:$BI$30)/1000/BO10 -> -0.028484315 | BP19: =-SUM('[2]Total P&C'!$AJ$31:$AK$31,'[2]Total P&C'!$BH$31:$BI$31)/1000/BP10 -> 0 | BR19: =-SUM('[3]Total P&C'!$AJ$29:$AK$29,'[3]Total P&C'!$BH$29:$BI$29)/1000/BR10 -> -0.065896952 | BS19: =-SUM('[3]Total P&C'!$AJ$30:$AK$30,'[3]Total P&C'!$BH$30:$BI$30)/1000/BS10 -> -0.013552619 | BT19: =-SUM('[3]Total P&C'!$AJ$31:$AK$31,'[3]Total P&C'!$BH$31:$BI$31)/1000/BT10 -> 0
D20: Expense ratio + ReR | J20: =+J21+J22+J23 -> 0.34596359 | K20: =+K21+K22+K23 -> 0.54604699 | L20: =+L21+L22+L23 -> #DIV/0! | N20: =+N21+N22+N23 -> 0.27932474 | O20: =+O21+O22+O23 -> 0.28309188 | P20: =+P21+P22+P23 -> 0.28546747 | R20: =+R21+R22+R23 -> 0.19471149 | S20: =+S21+S22+S23 -> 0.19464322 | T20: =+T21+T22+T23 -> 0.22206511 | V20: =+V21+V22+V23 -> 0.32889405 | W20: =+W21+W22+W23 -> 0.3193248 | X20: =+X21+X22+X23 -> 0.32131948 | Z20: =+Z21+Z22+Z23 -> 0.15005275 | AA20: =+AA21+AA22+AA23 -> #DIV/0! | AB20: =+AB21+AB22+AB23 -> #DIV/0! | AD20: =+AD21+AD22+AD23 -> 0 | AE20: =+AE21+AE22+AE23 -> 0 | AF20: =+AF21+AF22+AF23 -> #DIV/0! | AH20: =+AH21+AH22+AH23 -> 0.23996895 | AI20: =+AI21+AI22+AI23 -> 0.24299903 | AJ20: =+AJ21+AJ22+AJ23 -> 0.25931126 | AN20: Expense ratio + ReR | AT20: =+AT21+AT22+AT23 -> 0.34480766 | AU20: =+AU21+AU22+AU23 -> 0.3324183 | AV20: =+AV21+AV22+AV23 -> 0.33667054 | AX20: =+AX21+AX22+AX23 -> 0.38725268 | AY20: =+AY21+AY22+AY23 -> 0.36184421 | AZ20: =+AZ21+AZ22+AZ23 -> 0.3898946 | BB20: =+BB21+BB22+BB23 -> 0.29501349 | BC20: =+BC21+BC22+BC23 -> 0.26254148 | BD20: =+BD21+BD22+BD23 -> 0.30697295 | BJ20: =+BJ21+BJ22+BJ23 -> #DIV/0! | BK20: =+BK21+BK22+BK23 -> #DIV/0! | BL20: =+BL21+BL22+BL23 -> #DIV/0! | BN20: =+BN21+BN22+BN23 -> 0.33573383 | BO20: =+BO21+BO22+BO23 -> 0.31265967 | BP20: =+BP21+BP22+BP23 -> 0.33635556 | BR20: =+BR21+BR22+BR23 -> 0.25677692 | BS20: =+BS21+BS22+BS23 -> 0.25652845 | BT20: =+BT21+BT22+BT23 -> 0.2736893
D21: Commission | J21: =-SUM([1]Retail!$AL$29:$AN$29,[1]Retail!$BJ$29)/1000/J10 -> 0.18252445 | K21: =-SUM([1]Retail!$AL$30:$AN$30,[1]Retail!$BJ$30)/1000/K10 -> 0.18659632 | L21: =-SUM([1]Retail!$AL$31:$AN$31,[1]Retail!$BJ$31)/1000/L10 -> #DIV/0! | N21: =-SUM([1]SME!$AL$29:$AN$29,[1]SME!$BJ$29)/1000/N10 -> 0.16297493 | O21: =-SUM([1]SME!$AL$30:$AN$30,[1]SME!$BJ$30)/1000/O10 -> 0.16191156 | P21: =-SUM([1]SME!$AL$31:$AN$31,[1]SME!$BJ$31)/1000/P10 -> 0.16158192 | R21: =-SUM([1]MidCorp!$AL$29:$AN$29,[1]MidCorp!$BJ$29)/1000/R10 -> 0.10118582 | S21: =-SUM([1]MidCorp!$AL$30:$AN$30,[1]MidCorp!$BJ$30)/1000/S10 -> 0.10371762 | T21: =-SUM([1]MidCorp!$AL$31:$AN$31,[1]MidCorp!$BJ$31)/1000/T10 -> 0.10477137 | V21: =-SUM([1]MGA!$AL$29:$AN$29,[1]MGA!$BJ$29)/1000/V10 -> 0.26900051 | W21: =-SUM([1]MGA!$AL$30:$AN$30,[1]MGA!$BJ$30)/1000/W10 -> 0.26088453 | X21: =-SUM([1]MGA!$AL$31:$AN$31,[1]MGA!$BJ$31)/1000/X10 -> 0.24877882 | Z21: =-SUM([1]Bancassurance!$AL$29:$AN$29,[1]Bancassurance!$BJ$29)/1000/Z10 -> 0.15005275 | AA21: =-SUM([1]Bancassurance!$AL$30:$AN$30,[1]Bancassurance!$BJ$30)/1000/AA10 -> #DIV/0! | AB21: =-SUM([1]Bancassurance!$AL$31:$AN$31,[1]Bancassurance!$BJ$31)/1000/AB10 -> #DIV/0! | AD21: =-SUM([1]Specials!$AL$29:$AN$29,[1]Specials!$BJ$29)/1000/AD10 -> 0 | AE21: =-SUM([1]Specials!$AL$30:$AN$30,[1]Specials!$BJ$30)/1000/AE10 -> 0 | AF21: =-SUM([1]Specials!$AL$31:$AN$31,[1]Specials!$BJ$31)/1000/AF10 -> #DIV/0! | AH21: =-SUM('[1]Total P&C'!$AL$29:$AN$29,'[1]Total P&C'!$BJ$29)/1000/AH10 -> 0.15077857 | AI21: =-SUM('[1]Total P&C'!$AL$30:$AN$30,'[1]Total P&C'!$BJ$30)/1000/AI10 -> 0.14997419 | AJ21: =-SUM('[1]Total P&C'!$AL$31:$AN$31,'[1]Total P&C'!$BJ$31)/1000/AJ10 -> 0.15089465 | AN21: Commission | AT21: =-SUM([2]Retail!$AL$29:$AN$29,[2]Retail!$BJ$29)/1000/AT10 -> 0.16486588 | AU21: =-SUM([2]Retail!$AL$30:$AN$30,[2]Retail!$BJ$30)/1000/AU10 -> 0.16431696 | AV21: =-SUM([2]Retail!$AL$31:$AN$31,[2]Retail!$BJ$31)/1000/AV10 -> 0.16622672 | AX21: =-SUM([2]SME!$AL$29:$AN$29,[2]SME!$BJ$29)/1000/AX10 -> 0.19736587 | AY21: =-SUM([2]SME!$AL$30:$AN$30,[2]SME!$BJ$30)/1000/AY10 -> 0.19240737 | AZ21: =-SUM([2]SME!$AL$31:$AN$31,[2]SME!$BJ$31)/1000/AZ10 -> 0.20630263 | BB21: =-SUM([2]MidCorp!$AL$29:$AN$29,[2]MidCorp!$BJ$29)/1000/BB10 -> 0.11308665 | BC21: =-SUM([2]MidCorp!$AL$30:$AN$30,[2]MidCorp!$BJ$30)/1000/BC10 -> 0.1228958 | BD21: =-SUM([2]MidCorp!$AL$31:$AN$31,[2]MidCorp!$BJ$31)/1000/BD10 -> 0.12047252 | BJ21: =-SUM([2]Specials!$AL$29:$AN$29,[2]Specials!$BJ$29)/1000/BJ10 -> #DIV/0! | BK21: =-SUM([2]Specials!$AL$30:$AN$30,[2]Specials!$BJ$30)/1000/BK10 -> #DIV/0! | BL21: =-SUM([2]Specials!$AL$31:$AN$31,[2]Specials!$BJ$31)/1000/BL10 -> #DIV/0! | BN21: =-SUM('[2]Total P&C'!$AL$29:$AN$29,'[2]Total P&C'!$BJ$29)/1000/BN10 -> 0.15354406 | BO21: =-SUM('[2]Total P&C'!$AL$30:$AN$30,'[2]Total P&C'!$BJ$30)/1000/BO10 -> 0.15430552 | BP21: =-SUM('[2]Total P&C'!$AL$31:$AN$31,'[2]Total P&C'!$BJ$31)/1000/BP10 -> 0.1588484 | BR21: =-SUM('[3]Total P&C'!$AL$29:$AN$29,'[3]Total P&C'!$BJ$29)/1000/BR10 -> 0.15126395 | BS21: =-SUM('[3]Total P&C'!$AL$30:$AN$30,'[3]Total P&C'!$BJ$30)/1000/BS10 -> 0.15081542 | BT21: =-SUM('[3]Total P&C'!$AL$31:$AN$31,'[3]Total P&C'!$BJ$31)/1000/BT10 -> 0.15237898
D22: Acquisition | J22: =-SUM([1]Retail!$AO$29:$AP$29)/1000/J10 -> 0.005387357 | K22: =-SUM([1]Retail!$AO$30:$AP$30)/1000/K10 -> 0.056090318 | L22: =-SUM([1]Retail!$AO$31:$AP$31)/1000/L10 -> #DIV/0! | N22: =-SUM([1]SME!$AO$29:$AP$29)/1000/N10 -> 0.051243221 | O22: =-SUM([1]SME!$AO$30:$AP$30)/1000/O10 -> 0.059864908 | P22: =-SUM([1]SME!$AO$31:$AP$31)/1000/P10 -> 0.049226248 | R22: =-SUM([1]MidCorp!$AO$29:$AP$29)/1000/R10 -> 0.017664929 | S22: =-SUM([1]MidCorp!$AO$30:$AP$30)/1000/S10 -> 0.015764922 | T22: =-SUM([1]MidCorp!$AO$31:$AP$31)/1000/T10 -> 0.019997913 | V22: =-SUM([1]MGA!$AO$29:$AP$29)/1000/V10 -> 0.01907292 | W22: =-SUM([1]MGA!$AO$30:$AP$30)/1000/W10 -> 0.014468002 | X22: =-SUM([1]MGA!$AO$31:$AP$31)/1000/X10 -> 0.022731927 | Z22: =-SUM([1]Bancassurance!$AO$29:$AP$29)/1000/Z10 -> 0 | AA22: =-SUM([1]Bancassurance!$AO$30:$AP$30)/1000/AA10 -> #DIV/0! | AB22: =-SUM([1]Bancassurance!$AO$31:$AP$31)/1000/AB10 -> #DIV/0! | AD22: =-SUM([1]Specials!$AO$29:$AP$29)/1000/AD10 -> 0 | AE22: =-SUM([1]Specials!$AO$30:$AP$30)/1000/AE10 -> 0 | AF22: =-SUM([1]Specials!$AO$31:$AP$31)/1000/AF10 -> #DIV/0! | AH22: =-SUM('[1]Total P&C'!$AO$29:$AP$29)/1000/AH10 -> 0.022199133 | AI22: =-SUM('[1]Total P&C'!$AO$30:$AP$30)/1000/AI10 -> 0.023004984 | AJ22: =-SUM('[1]Total P&C'!$AO$31:$AP$31)/1000/AJ10 -> 0.024920702 | AN22: Acquisition | AT22: =-SUM([2]Retail!$AO$29:$AP$29)/1000/AT10 -> 0.099420012 | AU22: =-SUM([2]Retail!$AO$30:$AP$30)/1000/AU10 -> 0.093725473 | AV22: =-SUM([2]Retail!$AO$31:$AP$31)/1000/AV10 -> 0.092248224 | AX22: =-SUM([2]SME!$AO$29:$AP$29)/1000/AX10 -> 0.092953494 | AY22: =-SUM([2]SME!$AO$30:$AP$30)/1000/AY10 -> 0.083746917 | AZ22: =-SUM([2]SME!$AO$31:$AP$31)/1000/AZ10 -> 0.078496456 | BB22: =-SUM([2]MidCorp!$AO$29:$AP$29)/1000/BB10 -> 0.077122287 | BC22: =-SUM([2]MidCorp!$AO$30:$AP$30)/1000/BC10 -> 0.054461113 | BD22: =-SUM([2]MidCorp!$AO$31:$AP$31)/1000/BD10 -> 0.071038799 | BJ22: =-SUM([2]Specials!$AO$29:$AP$29)/1000/BJ10 -> #DIV/0! | BK22: =-SUM([2]Specials!$AO$30:$AP$30)/1000/BK10 -> #DIV/0! | BL22: =-SUM([2]Specials!$AO$31:$AP$31)/1000/BL10 -> #DIV/0! | BN22: =-SUM('[2]Total P&C'!$AO$29:$AP$29)/1000/BN10 -> 0.091227796 | BO22: =-SUM('[2]Total P&C'!$AO$30:$AP$30)/1000/BO10 -> 0.07838737 | BP22: =-SUM('[2]Total P&C'!$AO$31:$AP$31)/1000/BP10 -> 0.083512642 | BR22: =-SUM('[3]Total P&C'!$AO$29:$AP$29)/1000/BR10 -> 0.034314553 | BS22: =-SUM('[3]Total P&C'!$AO$30:$AP$30)/1000/BS10 -> 0.033761295 | BT22: =-SUM('[3]Total P&C'!$AO$31:$AP$31)/1000/BT10 -> 0.035855152
D23: Administration | J23: =-SUM([1]Retail!$AQ$29:$AR$29)/1000/J10 -> 0.15805178 | K23: =-SUM([1]Retail!$AQ$30:$AR$30)/1000/K10 -> 0.30336035 | L23: =-SUM([1]Retail!$AQ$31:$AR$31)/1000/L10 -> #DIV/0! | N23: =-SUM([1]SME!$AQ$29:$AR$29)/1000/N10 -> 0.065106588 | O23: =-SUM([1]SME!$AQ$30:$AR$30)/1000/O10 -> 0.061315412 | P23: =-SUM([1]SME!$AQ$31:$AR$31)/1000/P10 -> 0.074659305 | R23: =-SUM([1]MidCorp!$AQ$29:$AR$29)/1000/R10 -> 0.075860747 | S23: =-SUM([1]MidCorp!$AQ$30:$AR$30)/1000/S10 -> 0.075160677 | T23: =-SUM([1]MidCorp!$AQ$31:$AR$31)/1000/T10 -> 0.09729582 | V23: =-SUM([1]MGA!$AQ$29:$AR$29)/1000/V10 -> 0.040820616 | W23: =-SUM([1]MGA!$AQ$30:$AR$30)/1000/W10 -> 0.043972272 | X23: =-SUM([1]MGA!$AQ$31:$AR$31)/1000/X10 -> 0.049808737 | Z23: =-SUM([1]Bancassurance!$AQ$29:$AR$29)/1000/Z10 -> 0 | AA23: =-SUM([1]Bancassurance!$AQ$30:$AR$30)/1000/AA10 -> #DIV/0! | AB23: =-SUM([1]Bancassurance!$AQ$31:$AR$31)/1000/AB10 -> #DIV/0! | AD23: =-SUM([1]Specials!$AQ$29:$AR$29)/1000/AD10 -> 0 | AE23: =-SUM([1]Specials!$AQ$30:$AR$30)/1000/AE10 -> 0 | AF23: =-SUM([1]Specials!$AQ$31:$AR$31)/1000/AF10 -> #DIV/0! | AH23: =-SUM('[1]Total P&C'!$AQ$29:$AR$29)/1000/AH10 -> 0.066991245 | AI23: =-SUM('[1]Total P&C'!$AQ$30:$AR$30)/1000/AI10 -> 0.070019853 | AJ23: =-SUM('[1]Total P&C'!$AQ$31:$AR$31)/1000/AJ10 -> 0.083495914 | AN23: Administration | AT23: =-SUM([2]Retail!$AQ$29:$AR$29)/1000/AT10 -> 0.080521773 | AU23: =-SUM([2]Retail!$AQ$30:$AR$30)/1000/AU10 -> 0.074375873 | AV23: =-SUM([2]Retail!$AQ$31:$AR$31)/1000/AV10 -> 0.078195589 | AX23: =-SUM([2]SME!$AQ$29:$AR$29)/1000/AX10 -> 0.096933315 | AY23: =-SUM([2]SME!$AQ$30:$AR$30)/1000/AY10 -> 0.085689923 | AZ23: =-SUM([2]SME!$AQ$31:$AR$31)/1000/AZ10 -> 0.10509551 | BB23: =-SUM([2]MidCorp!$AQ$29:$AR$29)/1000/BB10 -> 0.10480456 | BC23: =-SUM([2]MidCorp!$AQ$30:$AR$30)/1000/BC10 -> 0.085184561 | BD23: =-SUM([2]MidCorp!$AQ$31:$AR$31)/1000/BD10 -> 0.11546163 | BJ23: =-SUM([2]Specials!$AQ$29:$AR$29)/1000/BJ10 -> #DIV/0! | BK23: =-SUM([2]Specials!$AQ$30:$AR$30)/1000/BK10 -> #DIV/0! | BL23: =-SUM([2]Specials!$AQ$31:$AR$31)/1000/BL10 -> #DIV/0! | BN23: =-SUM('[2]Total P&C'!$AQ$29:$AR$29)/1000/BN10 -> 0.090961981 | BO23: =-SUM('[2]Total P&C'!$AQ$30:$AR$30)/1000/BO10 -> 0.079966772 | BP23: =-SUM('[2]Total P&C'!$AQ$31:$AR$31)/1000/BP10 -> 0.093994511 | BR23: =-SUM('[3]Total P&C'!$AQ$29:$AR$29)/1000/BR10 -> 0.071198418 | BS23: =-SUM('[3]Total P&C'!$AQ$30:$AR$30)/1000/BS10 -> 0.071951733 | BT23: =-SUM('[3]Total P&C'!$AQ$31:$AR$31)/1000/BT10 -> 0.085455166
D24: Insurance Service Result | J24: =+[1]Retail!$BK$29/1000 -> 0.00806825 | K24: =+[1]Retail!$BK$30/1000 -> 0.56455387 | L24: =+[1]Retail!$BK$31/1000 -> 0.16401228 | N24: =+[1]SME!$BK$29/1000 -> 1.4282163 | O24: =+[1]SME!$BK$30/1000 -> -0.04587727 | P24: =+[1]SME!$BK$31/1000 -> 1.3058696 | R24: =+[1]MidCorp!$BK$29/1000 -> 0.74669515 | S24: =+[1]MidCorp!$BK$30/1000 -> 4.6789722 | T24: =+[1]MidCorp!$BK$31/1000 -> 2.3729878 | V24: =+[1]MGA!$BK$29/1000 -> 0.48738132 | W24: =+[1]MGA!$BK$30/1000 -> 1.9363633 | X24: =+[1]MGA!$BK$31/1000 -> 1.2019884 | Z24: =+[1]Bancassurance!$BK$29/1000 -> 0.03735553 | AA24: =+[1]Bancassurance!$BK$30/1000 -> -0.02490468 | AB24: =+[1]Bancassurance!$BK$31/1000 -> 0 | AD24: =+[1]Specials!$BK$29/1000 -> 0.63191197 | AE24: =+[1]Specials!$BK$30/1000 -> 0.58412767 | AF24: =+[1]Specials!$BK$31/1000 -> 0 | AH24: =+'[1]Total P&C'!$BK$29/1000 -> 3.3396285 | AI24: =+'[1]Total P&C'!$BK$30/1000 -> 7.6932351 | AJ24: =+'[1]Total P&C'!$BK$31/1000 -> 5.0448581 | AN24: Insurance Service Result | AT24: =+[2]Retail!$BK$29/1000 -> 1.3177537 | AU24: =+[2]Retail!$BK$30/1000 -> 3.2774154 | AV24: =+[2]Retail!$BK$31/1000 -> 0.2933166 | AX24: =+[2]SME!$BK$29/1000 -> -0.41201179 | AY24: =+[2]SME!$BK$30/1000 -> 0.36880338 | AZ24: =+[2]SME!$BK$31/1000 -> -0.54393185 | BB24: =+[2]MidCorp!$BK$29/1000 -> -1.1400242 | BC24: =+[2]MidCorp!$BK$30/1000 -> -4.5955594 | BD24: =+[2]MidCorp!$BK$31/1000 -> -1.3855469 | BJ24: =+[2]Specials!$BK$29/1000 -> 0 | BK24: =+[2]Specials!$BK$30/1000 -> 0 | BL24: =+[2]Specials!$BK$31/1000 -> 0 | BN24: =+'[2]Total P&C'!$BK$29/1000 -> -0.23428225 | BO24: =+'[2]Total P&C'!$BK$30/1000 -> -0.94934071 | BP24: =+'[2]Total P&C'!$BK$31/1000 -> -1.6361621 | BR24: =+'[3]Total P&C'!$BK$29/1000 -> 3.1053463 | BS24: =+'[3]Total P&C'!$BK$30/1000 -> 6.7438944 | BT24: =+'[3]Total P&C'!$BK$31/1000 -> 3.4086959
B26: MTPL | D26: GWP | J26: =+[1]Retail!$C$21/1000 -> 0.94467744 | K26: =+[1]Retail!$C$22/1000 -> 1.201728 | L26: =+[1]Retail!$C$23/1000 -> 0 | N26: =+[1]SME!$C$21/1000 -> 11.340722 | O26: =+[1]SME!$C$22/1000 -> 12.046397 | P26: =+[1]SME!$C$23/1000 -> 12.27762 | R26: =+[1]MidCorp!$C$21/1000 -> 54.983343 | S26: =+[1]MidCorp!$C$22/1000 -> 49.40399 | T26: =+[1]MidCorp!$C$23/1000 -> 49.38687 | V26: =+[1]MGA!$C$21/1000 -> 18.095317 | W26: =+[1]MGA!$C$22/1000 -> 16.027855 | X26: =+[1]MGA!$C$23/1000 -> 16.48508 | Z26: =+[1]Bancassurance!$C$21/1000 -> 0 | AA26: =+[1]Bancassurance!$C$22/1000 -> 0 | AB26: =+[1]Bancassurance!$C$23/1000 -> 0 | AD26: =+[1]Specials!$C$21/1000 -> 0.19433375 | AE26: =+[1]Specials!$C$22/1000 -> 0.12200984 | AF26: =+[1]Specials!$C$23/1000 -> 0 | AH26: =+'[1]Total P&C'!$C$21/1000 -> 85.558393 | AI26: =+'[1]Total P&C'!$C$22/1000 -> 78.80198 | AJ26: =+'[1]Total P&C'!$C$23/1000 -> 78.14957 | AL26: MTPL | AN26: GWP | AT26: =+[2]Retail!$C$21/1000 -> 7.7727622 | AU26: =+[2]Retail!$C$22/1000 -> 7.9758582 | AV26: =+[2]Retail!$C$23/1000 -> 9.0071362 | AX26: =+[2]SME!$C$21/1000 -> 2.2108949 | AY26: =+[2]SME!$C$22/1000 -> 2.3550842 | AZ26: =+[2]SME!$C$23/1000 -> 2.4117941 | BB26: =+[2]MidCorp!$C$21/1000 -> 6.3104131 | BC26: =+[2]MidCorp!$C$22/1000 -> 7.262468 | BD26: =+[2]MidCorp!$C$23/1000 -> 6.4797079 | BJ26: =+[2]Specials!$C$21/1000 -> 0 | BK26: =+[2]Specials!$C$22/1000 -> 0 | BL26: =+[2]Specials!$C$23/1000 -> 0 | BN26: =+'[2]Total P&C'!$C$21/1000 -> 16.29407 | BO26: =+'[2]Total P&C'!$C$22/1000 -> 17.59341 | BP26: =+'[2]Total P&C'!$C$23/1000 -> 17.898638 | BR26: =+'[3]Total P&C'!$C$21/1000 -> 101.85246 | BS26: =+'[3]Total P&C'!$C$22/1000 -> 96.39539 | BT26: =+'[3]Total P&C'!$C$23/1000 -> 96.048208
D27: Insurance Service Revenue | J27: =+[1]Retail!$N$21/1000 -> 0.95931627 | K27: =+[1]Retail!$N$22/1000 -> 1.1711001 | L27: =+[1]Retail!$N$23/1000 -> 0 | N27: =+[1]SME!$N$21/1000 -> 7.2882262 | O27: =+[1]SME!$N$22/1000 -> 7.7367101 | P27: =+[1]SME!$N$23/1000 -> 7.596553 | R27: =+[1]MidCorp!$N$21/1000 -> 43.5161 | S27: =+[1]MidCorp!$N$22/1000 -> 37.623425 | T27: =+[1]MidCorp!$N$23/1000 -> 38.709298 | V27: =+[1]MGA!$N$21/1000 -> 15.471581 | W27: =+[1]MGA!$N$22/1000 -> 13.696609 | X27: =+[1]MGA!$N$23/1000 -> 15.074523 | Z27: =+[1]Bancassurance!$N$21/1000 -> 0 | AA27: =+[1]Bancassurance!$N$22/1000 -> 0 | AB27: =+[1]Bancassurance!$N$23/1000 -> 0 | AD27: =+[1]Specials!$N$21/1000 -> 0.06909593 | AE27: =+[1]Specials!$N$22/1000 -> 0.01482135 | AF27: =+[1]Specials!$N$23/1000 -> 0 | AH27: =+'[1]Total P&C'!$N$21/1000 -> 67.30432 | AI27: =+'[1]Total P&C'!$N$22/1000 -> 60.242665 | AJ27: =+'[1]Total P&C'!$N$23/1000 -> 61.380375 | AN27: Insurance Service Revenue | AT27: =+[2]Retail!$N$21/1000 -> 7.5916697 | AU27: =+[2]Retail!$N$22/1000 -> 7.6689383 | AV27: =+[2]Retail!$N$23/1000 -> 8.4032179 | AX27: =+[2]SME!$N$21/1000 -> 1.8608463 | AY27: =+[2]SME!$N$22/1000 -> 1.9818039 | AZ27: =+[2]SME!$N$23/1000 -> 1.9861192 | BB27: =+[2]MidCorp!$N$21/1000 -> 4.2822112 | BC27: =+[2]MidCorp!$N$22/1000 -> 4.6941807 | BD27: =+[2]MidCorp!$N$23/1000 -> 4.131662 | BJ27: =+[2]Specials!$N$21/1000 -> 0 | BK27: =+[2]Specials!$N$22/1000 -> 0 | BL27: =+[2]Specials!$N$23/1000 -> 0 | BN27: =+'[2]Total P&C'!$N$21/1000 -> 13.734727 | BO27: =+'[2]Total P&C'!$N$22/1000 -> 14.344923 | BP27: =+'[2]Total P&C'!$N$23/1000 -> 14.520999 | BR27: =+'[3]Total P&C'!$N$21/1000 -> 81.039047 | BS27: =+'[3]Total P&C'!$N$22/1000 -> 74.587588 | BT27: =+'[3]Total P&C'!$N$23/1000 -> 75.901374
D28: CoR | J28: =+J29+J34+J35+J36+J37 -> 1.0172878 | K28: =+K29+K34+K35+K36+K37 -> 0.29341385 | L28: =+L29+L34+L35+L36+L37 -> #DIV/0! | N28: =+N29+N34+N35+N36+N37 -> 1.0101708 | O28: =+O29+O34+O35+O36+O37 -> 1.2646582 | P28: =+P29+P34+P35+P36+P37 -> 1.0941282 | R28: =+R29+R34+R35+R36+R37 -> 1.004745 | S28: =+S29+S34+S35+S36+S37 -> 0.97488672 | T28: =+T29+T34+T35+T36+T37 -> 0.99605638 | V28: =+V29+V34+V35+V36+V37 -> 1.2195132 | W28: =+W29+W34+W35+W36+W37 -> 0.91902832 | X28: =+X29+X34+X35+X36+X37 -> 1.0358868 | Z28: =+Z29+Z34+Z35+Z36+Z37 -> #DIV/0! | AA28: =+AA29+AA34+AA35+AA36+AA37 -> #DIV/0! | AB28: =+AB29+AB34+AB35+AB36+AB37 -> #DIV/0! | AD28: =+AD29+AD34+AD35+AD36+AD37 -> -6.1644669 | AE28: =+AE29+AE34+AE35+AE36+AE37 -> -30.384716 | AF28: =+AF29+AF34+AF35+AF36+AF37 -> #DIV/0! | AH28: =+AH29+AH34+AH35+AH36+AH37 -> 1.0475211 | AI28: =+AI29+AI34+AI35+AI36+AI37 -> 0.97864477 | AJ28: =+AJ29+AJ34+AJ35+AJ36+AJ37 -> 1.0128569 | AN28: CoR | AT28: =+AT29+AT34+AT35+AT36+AT37 -> 0.79181439 | AU28: =+AU29+AU34+AU35+AU36+AU37 -> 0.51016483 | AV28: =+AV29+AV34+AV35+AV36+AV37 -> 0.89191473 | AX28: =+AX29+AX34+AX35+AX36+AX37 -> 0.97580865 | AY28: =+AY29+AY34+AY35+AY36+AY37 -> 0.90635547 | AZ28: =+AZ29+AZ34+AZ35+AZ36+AZ37 -> 1.2388799 | BB28: =+BB29+BB34+BB35+BB36+BB37 -> 1.4196736 | BC28: =+BC29+BC34+BC35+BC36+BC37 -> 1.9442037 | BD28: =+BD29+BD34+BD35+BD36+BD37 -> 1.3347551 | BJ28: =+BJ29+BJ34+BJ35+BJ36+BJ37 -> #DIV/0! | BK28: =+BK29+BK34+BK35+BK36+BK37 -> #DIV/0! | BL28: =+BL29+BL34+BL35+BL36+BL37 -> #DIV/0! | BN28: =+BN29+BN34+BN35+BN36+BN37 -> 1.0124967 | BO28: =+BO29+BO34+BO35+BO36+BO37 -> 1.0341697 | BP28: =+BP29+BP34+BP35+BP36+BP37 -> 1.0653726 | BR28: =+BR29+BR34+BR35+BR36+BR37 -> 1.0415851 | BS28: =+BS29+BS34+BS35+BS36+BS37 -> 0.9893235 | BT28: =+BT29+BT34+BT35+BT36+BT37 -> 1.0229039
D29: L.R + ReR AY | J29: =+J30+J31+J32+J33 -> 0.16340121 | K29: =+K30+K31+K32+K33 -> 2.1728887 | L29: =+L30+L31+L32+L33 -> #DIV/0! | N29: =+N30+N31+N32+N33 -> 1.0509415 | O29: =+O30+O31+O32+O33 -> 0.68421973 | P29: =+P30+P31+P32+P33 -> 0.85941693 | R29: =+R30+R31+R32+R33 -> 0.87293392 | S29: =+S30+S31+S32+S33 -> 0.8318025 | T29: =+T30+T31+T32+T33 -> 0.86144793 | V29: =+V30+V31+V32+V33 -> 0.80742451 | W29: =+W30+W31+W32+W33 -> 0.77517821 | X29: =+X30+X31+X32+X33 -> 0.7849024 | Z29: =+Z30+Z31+Z32+Z33 -> #DIV/0! | AA29: =+AA30+AA31+AA32+AA33 -> #DIV/0! | AB29: =+AB30+AB31+AB32+AB33 -> #DIV/0! | AD29: =+AD30+AD31+AD32+AD33 -> -4.2983718 | AE29: =+AE30+AE31+AE32+AE33 -> -20.761469 | AF29: =+AF30+AF31+AF32+AF33 -> #DIV/0! | AH29: =+AH30+AH31+AH32+AH33 -> 0.86172873 | AI29: =+AI30+AI31+AI32+AI33 -> 0.82073292 | AJ29: =+AJ30+AJ31+AJ32+AJ33 -> 0.84334852 | AN29: L.R + ReR AY | AT29: =+AT30+AT31+AT32+AT33 -> 0.7051865 | AU29: =+AU30+AU31+AU32+AU33 -> 0.76676323 | AV29: =+AV30+AV31+AV32+AV33 -> 0.58793957 | AX29: =+AX30+AX31+AX32+AX33 -> 0.84503976 | AY29: =+AY30+AY31+AY32+AY33 -> 0.48836125 | AZ29: =+AZ30+AZ31+AZ32+AZ33 -> 0.79396338 | BB29: =+BB30+BB31+BB32+BB33 -> 1.5365526 | BC29: =+BC30+BC31+BC32+BC33 -> 1.2142868 | BD29: =+BD30+BD31+BD32+BD33 -> 1.0760238 | BJ29: =+BJ30+BJ31+BJ32+BJ33 -> #DIV/0! | BK29: =+BK30+BK31+BK32+BK33 -> #DIV/0! | BL29: =+BL30+BL31+BL32+BL33 -> #DIV/0! | BN29: =+BN30+BN31+BN32+BN33 -> 0.98333769 | BO29: =+BO30+BO31+BO32+BO33 -> 0.87474698 | BP29: =+BP30+BP31+BP32+BP33 -> 0.75499329 | BR29: =+BR30+BR31+BR32+BR33 -> 0.88233936 | BS29: =+BS30+BS31+BS32+BS33 -> 0.83112108 | BT29: =+BT30+BT31+BT32+BT33 -> 0.82644493
D30: Attritional | J30: =-SUM([1]Retail!$O$21,[1]Retail!$R$21:$V$21,[1]Retail!$Y$21,[1]Retail!$AB$21,[1]Retail!$AU$21,[1]Retail!$AX$21,[1]Retail!$BA$21,[1]Retail!$BD$21)/1000/J27 -> 0.091659469 | K30: =-SUM([1]Retail!$O$22,[1]Retail!$R$22:$V$22,[1]Retail!$Y$22,[1]Retail!$AB$22,[1]Retail!$AU$22,[1]Retail!$AX$22,[1]Retail!$BA$22,[1]Retail!$BD$22)/1000/K27 -> 0.99670086 | L30: =-SUM([1]Retail!$O$23,[1]Retail!$R$23:$V$23,[1]Retail!$Y$23,[1]Retail!$AB$23,[1]Retail!$AU$23,[1]Retail!$AX$23,[1]Retail!$BA$23,[1]Retail!$BD$23)/1000/L27 -> #DIV/0! | N30: =-SUM([1]SME!$O$21,[1]SME!$R$21:$V$21,[1]SME!$Y$21,[1]SME!$AB$21,[1]SME!$AU$21,[1]SME!$AX$21,[1]SME!$BA$21,[1]SME!$BD$21)/1000/N27 -> 0.85477501 | O30: =-SUM([1]SME!$O$22,[1]SME!$R$22:$V$22,[1]SME!$Y$22,[1]SME!$AB$22,[1]SME!$AU$22,[1]SME!$AX$22,[1]SME!$BA$22,[1]SME!$BD$22)/1000/O27 -> 0.60171297 | P30: =-SUM([1]SME!$O$23,[1]SME!$R$23:$V$23,[1]SME!$Y$23,[1]SME!$AB$23,[1]SME!$AU$23,[1]SME!$AX$23,[1]SME!$BA$23,[1]SME!$BD$23)/1000/P27 -> 0.66657349 | R30: =-SUM([1]MidCorp!$O$21,[1]MidCorp!$R$21:$V$21,[1]MidCorp!$Y$21,[1]MidCorp!$AB$21,[1]MidCorp!$AU$21,[1]MidCorp!$AX$21,[1]MidCorp!$BA$21,[1]MidCorp!$BD$21)/1000/R27 -> 0.69528507 | S30: =-SUM([1]MidCorp!$O$22,[1]MidCorp!$R$22:$V$22,[1]MidCorp!$Y$22,[1]MidCorp!$AB$22,[1]MidCorp!$AU$22,[1]MidCorp!$AX$22,[1]MidCorp!$BA$22,[1]MidCorp!$BD$22)/1000/S27 -> 0.58735375 | T30: =-SUM([1]MidCorp!$O$23,[1]MidCorp!$R$23:$V$23,[1]MidCorp!$Y$23,[1]MidCorp!$AB$23,[1]MidCorp!$AU$23,[1]MidCorp!$AX$23,[1]MidCorp!$BA$23,[1]MidCorp!$BD$23)/1000/T27 -> 0.62102784 | V30: =-SUM([1]MGA!$O$21,[1]MGA!$R$21:$V$21,[1]MGA!$Y$21,[1]MGA!$AB$21,[1]MGA!$AU$21,[1]MGA!$AX$21,[1]MGA!$BA$21,[1]MGA!$BD$21)/1000/V27 -> 0.67312267 | W30: =-SUM([1]MGA!$O$22,[1]MGA!$R$22:$V$22,[1]MGA!$Y$22,[1]MGA!$AB$22,[1]MGA!$AU$22,[1]MGA!$AX$22,[1]MGA!$BA$22,[1]MGA!$BD$22)/1000/W27 -> 0.6032715 | X30: =-SUM([1]MGA!$O$23,[1]MGA!$R$23:$V$23,[1]MGA!$Y$23,[1]MGA!$AB$23,[1]MGA!$AU$23,[1]MGA!$AX$23,[1]MGA!$BA$23,[1]MGA!$BD$23)/1000/X27 -> 0.61443725 | Z30: =-SUM([1]Bancassurance!$O$21,[1]Bancassurance!$R$21:$V$21,[1]Bancassurance!$Y$21,[1]Bancassurance!$AB$21,[1]Bancassurance!$AU$21,[1]Bancassurance!$AX$21,[1]Bancassurance!$BA$21,[1]Bancassurance!$BD$21)/1000/Z27 -> #DIV/0! | AA30: =-SUM([1]Bancassurance!$O$22,[1]Bancassurance!$R$22:$V$22,[1]Bancassurance!$Y$22,[1]Bancassurance!$AB$22,[1]Bancassurance!$AU$22,[1]Bancassurance!$AX$22,[1]Bancassurance!$BA$22,[1]Bancassurance!$BD$22)/1000/AA27 -> #DIV/0! | AB30: =-SUM([1]Bancassurance!$O$23,[1]Bancassurance!$R$23:$V$23,[1]Bancassurance!$Y$23,[1]Bancassurance!$AB$23,[1]Bancassurance!$AU$23,[1]Bancassurance!$AX$23,[1]Bancassurance!$BA$23,[1]Bancassurance!$BD$23)/1000/AB27 -> #DIV/0! | AD30: =-SUM([1]Specials!$O$21,[1]Specials!$R$21:$V$21,[1]Specials!$Y$21,[1]Specials!$AB$21,[1]Specials!$AU$21,[1]Specials!$AX$21,[1]Specials!$BA$21,[1]Specials!$BD$21)/1000/AD27 -> 0 | AE30: =-SUM([1]Specials!$O$22,[1]Specials!$R$22:$V$22,[1]Specials!$Y$22,[1]Specials!$AB$22,[1]Specials!$AU$22,[1]Specials!$AX$22,[1]Specials!$BA$22,[1]Specials!$BD$22)/1000/AE27 -> 0.019363958 | AF30: =-SUM([1]Specials!$O$23,[1]Specials!$R$23:$V$23,[1]Specials!$Y$23,[1]Specials!$AB$23,[1]Specials!$AU$23,[1]Specials!$AX$23,[1]Specials!$BA$23,[1]Specials!$BD$23)/1000/AF27 -> #DIV/0! | AH30: =-SUM('[1]Total P&C'!$O$21,'[1]Total P&C'!$R$21:$V$21,'[1]Total P&C'!$Y$21,'[1]Total P&C'!$AB$21,'[1]Total P&C'!$AU$21,'[1]Total P&C'!$AX$21,'[1]Total P&C'!$BA$21,'[1]Total P&C'!$BD$21)/1000/AH27 -> 0.69814376 | AI30: =-SUM('[1]Total P&C'!$O$22,'[1]Total P&C'!$R$22:$V$22,'[1]Total P&C'!$Y$22,'[1]Total P&C'!$AB$22,'[1]Total P&C'!$AU$22,'[1]Total P&C'!$AX$22,'[1]Total P&C'!$BA$22,'[1]Total P&C'!$BD$22)/1000/AI27 -> 0.60063471 | AJ30: =-SUM('[1]Total P&C'!$O$23,'[1]Total P&C'!$R$23:$V$23,'[1]Total P&C'!$Y$23,'[1]Total P&C'!$AB$23,'[1]Total P&C'!$AU$23,'[1]Total P&C'!$AX$23,'[1]Total P&C'!$BA$23,'[1]Total P&C'!$BD$23)/1000/AJ27 -> 0.62599698 | AN30: Attritional | AT30: =-SUM([2]Retail!$O$21,[2]Retail!$R$21:$V$21,[2]Retail!$Y$21,[2]Retail!$AB$21,[2]Retail!$AU$21,[2]Retail!$AX$21,[2]Retail!$BA$21,[2]Retail!$BD$21)/1000/AT27 -> 0.59282572 | AU30: =-SUM([2]Retail!$O$22,[2]Retail!$R$22:$V$22,[2]Retail!$Y$22,[2]Retail!$AB$22,[2]Retail!$AU$22,[2]Retail!$AX$22,[2]Retail!$BA$22,[2]Retail!$BD$22)/1000/AU27 -> 0.56904471 | AV30: =-SUM([2]Retail!$O$23,[2]Retail!$R$23:$V$23,[2]Retail!$Y$23,[2]Retail!$AB$23,[2]Retail!$AU$23,[2]Retail!$AX$23,[2]Retail!$BA$23,[2]Retail!$BD$23)/1000/AV27 -> 0.46919716 | AX30: =-SUM([2]SME!$O$21,[2]SME!$R$21:$V$21,[2]SME!$Y$21,[2]SME!$AB$21,[2]SME!$AU$21,[2]SME!$AX$21,[2]SME!$BA$21,[2]SME!$BD$21)/1000/AX27 -> 0.68126147 | AY30: =-SUM([2]SME!$O$22,[2]SME!$R$22:$V$22,[2]SME!$Y$22,[2]SME!$AB$22,[2]SME!$AU$22,[2]SME!$AX$22,[2]SME!$BA$22,[2]SME!$BD$22)/1000/AY27 -> 0.37376767 | AZ30: =-SUM([2]SME!$O$23,[2]SME!$R$23:$V$23,[2]SME!$Y$23,[2]SME!$AB$23,[2]SME!$AU$23,[2]SME!$AX$23,[2]SME!$BA$23,[2]SME!$BD$23)/1000/AZ27 -> 0.6405431 | BB30: =-SUM([2]MidCorp!$O$21,[2]MidCorp!$R$21:$V$21,[2]MidCorp!$Y$21,[2]MidCorp!$AB$21,[2]MidCorp!$AU$21,[2]MidCorp!$AX$21,[2]MidCorp!$BA$21,[2]MidCorp!$BD$21)/1000/BB27 -> 1.2626545 | BC30: =-SUM([2]MidCorp!$O$22,[2]MidCorp!$R$22:$V$22,[2]MidCorp!$Y$22,[2]MidCorp!$AB$22,[2]MidCorp!$AU$22,[2]MidCorp!$AX$22,[2]MidCorp!$BA$22,[2]MidCorp!$BD$22)/1000/BC27 -> 1.0211741 | BD30: =-SUM([2]MidCorp!$O$23,[2]MidCorp!$R$23:$V$23,[2]MidCorp!$Y$23,[2]MidCorp!$AB$23,[2]MidCorp!$AU$23,[2]MidCorp!$AX$23,[2]MidCorp!$BA$23,[2]MidCorp!$BD$23)/1000/BD27 -> 0.74635821 | BJ30: =-SUM([2]Specials!$O$21,[2]Specials!$R$21:$V$21,[2]Specials!$Y$21,[2]Specials!$AB$21,[2]Specials!$AU$21,[2]Specials!$AX$21,[2]Specials!$BA$21,[2]Specials!$BD$21)/1000/BJ27 -> #DIV/0! | BK30: =-SUM([2]Specials!$O$22,[2]Specials!$R$22:$V$22,[2]Specials!$Y$22,[2]Specials!$AB$22,[2]Specials!$AU$22,[2]Specials!$AX$22,[2]Specials!$BA$22,[2]Specials!$BD$22)/1000/BK27 -> #DIV/0! | BL30: =-SUM([2]Specials!$O$23,[2]Specials!$R$23:$V$23,[2]Specials!$Y$23,[2]Specials!$AB$23,[2]Specials!$AU$23,[2]Specials!$AX$23,[2]Specials!$BA$23,[2]Specials!$BD$23)/1000/BL27 -> #DIV/0! | BN30: =-SUM('[2]Total P&C'!$O$21,'[2]Total P&C'!$R$21:$V$21,'[2]Total P&C'!$Y$21,'[2]Total P&C'!$AB$21,'[2]Total P&C'!$AU$21,'[2]Total P&C'!$AX$21,'[2]Total P&C'!$BA$21,'[2]Total P&C'!$BD$21)/1000/BN27 -> 0.81364655 | BO30: =-SUM('[2]Total P&C'!$O$22,'[2]Total P&C'!$R$22:$V$22,'[2]Total P&C'!$Y$22,'[2]Total P&C'!$AB$22,'[2]Total P&C'!$AU$22,'[2]Total P&C'!$AX$22,'[2]Total P&C'!$BA$22,'[2]Total P&C'!$BD$22)/1000/BO27 -> 0.69001967 | BP30: =-SUM('[2]Total P&C'!$O$23,'[2]Total P&C'!$R$23:$V$23,'[2]Total P&C'!$Y$23,'[2]Total P&C'!$AB$23,'[2]Total P&C'!$AU$23,'[2]Total P&C'!$AX$23,'[2]Total P&C'!$BA$23,'[2]Total P&C'!$BD$23)/1000/BP27 -> 0.57149379 | BR30: =-SUM('[3]Total P&C'!$O$21,'[3]Total P&C'!$R$21:$V$21,'[3]Total P&C'!$Y$21,'[3]Total P&C'!$AB$21,'[3]Total P&C'!$AU$21,'[3]Total P&C'!$AX$21,'[3]Total P&C'!$BA$21,'[3]Total P&C'!$BD$21)/1000/BR27 -> 0.7177195 | BS30: =-SUM('[3]Total P&C'!$O$22,'[3]Total P&C'!$R$22:$V$22,'[3]Total P&C'!$Y$22,'[3]Total P&C'!$AB$22,'[3]Total P&C'!$AU$22,'[3]Total P&C'!$AX$22,'[3]Total P&C'!$BA$22,'[3]Total P&C'!$BD$22)/1000/BS27 -> 0.61782551 | BT30: =-SUM('[3]Total P&C'!$O$23,'[3]Total P&C'!$R$23:$V$23,'[3]Total P&C'!$Y$23,'[3]Total P&C'!$AB$23,'[3]Total P&C'!$AU$23,'[3]Total P&C'!$AX$23,'[3]Total P&C'!$BA$23,'[3]Total P&C'!$BD$23)/1000/BT27 -> 0.61556976
D31: Nat Cat | J31: =-([1]Retail!$P$21+[1]Retail!$W$21+[1]Retail!$AV$21+[1]Retail!$AY$21)/1000/J27 -> 0 | K31: =-([1]Retail!$P$22+[1]Retail!$W$22+[1]Retail!$AV$22+[1]Retail!$AY$22)/1000/K27 -> 0 | L31: =-([1]Retail!$P$23+[1]Retail!$W$23+[1]Retail!$AV$23+[1]Retail!$AY$23)/1000/L27 -> #DIV/0! | N31: =-([1]SME!$P$21+[1]SME!$W$21+[1]SME!$AV$21+[1]SME!$AY$21)/1000/N27 -> 0 | O31: =-([1]SME!$P$22+[1]SME!$W$22+[1]SME!$AV$22+[1]SME!$AY$22)/1000/O27 -> 0 | P31: =-([1]SME!$P$23+[1]SME!$W$23+[1]SME!$AV$23+[1]SME!$AY$23)/1000/P27 -> 0 | R31: =-([1]MidCorp!$P$21+[1]MidCorp!$W$21+[1]MidCorp!$AV$21+[1]MidCorp!$AY$21)/1000/R27 -> 0 | S31: =-([1]MidCorp!$P$22+[1]MidCorp!$W$22+[1]MidCorp!$AV$22+[1]MidCorp!$AY$22)/1000/S27 -> 0 | T31: =-([1]MidCorp!$P$23+[1]MidCorp!$W$23+[1]MidCorp!$AV$23+[1]MidCorp!$AY$23)/1000/T27 -> 0 | V31: =-([1]MGA!$P$21+[1]MGA!$W$21+[1]MGA!$AV$21+[1]MGA!$AY$21)/1000/V27 -> 0 | W31: =-([1]MGA!$P$22+[1]MGA!$W$22+[1]MGA!$AV$22+[1]MGA!$AY$22)/1000/W27 -> 0 | X31: =-([1]MGA!$P$23+[1]MGA!$W$23+[1]MGA!$AV$23+[1]MGA!$AY$23)/1000/X27 -> 0 | Z31: =-([1]Bancassurance!$P$21+[1]Bancassurance!$W$21+[1]Bancassurance!$AV$21+[1]Bancassurance!$AY$21)/1000/Z27 -> #DIV/0! | AA31: =-([1]Bancassurance!$P$22+[1]Bancassurance!$W$22+[1]Bancassurance!$AV$22+[1]Bancassurance!$AY$22)/1000/AA27 -> #DIV/0! | AB31: =-([1]Bancassurance!$P$23+[1]Bancassurance!$W$23+[1]Bancassurance!$AV$23+[1]Bancassurance!$AY$23)/1000/AB27 -> #DIV/0! | AD31: =-([1]Specials!$P$21+[1]Specials!$W$21+[1]Specials!$AV$21+[1]Specials!$AY$21)/1000/AD27 -> 0 | AE31: =-([1]Specials!$P$22+[1]Specials!$W$22+[1]Specials!$AV$22+[1]Specials!$AY$22)/1000/AE27 -> 0 | AF31: =-([1]Specials!$P$23+[1]Specials!$W$23+[1]Specials!$AV$23+[1]Specials!$AY$23)/1000/AF27 -> #DIV/0! | AH31: =-('[1]Total P&C'!$P$21+'[1]Total P&C'!$W$21+'[1]Total P&C'!$AV$21+'[1]Total P&C'!$AY$21)/1000/AH27 -> 0 | AI31: =-('[1]Total P&C'!$P$22+'[1]Total P&C'!$W$22+'[1]Total P&C'!$AV$22+'[1]Total P&C'!$AY$22)/1000/AI27 -> 0 | AJ31: =-('[1]Total P&C'!$P$23+'[1]Total P&C'!$W$23+'[1]Total P&C'!$AV$23+'[1]Total P&C'!$AY$23)/1000/AJ27 -> 0 | AN31: Nat Cat | AT31: =-([2]Retail!$P$21+[2]Retail!$W$21+[2]Retail!$AV$21+[2]Retail!$AY$21)/1000/AT27 -> 0 | AU31: =-([2]Retail!$P$22+[2]Retail!$W$22+[2]Retail!$AV$22+[2]Retail!$AY$22)/1000/AU27 -> 0 | AV31: =-([2]Retail!$P$23+[2]Retail!$W$23+[2]Retail!$AV$23+[2]Retail!$AY$23)/1000/AV27 -> 0 | AX31: =-([2]SME!$P$21+[2]SME!$W$21+[2]SME!$AV$21+[2]SME!$AY$21)/1000/AX27 -> 0 | AY31: =-([2]SME!$P$22+[2]SME!$W$22+[2]SME!$AV$22+[2]SME!$AY$22)/1000/AY27 -> 0 | AZ31: =-([2]SME!$P$23+[2]SME!$W$23+[2]SME!$AV$23+[2]SME!$AY$23)/1000/AZ27 -> 0 | BB31: =-([2]MidCorp!$P$21+[2]MidCorp!$W$21+[2]MidCorp!$AV$21+[2]MidCorp!$AY$21)/1000/BB27 -> 0 | BC31: =-([2]MidCorp!$P$22+[2]MidCorp!$W$22+[2]MidCorp!$AV$22+[2]MidCorp!$AY$22)/1000/BC27 -> 0 | BD31: =-([2]MidCorp!$P$23+[2]MidCorp!$W$23+[2]MidCorp!$AV$23+[2]MidCorp!$AY$23)/1000/BD27 -> 0 | BJ31: =-([2]Specials!$P$21+[2]Specials!$W$21+[2]Specials!$AV$21+[2]Specials!$AY$21)/1000/BJ27 -> #DIV/0! | BK31: =-([2]Specials!$P$22+[2]Specials!$W$22+[2]Specials!$AV$22+[2]Specials!$AY$22)/1000/BK27 -> #DIV/0! | BL31: =-([2]Specials!$P$23+[2]Specials!$W$23+[2]Specials!$AV$23+[2]Specials!$AY$23)/1000/BL27 -> #DIV/0! | BN31: =-('[2]Total P&C'!$P$21+'[2]Total P&C'!$W$21+'[2]Total P&C'!$AV$21+'[2]Total P&C'!$AY$21)/1000/BN27 -> 0 | BO31: =-('[2]Total P&C'!$P$22+'[2]Total P&C'!$W$22+'[2]Total P&C'!$AV$22+'[2]Total P&C'!$AY$22)/1000/BO27 -> 0 | BP31: =-('[2]Total P&C'!$P$23+'[2]Total P&C'!$W$23+'[2]Total P&C'!$AV$23+'[2]Total P&C'!$AY$23)/1000/BP27 -> 0 | BR31: =-('[3]Total P&C'!$P$21+'[3]Total P&C'!$W$21+'[3]Total P&C'!$AV$21+'[3]Total P&C'!$AY$21)/1000/BR27 -> 0 | BS31: =-('[3]Total P&C'!$P$22+'[3]Total P&C'!$W$22+'[3]Total P&C'!$AV$22+'[3]Total P&C'!$AY$22)/1000/BS27 -> 0 | BT31: =-('[3]Total P&C'!$P$23+'[3]Total P&C'!$W$23+'[3]Total P&C'!$AV$23+'[3]Total P&C'!$AY$23)/1000/BT27 -> 0
D32: Large Losses | J32: =-([1]Retail!$Q$21+[1]Retail!$X$21+[1]Retail!$AW$21+[1]Retail!$AZ$21)/1000/J27 -> 0 | K32: =-([1]Retail!$Q$22+[1]Retail!$X$22+[1]Retail!$AW$22+[1]Retail!$AZ$22)/1000/K27 -> 1.0869038 | L32: =-([1]Retail!$Q$23+[1]Retail!$X$23+[1]Retail!$AW$23+[1]Retail!$AZ$23)/1000/L27 -> #DIV/0! | N32: =-([1]SME!$Q$21+[1]SME!$X$21+[1]SME!$AW$21+[1]SME!$AZ$21)/1000/N27 -> 0.16660692 | O32: =-([1]SME!$Q$22+[1]SME!$X$22+[1]SME!$AW$22+[1]SME!$AZ$22)/1000/O27 -> 0.052724222 | P32: =-([1]SME!$Q$23+[1]SME!$X$23+[1]SME!$AW$23+[1]SME!$AZ$23)/1000/P27 -> 0.16353812 | R32: =-([1]MidCorp!$Q$21+[1]MidCorp!$X$21+[1]MidCorp!$AW$21+[1]MidCorp!$AZ$21)/1000/R27 -> 0.16243624 | S32: =-([1]MidCorp!$Q$22+[1]MidCorp!$X$22+[1]MidCorp!$AW$22+[1]MidCorp!$AZ$22)/1000/S27 -> 0.15594247 | T32: =-([1]MidCorp!$Q$23+[1]MidCorp!$X$23+[1]MidCorp!$AW$23+[1]MidCorp!$AZ$23)/1000/T27 -> 0.14581683 | V32: =-([1]MGA!$Q$21+[1]MGA!$X$21+[1]MGA!$AW$21+[1]MGA!$AZ$21)/1000/V27 -> 0.11584525 | W32: =-([1]MGA!$Q$22+[1]MGA!$X$22+[1]MGA!$AW$22+[1]MGA!$AZ$22)/1000/W27 -> 0.14913628 | X32: =-([1]MGA!$Q$23+[1]MGA!$X$23+[1]MGA!$AW$23+[1]MGA!$AZ$23)/1000/X27 -> 0.13797548 | Z32: =-([1]Bancassurance!$Q$21+[1]Bancassurance!$X$21+[1]Bancassurance!$AW$21+[1]Bancassurance!$AZ$21)/1000/Z27 -> #DIV/0! | AA32: =-([1]Bancassurance!$Q$22+[1]Bancassurance!$X$22+[1]Bancassurance!$AW$22+[1]Bancassurance!$AZ$22)/1000/AA27 -> #DIV/0! | AB32: =-([1]Bancassurance!$Q$23+[1]Bancassurance!$X$23+[1]Bancassurance!$AW$23+[1]Bancassurance!$AZ$23)/1000/AB27 -> #DIV/0! | AD32: =-([1]Specials!$Q$21+[1]Specials!$X$21+[1]Specials!$AW$21+[1]Specials!$AZ$21)/1000/AD27 -> 0 | AE32: =-([1]Specials!$Q$22+[1]Specials!$X$22+[1]Specials!$AW$22+[1]Specials!$AZ$22)/1000/AE27 -> 0 | AF32: =-([1]Specials!$Q$23+[1]Specials!$X$23+[1]Specials!$AW$23+[1]Specials!$AZ$23)/1000/AF27 -> #DIV/0! | AH32: =-('[1]Total P&C'!$Q$21+'[1]Total P&C'!$X$21+'[1]Total P&C'!$AW$21+'[1]Total P&C'!$AZ$21)/1000/AH27 -> 0.14969574 | AI32: =-('[1]Total P&C'!$Q$22+'[1]Total P&C'!$X$22+'[1]Total P&C'!$AW$22+'[1]Total P&C'!$AZ$22)/1000/AI27 -> 0.15919841 | AJ32: =-('[1]Total P&C'!$Q$23+'[1]Total P&C'!$X$23+'[1]Total P&C'!$AW$23+'[1]Total P&C'!$AZ$23)/1000/AJ27 -> 0.14608428 | AN32: Large Losses | AT32: =-([2]Retail!$Q$21+[2]Retail!$X$21+[2]Retail!$AW$21+[2]Retail!$AZ$21)/1000/AT27 -> 0.08667808 | AU32: =-([2]Retail!$Q$22+[2]Retail!$X$22+[2]Retail!$AW$22+[2]Retail!$AZ$22)/1000/AU27 -> 0.11188902 | AV32: =-([2]Retail!$Q$23+[2]Retail!$X$23+[2]Retail!$AW$23+[2]Retail!$AZ$23)/1000/AV27 -> 0.075900551 | AX32: =-([2]SME!$Q$21+[2]SME!$X$21+[2]SME!$AW$21+[2]SME!$AZ$21)/1000/AX27 -> 0.14188986 | AY32: =-([2]SME!$Q$22+[2]SME!$X$22+[2]SME!$AW$22+[2]SME!$AZ$22)/1000/AY27 -> 0.087137786 | AZ32: =-([2]SME!$Q$23+[2]SME!$X$23+[2]SME!$AW$23+[2]SME!$AZ$23)/1000/AZ27 -> 0.12885606 | BB32: =-([2]MidCorp!$Q$21+[2]MidCorp!$X$21+[2]MidCorp!$AW$21+[2]MidCorp!$AZ$21)/1000/BB27 -> 0.12822259 | BC32: =-([2]MidCorp!$Q$22+[2]MidCorp!$X$22+[2]MidCorp!$AW$22+[2]MidCorp!$AZ$22)/1000/BC27 -> 0.069567411 | BD32: =-([2]MidCorp!$Q$23+[2]MidCorp!$X$23+[2]MidCorp!$AW$23+[2]MidCorp!$AZ$23)/1000/BD27 -> 0.14862371 | BJ32: =-([2]Specials!$Q$21+[2]Specials!$X$21+[2]Specials!$AW$21+[2]Specials!$AZ$21)/1000/BJ27 -> #DIV/0! | BK32: =-([2]Specials!$Q$22+[2]Specials!$X$22+[2]Specials!$AW$22+[2]Specials!$AZ$22)/1000/BK27 -> #DIV/0! | BL32: =-([2]Specials!$Q$23+[2]Specials!$X$23+[2]Specials!$AW$23+[2]Specials!$AZ$23)/1000/BL27 -> #DIV/0! | BN32: =-('[2]Total P&C'!$Q$21+'[2]Total P&C'!$X$21+'[2]Total P&C'!$AW$21+'[2]Total P&C'!$AZ$21)/1000/BN27 -> 0.10711118 | BO32: =-('[2]Total P&C'!$Q$22+'[2]Total P&C'!$X$22+'[2]Total P&C'!$AW$22+'[2]Total P&C'!$AZ$22)/1000/BO27 -> 0.094620376 | BP32: =-('[2]Total P&C'!$Q$23+'[2]Total P&C'!$X$23+'[2]Total P&C'!$AW$23+'[2]Total P&C'!$AZ$23)/1000/BP27 -> 0.10383551 | BR32: =-('[3]Total P&C'!$Q$21+'[3]Total P&C'!$X$21+'[3]Total P&C'!$AW$21+'[3]Total P&C'!$AZ$21)/1000/BR27 -> 0.14247839 | BS32: =-('[3]Total P&C'!$Q$22+'[3]Total P&C'!$X$22+'[3]Total P&C'!$AW$22+'[3]Total P&C'!$AZ$22)/1000/BS27 -> 0.14677855 | BT32: =-('[3]Total P&C'!$Q$23+'[3]Total P&C'!$X$23+'[3]Total P&C'!$AW$23+'[3]Total P&C'!$AZ$23)/1000/BT27 -> 0.13800149
D33: Others | J33: =-[1]Retail!$AT$21/1000/J27 -> 0.071741742 | K33: =-[1]Retail!$AT$22/1000/K27 -> 0.089284006 | L33: =-[1]Retail!$AT$23/1000/L27 -> #DIV/0! | N33: =-[1]SME!$AT$21/1000/N27 -> 0.029559521 | O33: =-[1]SME!$AT$22/1000/O27 -> 0.029782536 | P33: =-[1]SME!$AT$23/1000/P27 -> 0.029305321 | R33: =-[1]MidCorp!$AT$21/1000/R27 -> 0.015212605 | S33: =-[1]MidCorp!$AT$22/1000/S27 -> 0.088506279 | T33: =-[1]MidCorp!$AT$23/1000/T27 -> 0.094603259 | V33: =-[1]MGA!$AT$21/1000/V27 -> 0.018456592 | W33: =-[1]MGA!$AT$22/1000/W27 -> 0.022770434 | X33: =-[1]MGA!$AT$23/1000/X27 -> 0.032489665 | Z33: =-[1]Bancassurance!$AT$21/1000/Z27 -> #DIV/0! | AA33: =-[1]Bancassurance!$AT$22/1000/AA27 -> #DIV/0! | AB33: =-[1]Bancassurance!$AT$23/1000/AB27 -> #DIV/0! | AD33: =-[1]Specials!$AT$21/1000/AD27 -> -4.2983718 | AE33: =-[1]Specials!$AT$22/1000/AE27 -> -20.780833 | AF33: =-[1]Specials!$AT$23/1000/AF27 -> #DIV/0! | AH33: =-'[1]Total P&C'!$AT$21/1000/AH27 -> 0.013889234 | AI33: =-'[1]Total P&C'!$AT$22/1000/AI27 -> 0.060899803 | AJ33: =-'[1]Total P&C'!$AT$23/1000/AJ27 -> 0.071267265 | AN33: Others | AT33: =-[2]Retail!$AT$21/1000/AT27 -> 0.025682692 | AU33: =-[2]Retail!$AT$22/1000/AU27 -> 0.085829504 | AV33: =-[2]Retail!$AT$23/1000/AV27 -> 0.042841856 | AX33: =-[2]SME!$AT$21/1000/AX27 -> 0.021888427 | AY33: =-[2]SME!$AT$22/1000/AY27 -> 0.027455795 | AZ33: =-[2]SME!$AT$23/1000/AZ27 -> 0.024564218 | BB33: =-[2]MidCorp!$AT$21/1000/BB27 -> 0.14567549 | BC33: =-[2]MidCorp!$AT$22/1000/BC27 -> 0.12354528 | BD33: =-[2]MidCorp!$AT$23/1000/BD27 -> 0.18104189 | BJ33: =-[2]Specials!$AT$21/1000/BJ27 -> #DIV/0! | BK33: =-[2]Specials!$AT$22/1000/BK27 -> #DIV/0! | BL33: =-[2]Specials!$AT$23/1000/BL27 -> #DIV/0! | BN33: =-'[2]Total P&C'!$AT$21/1000/BN27 -> 0.062579962 | BO33: =-'[2]Total P&C'!$AT$22/1000/BO27 -> 0.090106936 | BP33: =-'[2]Total P&C'!$AT$23/1000/BP27 -> 0.079663997 | BR33: =-'[3]Total P&C'!$AT$21/1000/BR27 -> 0.022141476 | BS33: =-'[3]Total P&C'!$AT$22/1000/BS27 -> 0.066517012 | BT33: =-'[3]Total P&C'!$AT$23/1000/BT27 -> 0.072873678
D34: Discounting a.y. | J34: =-([1]Retail!$Z$21+[1]Retail!$AA$21+[1]Retail!$BB$21+[1]Retail!$BC$21)/1000/J27 -> -0.015472374 | K34: =-([1]Retail!$Z$22+[1]Retail!$AA$22+[1]Retail!$BB$22+[1]Retail!$BC$22)/1000/K27 -> -0.13184524 | L34: =-([1]Retail!$Z$23+[1]Retail!$AA$23+[1]Retail!$BB$23+[1]Retail!$BC$23)/1000/L27 -> #DIV/0! | N34: =-([1]SME!$Z$21+[1]SME!$AA$21+[1]SME!$BB$21+[1]SME!$BC$21)/1000/N27 -> -0.075796827 | O34: =-([1]SME!$Z$22+[1]SME!$AA$22+[1]SME!$BB$22+[1]SME!$BC$22)/1000/O27 -> -0.039575467 | P34: =-([1]SME!$Z$23+[1]SME!$AA$23+[1]SME!$BB$23+[1]SME!$BC$23)/1000/P27 -> -0.047156561 | R34: =-([1]MidCorp!$Z$21+[1]MidCorp!$AA$21+[1]MidCorp!$BB$21+[1]MidCorp!$BC$21)/1000/R27 -> -0.078560315 | S34: =-([1]MidCorp!$Z$22+[1]MidCorp!$AA$22+[1]MidCorp!$BB$22+[1]MidCorp!$BC$22)/1000/S27 -> -0.060266971 | T34: =-([1]MidCorp!$Z$23+[1]MidCorp!$AA$23+[1]MidCorp!$BB$23+[1]MidCorp!$BC$23)/1000/T27 -> -0.041528755 | V34: =-([1]MGA!$Z$21+[1]MGA!$AA$21+[1]MGA!$BB$21+[1]MGA!$BC$21)/1000/V27 -> -0.050478888 | W34: =-([1]MGA!$Z$22+[1]MGA!$AA$22+[1]MGA!$BB$22+[1]MGA!$BC$22)/1000/W27 -> -0.054656905 | X34: =-([1]MGA!$Z$23+[1]MGA!$AA$23+[1]MGA!$BB$23+[1]MGA!$BC$23)/1000/X27 -> -0.053380922 | Z34: =-([1]Bancassurance!$Z$21+[1]Bancassurance!$AA$21+[1]Bancassurance!$BB$21+[1]Bancassurance!$BC$21)/1000/Z27 -> #DIV/0! | AA34: =-([1]Bancassurance!$Z$22+[1]Bancassurance!$AA$22+[1]Bancassurance!$BB$22+[1]Bancassurance!$BC$22)/1000/AA27 -> #DIV/0! | AB34: =-([1]Bancassurance!$Z$23+[1]Bancassurance!$AA$23+[1]Bancassurance!$BB$23+[1]Bancassurance!$BC$23)/1000/AB27 -> #DIV/0! | AD34: =-([1]Specials!$Z$21+[1]Specials!$AA$21+[1]Specials!$BB$21+[1]Specials!$BC$21)/1000/AD27 -> 0 | AE34: =-([1]Specials!$Z$22+[1]Specials!$AA$22+[1]Specials!$BB$22+[1]Specials!$BC$22)/1000/AE27 -> 0 | AF34: =-([1]Specials!$Z$23+[1]Specials!$AA$23+[1]Specials!$BB$23+[1]Specials!$BC$23)/1000/AF27 -> #DIV/0! | AH34: =-('[1]Total P&C'!$Z$21+'[1]Total P&C'!$AA$21+'[1]Total P&C'!$BB$21+'[1]Total P&C'!$BC$21)/1000/AH27 -> -0.070825975 | AI34: =-('[1]Total P&C'!$Z$22+'[1]Total P&C'!$AA$22+'[1]Total P&C'!$BB$22+'[1]Total P&C'!$BC$22)/1000/AI27 -> -0.057710793 | AJ34: =-('[1]Total P&C'!$Z$23+'[1]Total P&C'!$AA$23+'[1]Total P&C'!$BB$23+'[1]Total P&C'!$BC$23)/1000/AJ27 -> -0.045136059 | AN34: Discounting a.y. | AT34: =-([2]Retail!$Z$21+[2]Retail!$AA$21+[2]Retail!$BB$21+[2]Retail!$BC$21)/1000/AT27 -> -0.070867505 | AU34: =-([2]Retail!$Z$22+[2]Retail!$AA$22+[2]Retail!$BB$22+[2]Retail!$BC$22)/1000/AU27 -> -0.047850724 | AV34: =-([2]Retail!$Z$23+[2]Retail!$AA$23+[2]Retail!$BB$23+[2]Retail!$BC$23)/1000/AV27 -> -0.028314205 | AX34: =-([2]SME!$Z$21+[2]SME!$AA$21+[2]SME!$BB$21+[2]SME!$BC$21)/1000/AX27 -> -0.067103397 | AY34: =-([2]SME!$Z$22+[2]SME!$AA$22+[2]SME!$BB$22+[2]SME!$BC$22)/1000/AY27 -> -0.043646913 | AZ34: =-([2]SME!$Z$23+[2]SME!$AA$23+[2]SME!$BB$23+[2]SME!$BC$23)/1000/AZ27 -> -0.041114826 | BB34: =-([2]MidCorp!$Z$21+[2]MidCorp!$AA$21+[2]MidCorp!$BB$21+[2]MidCorp!$BC$21)/1000/BB27 -> -0.099006564 | BC34: =-([2]MidCorp!$Z$22+[2]MidCorp!$AA$22+[2]MidCorp!$BB$22+[2]MidCorp!$BC$22)/1000/BC27 -> -0.06452052 | BD34: =-([2]MidCorp!$Z$23+[2]MidCorp!$AA$23+[2]MidCorp!$BB$23+[2]MidCorp!$BC$23)/1000/BD27 -> -0.046732469 | BJ34: =-([2]Specials!$Z$21+[2]Specials!$AA$21+[2]Specials!$BB$21+[2]Specials!$BC$21)/1000/BJ27 -> #DIV/0! | BK34: =-([2]Specials!$Z$22+[2]Specials!$AA$22+[2]Specials!$BB$22+[2]Specials!$BC$22)/1000/BK27 -> #DIV/0! | BL34: =-([2]Specials!$Z$23+[2]Specials!$AA$23+[2]Specials!$BB$23+[2]Specials!$BC$23)/1000/BL27 -> #DIV/0! | BN34: =-('[2]Total P&C'!$Z$21+'[2]Total P&C'!$AA$21+'[2]Total P&C'!$BB$21+'[2]Total P&C'!$BC$21)/1000/BN27 -> -0.079130718 | BO34: =-('[2]Total P&C'!$Z$22+'[2]Total P&C'!$AA$22+'[2]Total P&C'!$BB$22+'[2]Total P&C'!$BC$22)/1000/BO27 -> -0.052724916 | BP34: =-('[2]Total P&C'!$Z$23+'[2]Total P&C'!$AA$23+'[2]Total P&C'!$BB$23+'[2]Total P&C'!$BC$23)/1000/BP27 -> -0.03530557 | BR34: =-('[3]Total P&C'!$Z$21+'[3]Total P&C'!$AA$21+'[3]Total P&C'!$BB$21+'[3]Total P&C'!$BC$21)/1000/BR27 -> -0.072233486 | BS34: =-('[3]Total P&C'!$Z$22+'[3]Total P&C'!$AA$22+'[3]Total P&C'!$BB$22+'[3]Total P&C'!$BC$22)/1000/BS27 -> -0.056751893 | BT34: =-('[3]Total P&C'!$Z$23+'[3]Total P&C'!$AA$23+'[3]Total P&C'!$BB$23+'[3]Total P&C'!$BC$23)/1000/BT27 -> -0.043255349
D35: Run-off + ReR | J35: =-SUM([1]Retail!$AC$21:$AI$21,[1]Retail!$BE$21:$BG$21)/1000/J27 -> -0.012031882 | K35: =-SUM([1]Retail!$AC$22:$AI$22,[1]Retail!$BE$22:$BG$22)/1000/K27 -> -2.3470068 | L35: =-SUM([1]Retail!$AC$23:$AI$23,[1]Retail!$BE$23:$BG$23)/1000/L27 -> #DIV/0! | N35: =-SUM([1]SME!$AC$21:$AI$21,[1]SME!$BE$21:$BG$21)/1000/N27 -> -0.22962266 | O35: =-SUM([1]SME!$AC$22:$AI$22,[1]SME!$BE$22:$BG$22)/1000/O27 -> 0.36564668 | P35: =-SUM([1]SME!$AC$23:$AI$23,[1]SME!$BE$23:$BG$23)/1000/P27 -> -0.012013091 | R35: =-SUM([1]MidCorp!$AC$21:$AI$21,[1]MidCorp!$BE$21:$BG$21)/1000/R27 -> 0.067722703 | S35: =-SUM([1]MidCorp!$AC$22:$AI$22,[1]MidCorp!$BE$22:$BG$22)/1000/S27 -> 0.018604199 | T35: =-SUM([1]MidCorp!$AC$23:$AI$23,[1]MidCorp!$BE$23:$BG$23)/1000/T27 -> -0.0065116679 | V35: =-SUM([1]MGA!$AC$21:$AI$21,[1]MGA!$BE$21:$BG$21)/1000/V27 -> -0.086719563 | W35: =-SUM([1]MGA!$AC$22:$AI$22,[1]MGA!$BE$22:$BG$22)/1000/W27 -> 0.027704834 | X35: =-SUM([1]MGA!$AC$23:$AI$23,[1]MGA!$BE$23:$BG$23)/1000/X27 -> -0.019818285 | Z35: =-SUM([1]Bancassurance!$AC$21:$AI$21,[1]Bancassurance!$BE$21:$BG$21)/1000/Z27 -> #DIV/0! | AA35: =-SUM([1]Bancassurance!$AC$22:$AI$22,[1]Bancassurance!$BE$22:$BG$22)/1000/AA27 -> #DIV/0! | AB35: =-SUM([1]Bancassurance!$AC$23:$AI$23,[1]Bancassurance!$BE$23:$BG$23)/1000/AB27 -> #DIV/0! | AD35: =-SUM([1]Specials!$AC$21:$AI$21,[1]Specials!$BE$21:$BG$21)/1000/AD27 -> -2.386652 | AE35: =-SUM([1]Specials!$AC$22:$AI$22,[1]Specials!$BE$22:$BG$22)/1000/AE27 -> -7.2112109 | AF35: =-SUM([1]Specials!$AC$23:$AI$23,[1]Specials!$BE$23:$BG$23)/1000/AF27 -> #DIV/0! | AH35: =-SUM('[1]Total P&C'!$AC$21:$AI$21,'[1]Total P&C'!$BE$21:$BG$21)/1000/AH27 -> -0.0036350277 | AI35: =-SUM('[1]Total P&C'!$AC$22:$AI$22,'[1]Total P&C'!$BE$22:$BG$22)/1000/AI27 -> 0.017476957 | AJ35: =-SUM('[1]Total P&C'!$AC$23:$AI$23,'[1]Total P&C'!$BE$23:$BG$23)/1000/AJ27 -> -0.018606458 | AN35: Run-off + ReR | AT35: =-SUM([2]Retail!$AC$21:$AI$21,[2]Retail!$BE$21:$BG$21)/1000/AT27 -> 0.8621719 | AU35: =-SUM([2]Retail!$AC$22:$AI$22,[2]Retail!$BE$22:$BG$22)/1000/AU27 -> -0.46627131 | AV35: =-SUM([2]Retail!$AC$23:$AI$23,[2]Retail!$BE$23:$BG$23)/1000/AV27 -> 0.011529881 | AX35: =-SUM([2]SME!$AC$21:$AI$21,[2]SME!$BE$21:$BG$21)/1000/AX27 -> 1.0539225 | AY35: =-SUM([2]SME!$AC$22:$AI$22,[2]SME!$BE$22:$BG$22)/1000/AY27 -> 0.2054628 | AZ35: =-SUM([2]SME!$AC$23:$AI$23,[2]SME!$BE$23:$BG$23)/1000/AZ27 -> 0.080604558 | BB35: =-SUM([2]MidCorp!$AC$21:$AI$21,[2]MidCorp!$BE$21:$BG$21)/1000/BB27 -> 0.28833246 | BC35: =-SUM([2]MidCorp!$AC$22:$AI$22,[2]MidCorp!$BE$22:$BG$22)/1000/BC27 -> 0.58191422 | BD35: =-SUM([2]MidCorp!$AC$23:$AI$23,[2]MidCorp!$BE$23:$BG$23)/1000/BD27 -> 0.032509584 | BJ35: =-SUM([2]Specials!$AC$21:$AI$21,[2]Specials!$BE$21:$BG$21)/1000/BJ27 -> #DIV/0! | BK35: =-SUM([2]Specials!$AC$22:$AI$22,[2]Specials!$BE$22:$BG$22)/1000/BK27 -> #DIV/0! | BL35: =-SUM([2]Specials!$AC$23:$AI$23,[2]Specials!$BE$23:$BG$23)/1000/BL27 -> #DIV/0! | BN35: =-SUM('[2]Total P&C'!$AC$21:$AI$21,'[2]Total P&C'!$BE$21:$BG$21)/1000/BN27 -> 0.70923961 | BO35: =-SUM('[2]Total P&C'!$AC$22:$AI$22,'[2]Total P&C'!$BE$22:$BG$22)/1000/BO27 -> -0.030464328 | BP35: =-SUM('[2]Total P&C'!$AC$23:$AI$23,'[2]Total P&C'!$BE$23:$BG$23)/1000/BP27 -> 0.026946974 | BR35: =-SUM('[3]Total P&C'!$AC$21:$AI$21,'[3]Total P&C'!$BE$21:$BG$21)/1000/BR27 -> 0.11718498 | BS35: =-SUM('[3]Total P&C'!$AC$22:$AI$22,'[3]Total P&C'!$BE$22:$BG$22)/1000/BS27 -> 0.0082567359 | BT35: =-SUM('[3]Total P&C'!$AC$23:$AI$23,'[3]Total P&C'!$BE$23:$BG$23)/1000/BT27 -> -0.0098914467
D36: Discounting Run-off | J36: =-SUM([1]Retail!$AJ$21:$AK$21,[1]Retail!$BH$21:$BI$21)/1000/J27 -> 0.54165483 | K36: =-SUM([1]Retail!$AJ$22:$AK$22,[1]Retail!$BH$22:$BI$22)/1000/K27 -> 0.10130468 | L36: =-SUM([1]Retail!$AJ$23:$AK$23,[1]Retail!$BH$23:$BI$23)/1000/L27 -> #DIV/0! | N36: =-SUM([1]SME!$AJ$21:$AK$21,[1]SME!$BH$21:$BI$21)/1000/N27 -> -0.020324317 | O36: =-SUM([1]SME!$AJ$22:$AK$22,[1]SME!$BH$22:$BI$22)/1000/O27 -> -0.03711735 | P36: =-SUM([1]SME!$AJ$23:$AK$23,[1]SME!$BH$23:$BI$23)/1000/P27 -> 0 | R36: =-SUM([1]MidCorp!$AJ$21:$AK$21,[1]MidCorp!$BH$21:$BI$21)/1000/R27 -> -0.0092451886 | S36: =-SUM([1]MidCorp!$AJ$22:$AK$22,[1]MidCorp!$BH$22:$BI$22)/1000/S27 -> 0.0322151 | T36: =-SUM([1]MidCorp!$AJ$23:$AK$23,[1]MidCorp!$BH$23:$BI$23)/1000/T27 -> 0 | V36: =-SUM([1]MGA!$AJ$21:$AK$21,[1]MGA!$BH$21:$BI$21)/1000/V27 -> 0.21711591 | W36: =-SUM([1]MGA!$AJ$22:$AK$22,[1]MGA!$BH$22:$BI$22)/1000/W27 -> -0.14936543 | X36: =-SUM([1]MGA!$AJ$23:$AK$23,[1]MGA!$BH$23:$BI$23)/1000/X27 -> 0 | Z36: =-SUM([1]Bancassurance!$AJ$21:$AK$21,[1]Bancassurance!$BH$21:$BI$21)/1000/Z27 -> #DIV/0! | AA36: =-SUM([1]Bancassurance!$AJ$22:$AK$22,[1]Bancassurance!$BH$22:$BI$22)/1000/AA27 -> #DIV/0! | AB36: =-SUM([1]Bancassurance!$AJ$23:$AK$23,[1]Bancassurance!$BH$23:$BI$23)/1000/AB27 -> #DIV/0! | AD36: =-SUM([1]Specials!$AJ$21:$AK$21,[1]Specials!$BH$21:$BI$21)/1000/AD27 -> 0.520557 | AE36: =-SUM([1]Specials!$AJ$22:$AK$22,[1]Specials!$BH$22:$BI$22)/1000/AE27 -> -2.412036 | AF36: =-SUM([1]Specials!$AJ$23:$AK$23,[1]Specials!$BH$23:$BI$23)/1000/AF27 -> #DIV/0! | AH36: =-SUM('[1]Total P&C'!$AJ$21:$AK$21,'[1]Total P&C'!$BH$21:$BI$21)/1000/AH27 -> 0.049985949 | AI36: =-SUM('[1]Total P&C'!$AJ$22:$AK$22,'[1]Total P&C'!$BH$22:$BI$22)/1000/AI27 -> -0.0172309 | AJ36: =-SUM('[1]Total P&C'!$AJ$23:$AK$23,'[1]Total P&C'!$BH$23:$BI$23)/1000/AJ27 -> 0 | AN36: Discounting Run-off | AT36: =-SUM([2]Retail!$AJ$21:$AK$21,[2]Retail!$BH$21:$BI$21)/1000/AT27 -> -1.0356632 | AU36: =-SUM([2]Retail!$AJ$22:$AK$22,[2]Retail!$BH$22:$BI$22)/1000/AU27 -> -0.063613769 | AV36: =-SUM([2]Retail!$AJ$23:$AK$23,[2]Retail!$BH$23:$BI$23)/1000/AV27 -> 0 | AX36: =-SUM([2]SME!$AJ$21:$AK$21,[2]SME!$BH$21:$BI$21)/1000/AX27 -> -1.2515667 | AY36: =-SUM([2]SME!$AJ$22:$AK$22,[2]SME!$BH$22:$BI$22)/1000/AY27 -> -0.11453123 | AZ36: =-SUM([2]SME!$AJ$23:$AK$23,[2]SME!$BH$23:$BI$23)/1000/AZ27 -> 0 | BB36: =-SUM([2]MidCorp!$AJ$21:$AK$21,[2]MidCorp!$BH$21:$BI$21)/1000/BB27 -> -0.55750516 | BC36: =-SUM([2]MidCorp!$AJ$22:$AK$22,[2]MidCorp!$BH$22:$BI$22)/1000/BC27 -> -0.021663033 | BD36: =-SUM([2]MidCorp!$AJ$23:$AK$23,[2]MidCorp!$BH$23:$BI$23)/1000/BD27 -> 0 | BJ36: =-SUM([2]Specials!$AJ$21:$AK$21,[2]Specials!$BH$21:$BI$21)/1000/BJ27 -> #DIV/0! | BK36: =-SUM([2]Specials!$AJ$22:$AK$22,[2]Specials!$BH$22:$BI$22)/1000/BK27 -> #DIV/0! | BL36: =-SUM([2]Specials!$AJ$23:$AK$23,[2]Specials!$BH$23:$BI$23)/1000/BL27 -> #DIV/0! | BN36: =-SUM('[2]Total P&C'!$AJ$21:$AK$21,'[2]Total P&C'!$BH$21:$BI$21)/1000/BN27 -> -0.91583478 | BO36: =-SUM('[2]Total P&C'!$AJ$22:$AK$22,'[2]Total P&C'!$BH$22:$BI$22)/1000/BO27 -> -0.056920396 | BP36: =-SUM('[2]Total P&C'!$AJ$23:$AK$23,'[2]Total P&C'!$BH$23:$BI$23)/1000/BP27 -> 0 | BR36: =-SUM('[3]Total P&C'!$AJ$21:$AK$21,'[3]Total P&C'!$BH$21:$BI$21)/1000/BR27 -> -0.11370408 | BS36: =-SUM('[3]Total P&C'!$AJ$22:$AK$22,'[3]Total P&C'!$BH$22:$BI$22)/1000/BS27 -> -0.024864111 | BT36: =-SUM('[3]Total P&C'!$AJ$23:$AK$23,'[3]Total P&C'!$BH$23:$BI$23)/1000/BT27 -> 0
D37: Expense ratio + ReR | J37: =+J38+J39+J40 -> 0.33973605 | K37: =+K38+K39+K40 -> 0.49807259 | L37: =+L38+L39+L40 -> #DIV/0! | N37: =+N38+N39+N40 -> 0.28497318 | O37: =+O38+O39+O40 -> 0.29148457 | P37: =+P38+P39+P40 -> 0.29388095 | R37: =+R38+R39+R40 -> 0.15189385 | S37: =+S38+S39+S40 -> 0.15253189 | T37: =+T38+T39+T40 -> 0.18264888 | V37: =+V38+V39+V40 -> 0.3321712 | W37: =+W38+W39+W40 -> 0.32016761 | X37: =+X38+X39+X40 -> 0.32418358 | Z37: =+Z38+Z39+Z40 -> #DIV/0! | AA37: =+AA38+AA39+AA40 -> #DIV/0! | AB37: =+AB38+AB39+AB40 -> #DIV/0! | AD37: =+AD38+AD39+AD40 -> 0 | AE37: =+AE38+AE39+AE40 -> 0 | AF37: =+AF38+AF39+AF40 -> #DIV/0! | AH37: =+AH38+AH39+AH40 -> 0.21026741 | AI37: =+AI38+AI39+AI40 -> 0.21537659 | AJ37: =+AJ38+AJ39+AJ40 -> 0.23325093 | AN37: Expense ratio + ReR | AT37: =+AT38+AT39+AT40 -> 0.33098667 | AU37: =+AU38+AU39+AU40 -> 0.3211374 | AV37: =+AV38+AV39+AV40 -> 0.32075949 | AX37: =+AX38+AX39+AX40 -> 0.39551654 | AY37: =+AY38+AY39+AY40 -> 0.37070956 | AZ37: =+AZ38+AZ39+AZ40 -> 0.40542682 | BB37: =+BB38+BB39+BB40 -> 0.25130029 | BC37: =+BC38+BC39+BC40 -> 0.23418621 | BD37: =+BD38+BD39+BD40 -> 0.27295418 | BJ37: =+BJ38+BJ39+BJ40 -> #DIV/0! | BK37: =+BK38+BK39+BK40 -> #DIV/0! | BL37: =+BL38+BL39+BL40 -> #DIV/0! | BN37: =+BN38+BN39+BN40 -> 0.31488488 | BO37: =+BO38+BO39+BO40 -> 0.29953239 | BP37: =+BP38+BP39+BP40 -> 0.31873787 | BR37: =+BR38+BR39+BR40 -> 0.22799827 | BS37: =+BS38+BS39+BS40 -> 0.2315617 | BT37: =+BT38+BT39+BT40 -> 0.24960578
D38: Commission | J38: =-SUM([1]Retail!$AL$21:$AN$21,[1]Retail!$BJ$21)/1000/J27 -> 0.18274192 | K38: =-SUM([1]Retail!$AL$22:$AN$22,[1]Retail!$BJ$22)/1000/K27 -> 0.18583854 | L38: =-SUM([1]Retail!$AL$23:$AN$23,[1]Retail!$BJ$23)/1000/L27 -> #DIV/0! | N38: =-SUM([1]SME!$AL$21:$AN$21,[1]SME!$BJ$21)/1000/N27 -> 0.16064757 | O38: =-SUM([1]SME!$AL$22:$AN$22,[1]SME!$BJ$22)/1000/O27 -> 0.16040258 | P38: =-SUM([1]SME!$AL$23:$AN$23,[1]SME!$BJ$23)/1000/P27 -> 0.16010288 | R38: =-SUM([1]MidCorp!$AL$21:$AN$21,[1]MidCorp!$BJ$21)/1000/R27 -> 0.07311555 | S38: =-SUM([1]MidCorp!$AL$22:$AN$22,[1]MidCorp!$BJ$22)/1000/S27 -> 0.077310611 | T38: =-SUM([1]MidCorp!$AL$23:$AN$23,[1]MidCorp!$BJ$23)/1000/T27 -> 0.078420769 | V38: =-SUM([1]MGA!$AL$21:$AN$21,[1]MGA!$BJ$21)/1000/V27 -> 0.27561797 | W38: =-SUM([1]MGA!$AL$22:$AN$22,[1]MGA!$BJ$22)/1000/W27 -> 0.26145882 | X38: =-SUM([1]MGA!$AL$23:$AN$23,[1]MGA!$BJ$23)/1000/X27 -> 0.2502246 | Z38: =-SUM([1]Bancassurance!$AL$21:$AN$21,[1]Bancassurance!$BJ$21)/1000/Z27 -> #DIV/0! | AA38: =-SUM([1]Bancassurance!$AL$22:$AN$22,[1]Bancassurance!$BJ$22)/1000/AA27 -> #DIV/0! | AB38: =-SUM([1]Bancassurance!$AL$23:$AN$23,[1]Bancassurance!$BJ$23)/1000/AB27 -> #DIV/0! | AD38: =-SUM([1]Specials!$AL$21:$AN$21,[1]Specials!$BJ$21)/1000/AD27 -> 0 | AE38: =-SUM([1]Specials!$AL$22:$AN$22,[1]Specials!$BJ$22)/1000/AE27 -> 0 | AF38: =-SUM([1]Specials!$AL$23:$AN$23,[1]Specials!$BJ$23)/1000/AF27 -> #DIV/0! | AH38: =-SUM('[1]Total P&C'!$AL$21:$AN$21,'[1]Total P&C'!$BJ$21)/1000/AH27 -> 0.13063192 | AI38: =-SUM('[1]Total P&C'!$AL$22:$AN$22,'[1]Total P&C'!$BJ$22)/1000/AI27 -> 0.13193993 | AJ38: =-SUM('[1]Total P&C'!$AL$23:$AN$23,'[1]Total P&C'!$BJ$23)/1000/AJ27 -> 0.13072353 | AN38: Commission | AT38: =-SUM([2]Retail!$AL$21:$AN$21,[2]Retail!$BJ$21)/1000/AT27 -> 0.15825847 | AU38: =-SUM([2]Retail!$AL$22:$AN$22,[2]Retail!$BJ$22)/1000/AU27 -> 0.15784161 | AV38: =-SUM([2]Retail!$AL$23:$AN$23,[2]Retail!$BJ$23)/1000/AV27 -> 0.16129475 | AX38: =-SUM([2]SME!$AL$21:$AN$21,[2]SME!$BJ$21)/1000/AX27 -> 0.189742 | AY38: =-SUM([2]SME!$AL$22:$AN$22,[2]SME!$BJ$22)/1000/AY27 -> 0.18242051 | AZ38: =-SUM([2]SME!$AL$23:$AN$23,[2]SME!$BJ$23)/1000/AZ27 -> 0.20675853 | BB38: =-SUM([2]MidCorp!$AL$21:$AN$21,[2]MidCorp!$BJ$21)/1000/BB27 -> 0.077933844 | BC38: =-SUM([2]MidCorp!$AL$22:$AN$22,[2]MidCorp!$BJ$22)/1000/BC27 -> 0.093396543 | BD38: =-SUM([2]MidCorp!$AL$23:$AN$23,[2]MidCorp!$BJ$23)/1000/BD27 -> 0.089350006 | BJ38: =-SUM([2]Specials!$AL$21:$AN$21,[2]Specials!$BJ$21)/1000/BJ27 -> #DIV/0! | BK38: =-SUM([2]Specials!$AL$22:$AN$22,[2]Specials!$BJ$22)/1000/BK27 -> #DIV/0! | BL38: =-SUM([2]Specials!$AL$23:$AN$23,[2]Specials!$BJ$23)/1000/BL27 -> #DIV/0! | BN38: =-SUM('[2]Total P&C'!$AL$21:$AN$21,'[2]Total P&C'!$BJ$21)/1000/BN27 -> 0.13748041 | BO38: =-SUM('[2]Total P&C'!$AL$22:$AN$22,'[2]Total P&C'!$BJ$22)/1000/BO27 -> 0.14014851 | BP38: =-SUM('[2]Total P&C'!$AL$23:$AN$23,'[2]Total P&C'!$BJ$23)/1000/BP27 -> 0.14704264 | BR38: =-SUM('[3]Total P&C'!$AL$21:$AN$21,'[3]Total P&C'!$BJ$21)/1000/BR27 -> 0.13179262 | BS38: =-SUM('[3]Total P&C'!$AL$22:$AN$22,'[3]Total P&C'!$BJ$22)/1000/BS27 -> 0.13351863 | BT38: =-SUM('[3]Total P&C'!$AL$23:$AN$23,'[3]Total P&C'!$BJ$23)/1000/BT27 -> 0.13384561
D39: Acquisition | J39: =-SUM([1]Retail!$AO$21:$AP$21)/1000/J27 -> 0.0045037597 | K39: =-SUM([1]Retail!$AO$22:$AP$22)/1000/K27 -> 0.0414057 | L39: =-SUM([1]Retail!$AO$23:$AP$23)/1000/L27 -> #DIV/0! | N39: =-SUM([1]SME!$AO$21:$AP$21)/1000/N27 -> 0.058258091 | O39: =-SUM([1]SME!$AO$22:$AP$22)/1000/O27 -> 0.064810347 | P39: =-SUM([1]SME!$AO$23:$AP$23)/1000/P27 -> 0.056569734 | R39: =-SUM([1]MidCorp!$AO$21:$AP$21)/1000/R27 -> 0.012610229 | S39: =-SUM([1]MidCorp!$AO$22:$AP$22)/1000/S27 -> 0.0036881021 | T39: =-SUM([1]MidCorp!$AO$23:$AP$23)/1000/T27 -> 0.015156603 | V39: =-SUM([1]MGA!$AO$21:$AP$21)/1000/V27 -> 0.018563897 | W39: =-SUM([1]MGA!$AO$22:$AP$22)/1000/W27 -> 0.014226736 | X39: =-SUM([1]MGA!$AO$23:$AP$23)/1000/X27 -> 0.023885843 | Z39: =-SUM([1]Bancassurance!$AO$21:$AP$21)/1000/Z27 -> #DIV/0! | AA39: =-SUM([1]Bancassurance!$AO$22:$AP$22)/1000/AA27 -> #DIV/0! | AB39: =-SUM([1]Bancassurance!$AO$23:$AP$23)/1000/AB27 -> #DIV/0! | AD39: =-SUM([1]Specials!$AO$21:$AP$21)/1000/AD27 -> 0 | AE39: =-SUM([1]Specials!$AO$22:$AP$22)/1000/AE27 -> 0 | AF39: =-SUM([1]Specials!$AO$23:$AP$23)/1000/AF27 -> #DIV/0! | AH39: =-SUM('[1]Total P&C'!$AO$21:$AP$21)/1000/AH27 -> 0.018793437 | AI39: =-SUM('[1]Total P&C'!$AO$22:$AP$22)/1000/AI27 -> 0.01485187 | AJ39: =-SUM('[1]Total P&C'!$AO$23:$AP$23)/1000/AJ27 -> 0.022491013 | AN39: Acquisition | AT39: =-SUM([2]Retail!$AO$21:$AP$21)/1000/AT27 -> 0.093342372 | AU39: =-SUM([2]Retail!$AO$22:$AP$22)/1000/AU27 -> 0.088115757 | AV39: =-SUM([2]Retail!$AO$23:$AP$23)/1000/AV27 -> 0.084406088 | AX39: =-SUM([2]SME!$AO$21:$AP$21)/1000/AX27 -> 0.1043108 | AY39: =-SUM([2]SME!$AO$22:$AP$22)/1000/AY27 -> 0.093510636 | AZ39: =-SUM([2]SME!$AO$23:$AP$23)/1000/AZ27 -> 0.088771698 | BB39: =-SUM([2]MidCorp!$AO$21:$AP$21)/1000/BB27 -> 0.072825562 | BC39: =-SUM([2]MidCorp!$AO$22:$AP$22)/1000/BC27 -> 0.054055407 | BD39: =-SUM([2]MidCorp!$AO$23:$AP$23)/1000/BD27 -> 0.069449491 | BJ39: =-SUM([2]Specials!$AO$21:$AP$21)/1000/BJ27 -> #DIV/0! | BK39: =-SUM([2]Specials!$AO$22:$AP$22)/1000/BK27 -> #DIV/0! | BL39: =-SUM([2]Specials!$AO$23:$AP$23)/1000/BL27 -> #DIV/0! | BN39: =-SUM('[2]Total P&C'!$AO$21:$AP$21)/1000/BN27 -> 0.088431699 | BO39: =-SUM('[2]Total P&C'!$AO$22:$AP$22)/1000/BO27 -> 0.077715293 | BP39: =-SUM('[2]Total P&C'!$AO$23:$AP$23)/1000/BP27 -> 0.080747595 | BR39: =-SUM('[3]Total P&C'!$AO$21:$AP$21)/1000/BR27 -> 0.030595927 | BS39: =-SUM('[3]Total P&C'!$AO$22:$AP$22)/1000/BS27 -> 0.026941965 | BT39: =-SUM('[3]Total P&C'!$AO$23:$AP$23)/1000/BT27 -> 0.033636316
D40: Administration | J40: =-SUM([1]Retail!$AQ$21:$AR$21)/1000/J27 -> 0.15249037 | K40: =-SUM([1]Retail!$AQ$22:$AR$22)/1000/K27 -> 0.27082835 | L40: =-SUM([1]Retail!$AQ$23:$AR$23)/1000/L27 -> #DIV/0! | N40: =-SUM([1]SME!$AQ$21:$AR$21)/1000/N27 -> 0.066067518 | O40: =-SUM([1]SME!$AQ$22:$AR$22)/1000/O27 -> 0.066271639 | P40: =-SUM([1]SME!$AQ$23:$AR$23)/1000/P27 -> 0.077208341 | R40: =-SUM([1]MidCorp!$AQ$21:$AR$21)/1000/R27 -> 0.066168068 | S40: =-SUM([1]MidCorp!$AQ$22:$AR$22)/1000/S27 -> 0.07153318 | T40: =-SUM([1]MidCorp!$AQ$23:$AR$23)/1000/T27 -> 0.089071507 | V40: =-SUM([1]MGA!$AQ$21:$AR$21)/1000/V27 -> 0.037989331 | W40: =-SUM([1]MGA!$AQ$22:$AR$22)/1000/W27 -> 0.044482057 | X40: =-SUM([1]MGA!$AQ$23:$AR$23)/1000/X27 -> 0.050073133 | Z40: =-SUM([1]Bancassurance!$AQ$21:$AR$21)/1000/Z27 -> #DIV/0! | AA40: =-SUM([1]Bancassurance!$AQ$22:$AR$22)/1000/AA27 -> #DIV/0! | AB40: =-SUM([1]Bancassurance!$AQ$23:$AR$23)/1000/AB27 -> #DIV/0! | AD40: =-SUM([1]Specials!$AQ$21:$AR$21)/1000/AD27 -> 0 | AE40: =-SUM([1]Specials!$AQ$22:$AR$22)/1000/AE27 -> 0 | AF40: =-SUM([1]Specials!$AQ$23:$AR$23)/1000/AF27 -> #DIV/0! | AH40: =-SUM('[1]Total P&C'!$AQ$21:$AR$21)/1000/AH27 -> 0.06084205 | AI40: =-SUM('[1]Total P&C'!$AQ$22:$AR$22)/1000/AI27 -> 0.068584787 | AJ40: =-SUM('[1]Total P&C'!$AQ$23:$AR$23)/1000/AJ27 -> 0.08003638 | AN40: Administration | AT40: =-SUM([2]Retail!$AQ$21:$AR$21)/1000/AT27 -> 0.079385834 | AU40: =-SUM([2]Retail!$AQ$22:$AR$22)/1000/AU27 -> 0.075180033 | AV40: =-SUM([2]Retail!$AQ$23:$AR$23)/1000/AV27 -> 0.075058653 | AX40: =-SUM([2]SME!$AQ$21:$AR$21)/1000/AX27 -> 0.10146374 | AY40: =-SUM([2]SME!$AQ$22:$AR$22)/1000/AY27 -> 0.094778411 | AZ40: =-SUM([2]SME!$AQ$23:$AR$23)/1000/AZ27 -> 0.10989658 | BB40: =-SUM([2]MidCorp!$AQ$21:$AR$21)/1000/BB27 -> 0.10054088 | BC40: =-SUM([2]MidCorp!$AQ$22:$AR$22)/1000/BC27 -> 0.086734262 | BD40: =-SUM([2]MidCorp!$AQ$23:$AR$23)/1000/BD27 -> 0.11415468 | BJ40: =-SUM([2]Specials!$AQ$21:$AR$21)/1000/BJ27 -> #DIV/0! | BK40: =-SUM([2]Specials!$AQ$22:$AR$22)/1000/BK27 -> #DIV/0! | BL40: =-SUM([2]Specials!$AQ$23:$AR$23)/1000/BL27 -> #DIV/0! | BN40: =-SUM('[2]Total P&C'!$AQ$21:$AR$21)/1000/BN27 -> 0.088972772 | BO40: =-SUM('[2]Total P&C'!$AQ$22:$AR$22)/1000/BO27 -> 0.081668585 | BP40: =-SUM('[2]Total P&C'!$AQ$23:$AR$23)/1000/BP27 -> 0.090947633 | BR40: =-SUM('[3]Total P&C'!$AQ$21:$AR$21)/1000/BR27 -> 0.065609724 | BS40: =-SUM('[3]Total P&C'!$AQ$22:$AR$22)/1000/BS27 -> 0.071101105 | BT40: =-SUM('[3]Total P&C'!$AQ$23:$AR$23)/1000/BT27 -> 0.082123856
D41: Insurance Service Result | J41: =+[1]Retail!$BK$21/1000 -> -0.0165845 | K41: =+[1]Retail!$BK$22/1000 -> 0.82748312 | L41: =+[1]Retail!$BK$23/1000 -> 0.3142079 | N41: =+[1]SME!$BK$21/1000 -> -0.07412734 | O41: =+[1]SME!$BK$22/1000 -> -2.0475835 | P41: =+[1]SME!$BK$23/1000 -> -0.71505008 | R41: =+[1]MidCorp!$BK$21/1000 -> -0.20648243 | S41: =+[1]MidCorp!$BK$22/1000 -> 0.94484761 | T41: =+[1]MidCorp!$BK$23/1000 -> 0.15265465 | V41: =+[1]MGA!$BK$21/1000 -> -3.3962158 | W41: =+[1]MGA!$BK$22/1000 -> 1.1090374 | X41: =+[1]MGA!$BK$23/1000 -> -0.54097592 | Z41: =+[1]Bancassurance!$BK$21/1000 -> 0 | AA41: =+[1]Bancassurance!$BK$22/1000 -> -0.01245234 | AB41: =+[1]Bancassurance!$BK$23/1000 -> 0 | AD41: =+[1]Specials!$BK$21/1000 -> 0.4950355 | AE41: =+[1]Specials!$BK$22/1000 -> 0.46516386 | AF41: =+[1]Specials!$BK$23/1000 -> 0 | AH41: =+'[1]Total P&C'!$BK$21/1000 -> -3.1983746 | AI41: =+'[1]Total P&C'!$BK$22/1000 -> 1.2864961 | AJ41: =+'[1]Total P&C'!$BK$23/1000 -> -0.78916344 | AN41: Insurance Service Result | AT41: =+[2]Retail!$BK$21/1000 -> 1.5804764 | AU41: =+[2]Retail!$BK$22/1000 -> 3.7565157 | AV41: =+[2]Retail!$BK$23/1000 -> 0.90826405 | AX41: =+[2]SME!$BK$21/1000 -> 0.04501638 | AY41: =+[2]SME!$BK$22/1000 -> 0.18558509 | AZ41: =+[2]SME!$BK$23/1000 -> -0.47444402 | BB41: =+[2]MidCorp!$BK$21/1000 -> -1.7971311 | BC41: =+[2]MidCorp!$BK$22/1000 -> -4.4322629 | BD41: =+[2]MidCorp!$BK$23/1000 -> -1.383095 | BJ41: =+[2]Specials!$BK$21/1000 -> 0 | BK41: =+[2]Specials!$BK$22/1000 -> 0 | BL41: =+[2]Specials!$BK$23/1000 -> 0 | BN41: =+'[2]Total P&C'!$BK$21/1000 -> -0.17163838 | BO41: =+'[2]Total P&C'!$BK$22/1000 -> -0.49016206 | BP41: =+'[2]Total P&C'!$BK$23/1000 -> -0.94927495 | BR41: =+'[3]Total P&C'!$BK$21/1000 -> -3.370013 | BS41: =+'[3]Total P&C'!$BK$22/1000 -> 0.79633408 | BT41: =+'[3]Total P&C'!$BK$23/1000 -> -1.7384384
B43: MOD | D43: GWP | J43: =+[1]Retail!$C$25/1000 -> 0.61171333 | K43: =+[1]Retail!$C$26/1000 -> 0.77600112 | L43: =+[1]Retail!$C$27/1000 -> 0 | N43: =+[1]SME!$C$25/1000 -> 13.376559 | O43: =+[1]SME!$C$26/1000 -> 14.223475 | P43: =+[1]SME!$C$27/1000 -> 13.82106 | R43: =+[1]MidCorp!$C$25/1000 -> 33.736337 | S43: =+[1]MidCorp!$C$26/1000 -> 33.656796 | T43: =+[1]MidCorp!$C$27/1000 -> 37.12313 | V43: =+[1]MGA!$C$25/1000 -> 16.548544 | W43: =+[1]MGA!$C$26/1000 -> 14.175313 | X43: =+[1]MGA!$C$27/1000 -> 16.52894 | Z43: =+[1]Bancassurance!$C$25/1000 -> 0.04775279 | AA43: =+[1]Bancassurance!$C$26/1000 -> 0 | AB43: =+[1]Bancassurance!$C$27/1000 -> 0 | AD43: =+[1]Specials!$C$25/1000 -> 0.03297486 | AE43: =+[1]Specials!$C$26/1000 -> 0.03064196 | AF43: =+[1]Specials!$C$27/1000 -> 0 | AH43: =+'[1]Total P&C'!$C$25/1000 -> 64.353881 | AI43: =+'[1]Total P&C'!$C$26/1000 -> 62.862228 | AJ43: =+'[1]Total P&C'!$C$27/1000 -> 67.47313 | AL43: MOD | AN43: GWP | AT43: =+[2]Retail!$C$25/1000 -> 5.6131757 | AU43: =+[2]Retail!$C$26/1000 -> 5.5810265 | AV43: =+[2]Retail!$C$27/1000 -> 6.0438989 | AX43: =+[2]SME!$C$25/1000 -> 2.6313785 | AY43: =+[2]SME!$C$26/1000 -> 2.6709543 | AZ43: =+[2]SME!$C$27/1000 -> 2.7790462 | BB43: =+[2]MidCorp!$C$25/1000 -> 5.8924798 | BC43: =+[2]MidCorp!$C$26/1000 -> 7.339314 | BD43: =+[2]MidCorp!$C$27/1000 -> 6.2036933 | BJ43: =+[2]Specials!$C$25/1000 -> 0 | BK43: =+[2]Specials!$C$26/1000 -> 0 | BL43: =+[2]Specials!$C$27/1000 -> 0 | BN43: =+'[2]Total P&C'!$C$25/1000 -> 14.137034 | BO43: =+'[2]Total P&C'!$C$26/1000 -> 15.591295 | BP43: =+'[2]Total P&C'!$C$27/1000 -> 15.026638 | BR43: =+'[3]Total P&C'!$C$25/1000 -> 78.490915 | BS43: =+'[3]Total P&C'!$C$26/1000 -> 78.453523 | BT43: =+'[3]Total P&C'!$C$27/1000 -> 82.499768
D44: Insurance Service Revenue | J44: =+[1]Retail!$N$25/1000 -> 0.57285803 | K44: =+[1]Retail!$N$26/1000 -> 0.77384197 | L44: =+[1]Retail!$N$27/1000 -> 0 | N44: =+[1]SME!$N$25/1000 -> 8.0021348 | O44: =+[1]SME!$N$26/1000 -> 8.5683675 | P44: =+[1]SME!$N$27/1000 -> 8.5351977 | R44: =+[1]MidCorp!$N$25/1000 -> 28.599752 | S44: =+[1]MidCorp!$N$26/1000 -> 27.887173 | T44: =+[1]MidCorp!$N$27/1000 -> 29.096952 | V44: =+[1]MGA!$N$25/1000 -> 12.889772 | W44: =+[1]MGA!$N$26/1000 -> 11.253687 | X44: =+[1]MGA!$N$27/1000 -> 15.114645 | Z44: =+[1]Bancassurance!$N$25/1000 -> 0.04395041 | AA44: =+[1]Bancassurance!$N$26/1000 -> 0 | AB44: =+[1]Bancassurance!$N$27/1000 -> 0 | AD44: =+[1]Specials!$N$25/1000 -> 0.00787647 | AE44: =+[1]Specials!$N$26/1000 -> 0.00396381 | AF44: =+[1]Specials!$N$27/1000 -> 0 | AH44: =+'[1]Total P&C'!$N$25/1000 -> 50.116343 | AI44: =+'[1]Total P&C'!$N$26/1000 -> 48.487033 | AJ44: =+'[1]Total P&C'!$N$27/1000 -> 52.746794 | AN44: Insurance Service Revenue | AT44: =+[2]Retail!$N$25/1000 -> 5.3441295 | AU44: =+[2]Retail!$N$26/1000 -> 5.1781473 | AV44: =+[2]Retail!$N$27/1000 -> 5.483179 | AX44: =+[2]SME!$N$25/1000 -> 2.190753 | AY44: =+[2]SME!$N$26/1000 -> 2.2048938 | AZ44: =+[2]SME!$N$27/1000 -> 2.3190896 | BB44: =+[2]MidCorp!$N$25/1000 -> 3.7263401 | BC44: =+[2]MidCorp!$N$26/1000 -> 4.4793697 | BD44: =+[2]MidCorp!$N$27/1000 -> 3.8618668 | BJ44: =+[2]Specials!$N$25/1000 -> 0 | BK44: =+[2]Specials!$N$26/1000 -> 0 | BL44: =+[2]Specials!$N$27/1000 -> 0 | BN44: =+'[2]Total P&C'!$N$25/1000 -> 11.261223 | BO44: =+'[2]Total P&C'!$N$26/1000 -> 11.862411 | BP44: =+'[2]Total P&C'!$N$27/1000 -> 11.664135 | BR44: =+'[3]Total P&C'!$N$25/1000 -> 61.377566 | BS44: =+'[3]Total P&C'!$N$26/1000 -> 60.349444 | BT44: =+'[3]Total P&C'!$N$27/1000 -> 64.41093
D45: CoR | J45: =+J46+J51+J52+J53+J54 -> 0.95696534 | K45: =+K46+K51+K52+K53+K54 -> 1.3397712 | L45: =+L46+L51+L52+L53+L54 -> #DIV/0! | N45: =+N46+N51+N52+N53+N54 -> 0.81225715 | O45: =+O46+O51+O52+O53+O54 -> 0.76638418 | P45: =+P46+P51+P52+P53+P54 -> 0.7632252 | R45: =+R46+R51+R52+R53+R54 -> 0.96667182 | S45: =+S46+S51+S52+S53+S54 -> 0.86609885 | T45: =+T46+T51+T52+T53+T54 -> 0.9236919 | V45: =+V46+V51+V52+V53+V54 -> 0.69870706 | W45: =+W46+W51+W52+W53+W54 -> 0.92648401 | X45: =+X46+X51+X52+X53+X54 -> 0.88468374 | Z45: =+Z46+Z51+Z52+Z53+Z54 -> 0.15005275 | AA45: =+AA46+AA51+AA52+AA53+AA54 -> #DIV/0! | AB45: =+AB46+AB51+AB52+AB53+AB54 -> #DIV/0! | AD45: =+AD46+AD51+AD52+AD53+AD54 -> -16.377895 | AE45: =+AE46+AE51+AE52+AE53+AE54 -> -29.012491 | AF45: =+AF46+AF51+AF52+AF53+AF54 -> #DIV/0! | AH45: =+AH46+AH51+AH52+AH53+AH54 -> 0.86954349 | AI45: =+AI46+AI51+AI52+AI53+AI54 -> 0.86786696 | AJ45: =+AJ46+AJ51+AJ52+AJ53+AJ54 -> 0.88939571 | AN45: CoR | AT45: =+AT46+AT51+AT52+AT53+AT54 -> 1.049161 | AU45: =+AU46+AU51+AU52+AU53+AU54 -> 1.0925235 | AV45: =+AV46+AV51+AV52+AV53+AV54 -> 1.1121516 | AX45: =+AX46+AX51+AX52+AX53+AX54 -> 1.2086169 | AY45: =+AY46+AY51+AY52+AY53+AY54 -> 0.9169038 | AZ45: =+AZ46+AZ51+AZ52+AZ53+AZ54 -> 1.0299634 | BB45: =+BB46+BB51+BB52+BB53+BB54 -> 0.82365889 | BC45: =+BC46+BC51+BC52+BC53+BC54 -> 1.0364553 | BD45: =+BD46+BD51+BD52+BD53+BD54 -> 1.0006349 | BJ45: =+BJ46+BJ51+BJ52+BJ53+BJ54 -> #DIV/0! | BK45: =+BK46+BK51+BK52+BK53+BK54 -> #DIV/0! | BL45: =+BL46+BL51+BL52+BL53+BL54 -> #DIV/0! | BN45: =+BN46+BN51+BN52+BN53+BN54 -> 1.0055628 | BO45: =+BO46+BO51+BO52+BO53+BO54 -> 1.0387087 | BP45: =+BP46+BP51+BP52+BP53+BP54 -> 1.0588888 | BR45: =+BR46+BR51+BR52+BR53+BR54 -> 0.89449957 | BS45: =+BS46+BS51+BS52+BS53+BS54 -> 0.90144797 | BT45: =+BT46+BT51+BT52+BT53+BT54 -> 0.92008912
D46: L.R + ReR AY | J46: =+J47+J48+J49+J50 -> 0.10159372 | K46: =+K47+K48+K49+K50 -> 0.76434504 | L46: =+L47+L48+L49+L50 -> #DIV/0! | N46: =+N47+N48+N49+N50 -> 0.40254885 | O46: =+O47+O48+O49+O50 -> 0.46875713 | P46: =+P47+P48+P49+P50 -> 0.48963456 | R46: =+R47+R48+R49+R50 -> 0.60229744 | S46: =+S47+S48+S49+S50 -> 0.63833015 | T46: =+T47+T48+T49+T50 -> 0.65396588 | V46: =+V47+V48+V49+V50 -> 0.6235944 | W46: =+W47+W48+W49+W50 -> 0.63959991 | X46: =+X47+X48+X49+X50 -> 0.59577495 | Z46: =+Z47+Z48+Z49+Z50 -> 0 | AA46: =+AA47+AA48+AA49+AA50 -> #DIV/0! | AB46: =+AB47+AB48+AB49+AB50 -> #DIV/0! | AD46: =+AD47+AD48+AD49+AD50 -> -16.377895 | AE46: =+AE47+AE48+AE49+AE50 -> -29.012491 | AF46: =+AF47+AF48+AF49+AF50 -> #DIV/0! | AH46: =+AH47+AH48+AH49+AH50 -> 0.56696067 | AI46: =+AI47+AI48+AI49+AI50 -> 0.60824604 | AJ46: =+AJ47+AJ48+AJ49+AJ50 -> 0.61157248 | AN46: L.R + ReR AY | AT46: =+AT47+AT48+AT49+AT50 -> 0.75966587 | AU46: =+AU47+AU48+AU49+AU50 -> 0.88756057 | AV46: =+AV47+AV48+AV49+AV50 -> 0.75623414 | AX46: =+AX47+AX48+AX49+AX50 -> 0.87688609 | AY46: =+AY47+AY48+AY49+AY50 -> 0.72699774 | AZ46: =+AZ47+AZ48+AZ49+AZ50 -> 0.65896088 | BB46: =+BB47+BB48+BB49+BB50 -> 0.52873222 | BC46: =+BC47+BC48+BC49+BC50 -> 0.65945295 | BD46: =+BD47+BD48+BD49+BD50 -> 0.66020678 | BJ46: =+BJ47+BJ48+BJ49+BJ50 -> #DIV/0! | BK46: =+BK47+BK48+BK49+BK50 -> #DIV/0! | BL46: =+BL47+BL48+BL49+BL50 -> #DIV/0! | BN46: =+BN47+BN48+BN49+BN50 -> 0.70605386 | BO46: =+BO47+BO48+BO49+BO50 -> 0.77158057 | BP46: =+BP47+BP48+BP49+BP50 -> 0.70510045 | BR46: =+BR47+BR48+BR49+BR50 -> 0.59248074 | BS46: =+BS47+BS48+BS49+BS50 -> 0.64035141 | BT46: =+BT47+BT48+BT49+BT50 -> 0.62850941
D47: Attritional | J47: =-SUM([1]Retail!$O$25,[1]Retail!$R$25:$V$25,[1]Retail!$Y$25,[1]Retail!$AB$25,[1]Retail!$AU$25,[1]Retail!$AX$25,[1]Retail!$BA$25,[1]Retail!$BD$25)/1000/J44 -> 0.01042033 | K47: =-SUM([1]Retail!$O$26,[1]Retail!$R$26:$V$26,[1]Retail!$Y$26,[1]Retail!$AB$26,[1]Retail!$AU$26,[1]Retail!$AX$26,[1]Retail!$BA$26,[1]Retail!$BD$26)/1000/K44 -> 0.67183495 | L47: =-SUM([1]Retail!$O$27,[1]Retail!$R$27:$V$27,[1]Retail!$Y$27,[1]Retail!$AB$27,[1]Retail!$AU$27,[1]Retail!$AX$27,[1]Retail!$BA$27,[1]Retail!$BD$27)/1000/L44 -> #DIV/0! | N47: =-SUM([1]SME!$O$25,[1]SME!$R$25:$V$25,[1]SME!$Y$25,[1]SME!$AB$25,[1]SME!$AU$25,[1]SME!$AX$25,[1]SME!$BA$25,[1]SME!$BD$25)/1000/N44 -> 0.38316087 | O47: =-SUM([1]SME!$O$26,[1]SME!$R$26:$V$26,[1]SME!$Y$26,[1]SME!$AB$26,[1]SME!$AU$26,[1]SME!$AX$26,[1]SME!$BA$26,[1]SME!$BD$26)/1000/O44 -> 0.44825787 | P47: =-SUM([1]SME!$O$27,[1]SME!$R$27:$V$27,[1]SME!$Y$27,[1]SME!$AB$27,[1]SME!$AU$27,[1]SME!$AX$27,[1]SME!$BA$27,[1]SME!$BD$27)/1000/P44 -> 0.45093216 | R47: =-SUM([1]MidCorp!$O$25,[1]MidCorp!$R$25:$V$25,[1]MidCorp!$Y$25,[1]MidCorp!$AB$25,[1]MidCorp!$AU$25,[1]MidCorp!$AX$25,[1]MidCorp!$BA$25,[1]MidCorp!$BD$25)/1000/R44 -> 0.56054955 | S47: =-SUM([1]MidCorp!$O$26,[1]MidCorp!$R$26:$V$26,[1]MidCorp!$Y$26,[1]MidCorp!$AB$26,[1]MidCorp!$AU$26,[1]MidCorp!$AX$26,[1]MidCorp!$BA$26,[1]MidCorp!$BD$26)/1000/S44 -> 0.58037337 | T47: =-SUM([1]MidCorp!$O$27,[1]MidCorp!$R$27:$V$27,[1]MidCorp!$Y$27,[1]MidCorp!$AB$27,[1]MidCorp!$AU$27,[1]MidCorp!$AX$27,[1]MidCorp!$BA$27,[1]MidCorp!$BD$27)/1000/T44 -> 0.54340237 | V47: =-SUM([1]MGA!$O$25,[1]MGA!$R$25:$V$25,[1]MGA!$Y$25,[1]MGA!$AB$25,[1]MGA!$AU$25,[1]MGA!$AX$25,[1]MGA!$BA$25,[1]MGA!$BD$25)/1000/V44 -> 0.60885973 | W47: =-SUM([1]MGA!$O$26,[1]MGA!$R$26:$V$26,[1]MGA!$Y$26,[1]MGA!$AB$26,[1]MGA!$AU$26,[1]MGA!$AX$26,[1]MGA!$BA$26,[1]MGA!$BD$26)/1000/W44 -> 0.62198712 | X47: =-SUM([1]MGA!$O$27,[1]MGA!$R$27:$V$27,[1]MGA!$Y$27,[1]MGA!$AB$27,[1]MGA!$AU$27,[1]MGA!$AX$27,[1]MGA!$BA$27,[1]MGA!$BD$27)/1000/X44 -> 0.55070225 | Z47: =-SUM([1]Bancassurance!$O$25,[1]Bancassurance!$R$25:$V$25,[1]Bancassurance!$Y$25,[1]Bancassurance!$AB$25,[1]Bancassurance!$AU$25,[1]Bancassurance!$AX$25,[1]Bancassurance!$BA$25,[1]Bancassurance!$BD$25)/1000/Z44 -> 0 | AA47: =-SUM([1]Bancassurance!$O$26,[1]Bancassurance!$R$26:$V$26,[1]Bancassurance!$Y$26,[1]Bancassurance!$AB$26,[1]Bancassurance!$AU$26,[1]Bancassurance!$AX$26,[1]Bancassurance!$BA$26,[1]Bancassurance!$BD$26)/1000/AA44 -> #DIV/0! | AB47: =-SUM([1]Bancassurance!$O$27,[1]Bancassurance!$R$27:$V$27,[1]Bancassurance!$Y$27,[1]Bancassurance!$AB$27,[1]Bancassurance!$AU$27,[1]Bancassurance!$AX$27,[1]Bancassurance!$BA$27,[1]Bancassurance!$BD$27)/1000/AB44 -> #DIV/0! | AD47: =-SUM([1]Specials!$O$25,[1]Specials!$R$25:$V$25,[1]Specials!$Y$25,[1]Specials!$AB$25,[1]Specials!$AU$25,[1]Specials!$AX$25,[1]Specials!$BA$25,[1]Specials!$BD$25)/1000/AD44 -> 0 | AE47: =-SUM([1]Specials!$O$26,[1]Specials!$R$26:$V$26,[1]Specials!$Y$26,[1]Specials!$AB$26,[1]Specials!$AU$26,[1]Specials!$AX$26,[1]Specials!$BA$26,[1]Specials!$BD$26)/1000/AE44 -> 0 | AF47: =-SUM([1]Specials!$O$27,[1]Specials!$R$27:$V$27,[1]Specials!$Y$27,[1]Specials!$AB$27,[1]Specials!$AU$27,[1]Specials!$AX$27,[1]Specials!$BA$27,[1]Specials!$BD$27)/1000/AF44 -> #DIV/0! | AH47: =-SUM('[1]Total P&C'!$O$25,'[1]Total P&C'!$R$25:$V$25,'[1]Total P&C'!$Y$25,'[1]Total P&C'!$AB$25,'[1]Total P&C'!$AU$25,'[1]Total P&C'!$AX$25,'[1]Total P&C'!$BA$25,'[1]Total P&C'!$BD$25)/1000/AH44 -> 0.53778296 | AI47: =-SUM('[1]Total P&C'!$O$26,'[1]Total P&C'!$R$26:$V$26,'[1]Total P&C'!$Y$26,'[1]Total P&C'!$AB$26,'[1]Total P&C'!$AU$26,'[1]Total P&C'!$AX$26,'[1]Total P&C'!$BA$26,'[1]Total P&C'!$BD$26)/1000/AI44 -> 0.56809731 | AJ47: =-SUM('[1]Total P&C'!$O$27,'[1]Total P&C'!$R$27:$V$27,'[1]Total P&C'!$Y$27,'[1]Total P&C'!$AB$27,'[1]Total P&C'!$AU$27,'[1]Total P&C'!$AX$27,'[1]Total P&C'!$BA$27,'[1]Total P&C'!$BD$27)/1000/AJ44 -> 0.5314036 | AN47: Attritional | AT47: =-SUM([2]Retail!$O$25,[2]Retail!$R$25:$V$25,[2]Retail!$Y$25,[2]Retail!$AB$25,[2]Retail!$AU$25,[2]Retail!$AX$25,[2]Retail!$BA$25,[2]Retail!$BD$25)/1000/AT44 -> 0.74843439 | AU47: =-SUM([2]Retail!$O$26,[2]Retail!$R$26:$V$26,[2]Retail!$Y$26,[2]Retail!$AB$26,[2]Retail!$AU$26,[2]Retail!$AX$26,[2]Retail!$BA$26,[2]Retail!$BD$26)/1000/AU44 -> 0.87258359 | AV47: =-SUM([2]Retail!$O$27,[2]Retail!$R$27:$V$27,[2]Retail!$Y$27,[2]Retail!$AB$27,[2]Retail!$AU$27,[2]Retail!$AX$27,[2]Retail!$BA$27,[2]Retail!$BD$27)/1000/AV44 -> 0.72302585 | AX47: =-SUM([2]SME!$O$25,[2]SME!$R$25:$V$25,[2]SME!$Y$25,[2]SME!$AB$25,[2]SME!$AU$25,[2]SME!$AX$25,[2]SME!$BA$25,[2]SME!$BD$25)/1000/AX44 -> 0.86186579 | AY47: =-SUM([2]SME!$O$26,[2]SME!$R$26:$V$26,[2]SME!$Y$26,[2]SME!$AB$26,[2]SME!$AU$26,[2]SME!$AX$26,[2]SME!$BA$26,[2]SME!$BD$26)/1000/AY44 -> 0.7128152 | AZ47: =-SUM([2]SME!$O$27,[2]SME!$R$27:$V$27,[2]SME!$Y$27,[2]SME!$AB$27,[2]SME!$AU$27,[2]SME!$AX$27,[2]SME!$BA$27,[2]SME!$BD$27)/1000/AZ44 -> 0.62701438 | BB47: =-SUM([2]MidCorp!$O$25,[2]MidCorp!$R$25:$V$25,[2]MidCorp!$Y$25,[2]MidCorp!$AB$25,[2]MidCorp!$AU$25,[2]MidCorp!$AX$25,[2]MidCorp!$BA$25,[2]MidCorp!$BD$25)/1000/BB44 -> 0.52486464 | BC47: =-SUM([2]MidCorp!$O$26,[2]MidCorp!$R$26:$V$26,[2]MidCorp!$Y$26,[2]MidCorp!$AB$26,[2]MidCorp!$AU$26,[2]MidCorp!$AX$26,[2]MidCorp!$BA$26,[2]MidCorp!$BD$26)/1000/BC44 -> 0.65582275 | BD47: =-SUM([2]MidCorp!$O$27,[2]MidCorp!$R$27:$V$27,[2]MidCorp!$Y$27,[2]MidCorp!$AB$27,[2]MidCorp!$AU$27,[2]MidCorp!$AX$27,[2]MidCorp!$BA$27,[2]MidCorp!$BD$27)/1000/BD44 -> 0.58642516 | BJ47: =-SUM([2]Specials!$O$25,[2]Specials!$R$25:$V$25,[2]Specials!$Y$25,[2]Specials!$AB$25,[2]Specials!$AU$25,[2]Specials!$AX$25,[2]Specials!$BA$25,[2]Specials!$BD$25)/1000/BJ44 -> #DIV/0! | BK47: =-SUM([2]Specials!$O$26,[2]Specials!$R$26:$V$26,[2]Specials!$Y$26,[2]Specials!$AB$26,[2]Specials!$AU$26,[2]Specials!$AX$26,[2]Specials!$BA$26,[2]Specials!$BD$26)/1000/BK44 -> #DIV/0! | BL47: =-SUM([2]Specials!$O$27,[2]Specials!$R$27:$V$27,[2]Specials!$Y$27,[2]Specials!$AB$27,[2]Specials!$AU$27,[2]Specials!$AX$27,[2]Specials!$BA$27,[2]Specials!$BD$27)/1000/BL44 -> #DIV/0! | BN47: =-SUM('[2]Total P&C'!$O$25,'[2]Total P&C'!$R$25:$V$25,'[2]Total P&C'!$Y$25,'[2]Total P&C'!$AB$25,'[2]Total P&C'!$AU$25,'[2]Total P&C'!$AX$25,'[2]Total P&C'!$BA$25,'[2]Total P&C'!$BD$25)/1000/BN44 -> 0.69652202 | BO47: =-SUM('[2]Total P&C'!$O$26,'[2]Total P&C'!$R$26:$V$26,'[2]Total P&C'!$Y$26,'[2]Total P&C'!$AB$26,'[2]Total P&C'!$AU$26,'[2]Total P&C'!$AX$26,'[2]Total P&C'!$BA$26,'[2]Total P&C'!$BD$26)/1000/BO44 -> 0.76103592 | BP47: =-SUM('[2]Total P&C'!$O$27,'[2]Total P&C'!$R$27:$V$27,'[2]Total P&C'!$Y$27,'[2]Total P&C'!$AB$27,'[2]Total P&C'!$AU$27,'[2]Total P&C'!$AX$27,'[2]Total P&C'!$BA$27,'[2]Total P&C'!$BD$27)/1000/BP44 -> 0.65870965 | BR47: =-SUM('[3]Total P&C'!$O$25,'[3]Total P&C'!$R$25:$V$25,'[3]Total P&C'!$Y$25,'[3]Total P&C'!$AB$25,'[3]Total P&C'!$AU$25,'[3]Total P&C'!$AX$25,'[3]Total P&C'!$BA$25,'[3]Total P&C'!$BD$25)/1000/BR44 -> 0.56690754 | BS47: =-SUM('[3]Total P&C'!$O$26,'[3]Total P&C'!$R$26:$V$26,'[3]Total P&C'!$Y$26,'[3]Total P&C'!$AB$26,'[3]Total P&C'!$AU$26,'[3]Total P&C'!$AX$26,'[3]Total P&C'!$BA$26,'[3]Total P&C'!$BD$26)/1000/BS44 -> 0.60602172 | BT47: =-SUM('[3]Total P&C'!$O$27,'[3]Total P&C'!$R$27:$V$27,'[3]Total P&C'!$Y$27,'[3]Total P&C'!$AB$27,'[3]Total P&C'!$AU$27,'[3]Total P&C'!$AX$27,'[3]Total P&C'!$BA$27,'[3]Total P&C'!$BD$27)/1000/BT44 -> 0.55445737
D48: Nat Cat | J48: =-([1]Retail!$P$25+[1]Retail!$W$25+[1]Retail!$AV$25+[1]Retail!$AY$25)/1000/J44 -> 0 | K48: =-([1]Retail!$P$26+[1]Retail!$W$26+[1]Retail!$AV$26+[1]Retail!$AY$26)/1000/K44 -> 0 | L48: =-([1]Retail!$P$27+[1]Retail!$W$27+[1]Retail!$AV$27+[1]Retail!$AY$27)/1000/L44 -> #DIV/0! | N48: =-([1]SME!$P$25+[1]SME!$W$25+[1]SME!$AV$25+[1]SME!$AY$25)/1000/N44 -> 0 | O48: =-([1]SME!$P$26+[1]SME!$W$26+[1]SME!$AV$26+[1]SME!$AY$26)/1000/O44 -> 0 | P48: =-([1]SME!$P$27+[1]SME!$W$27+[1]SME!$AV$27+[1]SME!$AY$27)/1000/P44 -> 0.022652246 | R48: =-([1]MidCorp!$P$25+[1]MidCorp!$W$25+[1]MidCorp!$AV$25+[1]MidCorp!$AY$25)/1000/R44 -> 0 | S48: =-([1]MidCorp!$P$26+[1]MidCorp!$W$26+[1]MidCorp!$AV$26+[1]MidCorp!$AY$26)/1000/S44 -> 0 | T48: =-([1]MidCorp!$P$27+[1]MidCorp!$W$27+[1]MidCorp!$AV$27+[1]MidCorp!$AY$27)/1000/T44 -> 0.022356755 | V48: =-([1]MGA!$P$25+[1]MGA!$W$25+[1]MGA!$AV$25+[1]MGA!$AY$25)/1000/V44 -> 0.00019783128 | W48: =-([1]MGA!$P$26+[1]MGA!$W$26+[1]MGA!$AV$26+[1]MGA!$AY$26)/1000/W44 -> 0 | X48: =-([1]MGA!$P$27+[1]MGA!$W$27+[1]MGA!$AV$27+[1]MGA!$AY$27)/1000/X44 -> 0.026024796 | Z48: =-([1]Bancassurance!$P$25+[1]Bancassurance!$W$25+[1]Bancassurance!$AV$25+[1]Bancassurance!$AY$25)/1000/Z44 -> 0 | AA48: =-([1]Bancassurance!$P$26+[1]Bancassurance!$W$26+[1]Bancassurance!$AV$26+[1]Bancassurance!$AY$26)/1000/AA44 -> #DIV/0! | AB48: =-([1]Bancassurance!$P$27+[1]Bancassurance!$W$27+[1]Bancassurance!$AV$27+[1]Bancassurance!$AY$27)/1000/AB44 -> #DIV/0! | AD48: =-([1]Specials!$P$25+[1]Specials!$W$25+[1]Specials!$AV$25+[1]Specials!$AY$25)/1000/AD44 -> 0 | AE48: =-([1]Specials!$P$26+[1]Specials!$W$26+[1]Specials!$AV$26+[1]Specials!$AY$26)/1000/AE44 -> 0 | AF48: =-([1]Specials!$P$27+[1]Specials!$W$27+[1]Specials!$AV$27+[1]Specials!$AY$27)/1000/AF44 -> #DIV/0! | AH48: =-('[1]Total P&C'!$P$25+'[1]Total P&C'!$W$25+'[1]Total P&C'!$AV$25+'[1]Total P&C'!$AY$25)/1000/AH44 -> 5.0881606e-05 | AI48: =-('[1]Total P&C'!$P$26+'[1]Total P&C'!$W$26+'[1]Total P&C'!$AV$26+'[1]Total P&C'!$AY$26)/1000/AI44 -> 0 | AJ48: =-('[1]Total P&C'!$P$27+'[1]Total P&C'!$W$27+'[1]Total P&C'!$AV$27+'[1]Total P&C'!$AY$27)/1000/AJ44 -> 0.02345565 | AN48: Nat Cat | AT48: =-([2]Retail!$P$25+[2]Retail!$W$25+[2]Retail!$AV$25+[2]Retail!$AY$25)/1000/AT44 -> 0.0015546929 | AU48: =-([2]Retail!$P$26+[2]Retail!$W$26+[2]Retail!$AV$26+[2]Retail!$AY$26)/1000/AU44 -> 0 | AV48: =-([2]Retail!$P$27+[2]Retail!$W$27+[2]Retail!$AV$27+[2]Retail!$AY$27)/1000/AV44 -> 0.022574742 | AX48: =-([2]SME!$P$25+[2]SME!$W$25+[2]SME!$AV$25+[2]SME!$AY$25)/1000/AX44 -> 0.0055018159 | AY48: =-([2]SME!$P$26+[2]SME!$W$26+[2]SME!$AV$26+[2]SME!$AY$26)/1000/AY44 -> 0 | AZ48: =-([2]SME!$P$27+[2]SME!$W$27+[2]SME!$AV$27+[2]SME!$AY$27)/1000/AZ44 -> 0.022651593 | BB48: =-([2]MidCorp!$P$25+[2]MidCorp!$W$25+[2]MidCorp!$AV$25+[2]MidCorp!$AY$25)/1000/BB44 -> 0.00095778696 | BC48: =-([2]MidCorp!$P$26+[2]MidCorp!$W$26+[2]MidCorp!$AV$26+[2]MidCorp!$AY$26)/1000/BC44 -> 0 | BD48: =-([2]MidCorp!$P$27+[2]MidCorp!$W$27+[2]MidCorp!$AV$27+[2]MidCorp!$AY$27)/1000/BD44 -> 0.022392593 | BJ48: =-([2]Specials!$P$25+[2]Specials!$W$25+[2]Specials!$AV$25+[2]Specials!$AY$25)/1000/BJ44 -> #DIV/0! | BK48: =-([2]Specials!$P$26+[2]Specials!$W$26+[2]Specials!$AV$26+[2]Specials!$AY$26)/1000/BK44 -> #DIV/0! | BL48: =-([2]Specials!$P$27+[2]Specials!$W$27+[2]Specials!$AV$27+[2]Specials!$AY$27)/1000/BL44 -> #DIV/0! | BN48: =-('[2]Total P&C'!$P$25+'[2]Total P&C'!$W$25+'[2]Total P&C'!$AV$25+'[2]Total P&C'!$AY$25)/1000/BN44 -> 0.0021250481 | BO48: =-('[2]Total P&C'!$P$26+'[2]Total P&C'!$W$26+'[2]Total P&C'!$AV$26+'[2]Total P&C'!$AY$26)/1000/BO44 -> 0 | BP48: =-('[2]Total P&C'!$P$27+'[2]Total P&C'!$W$27+'[2]Total P&C'!$AV$27+'[2]Total P&C'!$AY$27)/1000/BP44 -> 0.022529714 | BR48: =-('[3]Total P&C'!$P$25+'[3]Total P&C'!$W$25+'[3]Total P&C'!$AV$25+'[3]Total P&C'!$AY$25)/1000/BR44 -> 0.00043143842 | BS48: =-('[3]Total P&C'!$P$26+'[3]Total P&C'!$W$26+'[3]Total P&C'!$AV$26+'[3]Total P&C'!$AY$26)/1000/BS44 -> 0 | BT48: =-('[3]Total P&C'!$P$27+'[3]Total P&C'!$W$27+'[3]Total P&C'!$AV$27+'[3]Total P&C'!$AY$27)/1000/BT44 -> 0.023287973
D49: Large Losses | J49: =-([1]Retail!$Q$25+[1]Retail!$X$25+[1]Retail!$AW$25+[1]Retail!$AZ$25)/1000/J44 -> 0 | K49: =-([1]Retail!$Q$26+[1]Retail!$X$26+[1]Retail!$AW$26+[1]Retail!$AZ$26)/1000/K44 -> 0 | L49: =-([1]Retail!$Q$27+[1]Retail!$X$27+[1]Retail!$AW$27+[1]Retail!$AZ$27)/1000/L44 -> #DIV/0! | N49: =-([1]SME!$Q$25+[1]SME!$X$25+[1]SME!$AW$25+[1]SME!$AZ$25)/1000/N44 -> 0 | O49: =-([1]SME!$Q$26+[1]SME!$X$26+[1]SME!$AW$26+[1]SME!$AZ$26)/1000/O44 -> 0 | P49: =-([1]SME!$Q$27+[1]SME!$X$27+[1]SME!$AW$27+[1]SME!$AZ$27)/1000/P44 -> 0 | R49: =-([1]MidCorp!$Q$25+[1]MidCorp!$X$25+[1]MidCorp!$AW$25+[1]MidCorp!$AZ$25)/1000/R44 -> 0 | S49: =-([1]MidCorp!$Q$26+[1]MidCorp!$X$26+[1]MidCorp!$AW$26+[1]MidCorp!$AZ$26)/1000/S44 -> 0 | T49: =-([1]MidCorp!$Q$27+[1]MidCorp!$X$27+[1]MidCorp!$AW$27+[1]MidCorp!$AZ$27)/1000/T44 -> 0 | V49: =-([1]MGA!$Q$25+[1]MGA!$X$25+[1]MGA!$AW$25+[1]MGA!$AZ$25)/1000/V44 -> 0 | W49: =-([1]MGA!$Q$26+[1]MGA!$X$26+[1]MGA!$AW$26+[1]MGA!$AZ$26)/1000/W44 -> 0 | X49: =-([1]MGA!$Q$27+[1]MGA!$X$27+[1]MGA!$AW$27+[1]MGA!$AZ$27)/1000/X44 -> 0 | Z49: =-([1]Bancassurance!$Q$25+[1]Bancassurance!$X$25+[1]Bancassurance!$AW$25+[1]Bancassurance!$AZ$25)/1000/Z44 -> 0 | AA49: =-([1]Bancassurance!$Q$26+[1]Bancassurance!$X$26+[1]Bancassurance!$AW$26+[1]Bancassurance!$AZ$26)/1000/AA44 -> #DIV/0! | AB49: =-([1]Bancassurance!$Q$27+[1]Bancassurance!$X$27+[1]Bancassurance!$AW$27+[1]Bancassurance!$AZ$27)/1000/AB44 -> #DIV/0! | AD49: =-([1]Specials!$Q$25+[1]Specials!$X$25+[1]Specials!$AW$25+[1]Specials!$AZ$25)/1000/AD44 -> 0 | AE49: =-([1]Specials!$Q$26+[1]Specials!$X$26+[1]Specials!$AW$26+[1]Specials!$AZ$26)/1000/AE44 -> 0 | AF49: =-([1]Specials!$Q$27+[1]Specials!$X$27+[1]Specials!$AW$27+[1]Specials!$AZ$27)/1000/AF44 -> #DIV/0! | AH49: =-('[1]Total P&C'!$Q$25+'[1]Total P&C'!$X$25+'[1]Total P&C'!$AW$25+'[1]Total P&C'!$AZ$25)/1000/AH44 -> 0 | AI49: =-('[1]Total P&C'!$Q$26+'[1]Total P&C'!$X$26+'[1]Total P&C'!$AW$26+'[1]Total P&C'!$AZ$26)/1000/AI44 -> 0 | AJ49: =-('[1]Total P&C'!$Q$27+'[1]Total P&C'!$X$27+'[1]Total P&C'!$AW$27+'[1]Total P&C'!$AZ$27)/1000/AJ44 -> 0 | AN49: Large Losses | AT49: =-([2]Retail!$Q$25+[2]Retail!$X$25+[2]Retail!$AW$25+[2]Retail!$AZ$25)/1000/AT44 -> 0 | AU49: =-([2]Retail!$Q$26+[2]Retail!$X$26+[2]Retail!$AW$26+[2]Retail!$AZ$26)/1000/AU44 -> 0 | AV49: =-([2]Retail!$Q$27+[2]Retail!$X$27+[2]Retail!$AW$27+[2]Retail!$AZ$27)/1000/AV44 -> 0 | AX49: =-([2]SME!$Q$25+[2]SME!$X$25+[2]SME!$AW$25+[2]SME!$AZ$25)/1000/AX44 -> 0 | AY49: =-([2]SME!$Q$26+[2]SME!$X$26+[2]SME!$AW$26+[2]SME!$AZ$26)/1000/AY44 -> 0 | AZ49: =-([2]SME!$Q$27+[2]SME!$X$27+[2]SME!$AW$27+[2]SME!$AZ$27)/1000/AZ44 -> 0 | BB49: =-([2]MidCorp!$Q$25+[2]MidCorp!$X$25+[2]MidCorp!$AW$25+[2]MidCorp!$AZ$25)/1000/BB44 -> 0 | BC49: =-([2]MidCorp!$Q$26+[2]MidCorp!$X$26+[2]MidCorp!$AW$26+[2]MidCorp!$AZ$26)/1000/BC44 -> 0 | BD49: =-([2]MidCorp!$Q$27+[2]MidCorp!$X$27+[2]MidCorp!$AW$27+[2]MidCorp!$AZ$27)/1000/BD44 -> 0 | BJ49: =-([2]Specials!$Q$25+[2]Specials!$X$25+[2]Specials!$AW$25+[2]Specials!$AZ$25)/1000/BJ44 -> #DIV/0! | BK49: =-([2]Specials!$Q$26+[2]Specials!$X$26+[2]Specials!$AW$26+[2]Specials!$AZ$26)/1000/BK44 -> #DIV/0! | BL49: =-([2]Specials!$Q$27+[2]Specials!$X$27+[2]Specials!$AW$27+[2]Specials!$AZ$27)/1000/BL44 -> #DIV/0! | BN49: =-('[2]Total P&C'!$Q$25+'[2]Total P&C'!$X$25+'[2]Total P&C'!$AW$25+'[2]Total P&C'!$AZ$25)/1000/BN44 -> 0 | BO49: =-('[2]Total P&C'!$Q$26+'[2]Total P&C'!$X$26+'[2]Total P&C'!$AW$26+'[2]Total P&C'!$AZ$26)/1000/BO44 -> 0 | BP49: =-('[2]Total P&C'!$Q$27+'[2]Total P&C'!$X$27+'[2]Total P&C'!$AW$27+'[2]Total P&C'!$AZ$27)/1000/BP44 -> 0 | BR49: =-('[3]Total P&C'!$Q$25+'[3]Total P&C'!$X$25+'[3]Total P&C'!$AW$25+'[3]Total P&C'!$AZ$25)/1000/BR44 -> 0 | BS49: =-('[3]Total P&C'!$Q$26+'[3]Total P&C'!$X$26+'[3]Total P&C'!$AW$26+'[3]Total P&C'!$AZ$26)/1000/BS44 -> 0 | BT49: =-('[3]Total P&C'!$Q$27+'[3]Total P&C'!$X$27+'[3]Total P&C'!$AW$27+'[3]Total P&C'!$AZ$27)/1000/BT44 -> 0
D50: Others | J50: =-[1]Retail!$AT$25/1000/J44 -> 0.091173392 | K50: =-[1]Retail!$AT$26/1000/K44 -> 0.09251009 | L50: =-[1]Retail!$AT$27/1000/L44 -> #DIV/0! | N50: =-[1]SME!$AT$25/1000/N44 -> 0.01938798 | O50: =-[1]SME!$AT$26/1000/O44 -> 0.02049926 | P50: =-[1]SME!$AT$27/1000/P44 -> 0.016050151 | R50: =-[1]MidCorp!$AT$25/1000/R44 -> 0.041747892 | S50: =-[1]MidCorp!$AT$26/1000/S44 -> 0.057956777 | T50: =-[1]MidCorp!$AT$27/1000/T44 -> 0.088206756 | V50: =-[1]MGA!$AT$25/1000/V44 -> 0.014536839 | W50: =-[1]MGA!$AT$26/1000/W44 -> 0.017612788 | X50: =-[1]MGA!$AT$27/1000/X44 -> 0.019047901 | Z50: =-[1]Bancassurance!$AT$25/1000/Z44 -> 0 | AA50: =-[1]Bancassurance!$AT$26/1000/AA44 -> #DIV/0! | AB50: =-[1]Bancassurance!$AT$27/1000/AB44 -> #DIV/0! | AD50: =-[1]Specials!$AT$25/1000/AD44 -> -16.377895 | AE50: =-[1]Specials!$AT$26/1000/AE44 -> -29.012491 | AF50: =-[1]Specials!$AT$27/1000/AF44 -> #DIV/0! | AH50: =-'[1]Total P&C'!$AT$25/1000/AH44 -> 0.029126837 | AI50: =-'[1]Total P&C'!$AT$26/1000/AI44 -> 0.040148731 | AJ50: =-'[1]Total P&C'!$AT$27/1000/AJ44 -> 0.056713232 | AN50: Others | AT50: =-[2]Retail!$AT$25/1000/AT44 -> 0.0096767901 | AU50: =-[2]Retail!$AT$26/1000/AU44 -> 0.014976978 | AV50: =-[2]Retail!$AT$27/1000/AV44 -> 0.010633551 | AX50: =-[2]SME!$AT$25/1000/AX44 -> 0.0095184804 | AY50: =-[2]SME!$AT$26/1000/AY44 -> 0.014182543 | AZ50: =-[2]SME!$AT$27/1000/AZ44 -> 0.0092949069 | BB50: =-[2]MidCorp!$AT$25/1000/BB44 -> 0.0029097934 | BC50: =-[2]MidCorp!$AT$26/1000/BC44 -> 0.0036301982 | BD50: =-[2]MidCorp!$AT$27/1000/BD44 -> 0.051389026 | BJ50: =-[2]Specials!$AT$25/1000/BJ44 -> #DIV/0! | BK50: =-[2]Specials!$AT$26/1000/BK44 -> #DIV/0! | BL50: =-[2]Specials!$AT$27/1000/BL44 -> #DIV/0! | BN50: =-'[2]Total P&C'!$AT$25/1000/BN44 -> 0.0074067925 | BO50: =-'[2]Total P&C'!$AT$26/1000/BO44 -> 0.010544652 | BP50: =-'[2]Total P&C'!$AT$27/1000/BP44 -> 0.023861088 | BR50: =-'[3]Total P&C'!$AT$25/1000/BR44 -> 0.025141761 | BS50: =-'[3]Total P&C'!$AT$26/1000/BS44 -> 0.034329693 | BT50: =-'[3]Total P&C'!$AT$27/1000/BT44 -> 0.050764058
D51: Discounting a.y. | J51: =-([1]Retail!$Z$25+[1]Retail!$AA$25+[1]Retail!$BB$25+[1]Retail!$BC$25)/1000/J44 -> -0.00073955496 | K51: =-([1]Retail!$Z$26+[1]Retail!$AA$26+[1]Retail!$BB$26+[1]Retail!$BC$26)/1000/K44 -> -0.0067491299 | L51: =-([1]Retail!$Z$27+[1]Retail!$AA$27+[1]Retail!$BB$27+[1]Retail!$BC$27)/1000/L44 -> #DIV/0! | N51: =-([1]SME!$Z$25+[1]SME!$AA$25+[1]SME!$BB$25+[1]SME!$BC$25)/1000/N44 -> -0.0027048319 | O51: =-([1]SME!$Z$26+[1]SME!$AA$26+[1]SME!$BB$26+[1]SME!$BC$26)/1000/O44 -> -0.0048412851 | P51: =-([1]SME!$Z$27+[1]SME!$AA$27+[1]SME!$BB$27+[1]SME!$BC$27)/1000/P44 -> -0.0014171824 | R51: =-([1]MidCorp!$Z$25+[1]MidCorp!$AA$25+[1]MidCorp!$BB$25+[1]MidCorp!$BC$25)/1000/R44 -> -0.0039728331 | S51: =-([1]MidCorp!$Z$26+[1]MidCorp!$AA$26+[1]MidCorp!$BB$26+[1]MidCorp!$BC$26)/1000/S44 -> -0.0052091389 | T51: =-([1]MidCorp!$Z$27+[1]MidCorp!$AA$27+[1]MidCorp!$BB$27+[1]MidCorp!$BC$27)/1000/T44 -> -0.0015402302 | V51: =-([1]MGA!$Z$25+[1]MGA!$AA$25+[1]MGA!$BB$25+[1]MGA!$BC$25)/1000/V44 -> -0.006715254 | W51: =-([1]MGA!$Z$26+[1]MGA!$AA$26+[1]MGA!$BB$26+[1]MGA!$BC$26)/1000/W44 -> -0.0081649483 | X51: =-([1]MGA!$Z$27+[1]MGA!$AA$27+[1]MGA!$BB$27+[1]MGA!$BC$27)/1000/X44 -> -0.0026239369 | Z51: =-([1]Bancassurance!$Z$25+[1]Bancassurance!$AA$25+[1]Bancassurance!$BB$25+[1]Bancassurance!$BC$25)/1000/Z44 -> 0 | AA51: =-([1]Bancassurance!$Z$26+[1]Bancassurance!$AA$26+[1]Bancassurance!$BB$26+[1]Bancassurance!$BC$26)/1000/AA44 -> #DIV/0! | AB51: =-([1]Bancassurance!$Z$27+[1]Bancassurance!$AA$27+[1]Bancassurance!$BB$27+[1]Bancassurance!$BC$27)/1000/AB44 -> #DIV/0! | AD51: =-([1]Specials!$Z$25+[1]Specials!$AA$25+[1]Specials!$BB$25+[1]Specials!$BC$25)/1000/AD44 -> 0 | AE51: =-([1]Specials!$Z$26+[1]Specials!$AA$26+[1]Specials!$BB$26+[1]Specials!$BC$26)/1000/AE44 -> 0 | AF51: =-([1]Specials!$Z$27+[1]Specials!$AA$27+[1]Specials!$BB$27+[1]Specials!$BC$27)/1000/AF44 -> #DIV/0! | AH51: =-('[1]Total P&C'!$Z$25+'[1]Total P&C'!$AA$25+'[1]Total P&C'!$BB$25+'[1]Total P&C'!$BC$25)/1000/AH44 -> -0.0044346456 | AI51: =-('[1]Total P&C'!$Z$26+'[1]Total P&C'!$AA$26+'[1]Total P&C'!$BB$26+'[1]Total P&C'!$BC$26)/1000/AI44 -> -0.0058543198 | AJ51: =-('[1]Total P&C'!$Z$27+'[1]Total P&C'!$AA$27+'[1]Total P&C'!$BB$27+'[1]Total P&C'!$BC$27)/1000/AJ44 -> -0.0018308564 | AN51: Discounting a.y. | AT51: =-([2]Retail!$Z$25+[2]Retail!$AA$25+[2]Retail!$BB$25+[2]Retail!$BC$25)/1000/AT44 -> -0.0051893933 | AU51: =-([2]Retail!$Z$26+[2]Retail!$AA$26+[2]Retail!$BB$26+[2]Retail!$BC$26)/1000/AU44 -> -0.0074975117 | AV51: =-([2]Retail!$Z$27+[2]Retail!$AA$27+[2]Retail!$BB$27+[2]Retail!$BC$27)/1000/AV44 -> -0.0010560283 | AX51: =-([2]SME!$Z$25+[2]SME!$AA$25+[2]SME!$BB$25+[2]SME!$BC$25)/1000/AX44 -> -0.0073495595 | AY51: =-([2]SME!$Z$26+[2]SME!$AA$26+[2]SME!$BB$26+[2]SME!$BC$26)/1000/AY44 -> -0.0062239415 | AZ51: =-([2]SME!$Z$27+[2]SME!$AA$27+[2]SME!$BB$27+[2]SME!$BC$27)/1000/AZ44 -> -0.00094741492 | BB51: =-([2]MidCorp!$Z$25+[2]MidCorp!$AA$25+[2]MidCorp!$BB$25+[2]MidCorp!$BC$25)/1000/BB44 -> -0.0043389598 | BC51: =-([2]MidCorp!$Z$26+[2]MidCorp!$AA$26+[2]MidCorp!$BB$26+[2]MidCorp!$BC$26)/1000/BC44 -> -0.0067185345 | BD51: =-([2]MidCorp!$Z$27+[2]MidCorp!$AA$27+[2]MidCorp!$BB$27+[2]MidCorp!$BC$27)/1000/BD44 -> -0.00086554011 | BJ51: =-([2]Specials!$Z$25+[2]Specials!$AA$25+[2]Specials!$BB$25+[2]Specials!$BC$25)/1000/BJ44 -> #DIV/0! | BK51: =-([2]Specials!$Z$26+[2]Specials!$AA$26+[2]Specials!$BB$26+[2]Specials!$BC$26)/1000/BK44 -> #DIV/0! | BL51: =-([2]Specials!$Z$27+[2]Specials!$AA$27+[2]Specials!$BB$27+[2]Specials!$BC$27)/1000/BL44 -> #DIV/0! | BN51: =-('[2]Total P&C'!$Z$25+'[2]Total P&C'!$AA$25+'[2]Total P&C'!$BB$25+'[2]Total P&C'!$BC$25)/1000/BN44 -> -0.0053282225 | BO51: =-('[2]Total P&C'!$Z$26+'[2]Total P&C'!$AA$26+'[2]Total P&C'!$BB$26+'[2]Total P&C'!$BC$26)/1000/BO44 -> -0.0069666404 | BP51: =-('[2]Total P&C'!$Z$27+'[2]Total P&C'!$AA$27+'[2]Total P&C'!$BB$27+'[2]Total P&C'!$BC$27)/1000/BP44 -> -0.00097136499 | BR51: =-('[3]Total P&C'!$Z$25+'[3]Total P&C'!$AA$25+'[3]Total P&C'!$BB$25+'[3]Total P&C'!$BC$25)/1000/BR44 -> -0.0045985942 | BS51: =-('[3]Total P&C'!$Z$26+'[3]Total P&C'!$AA$26+'[3]Total P&C'!$BB$26+'[3]Total P&C'!$BC$26)/1000/BS44 -> -0.0060729598 | BT51: =-('[3]Total P&C'!$Z$27+'[3]Total P&C'!$AA$27+'[3]Total P&C'!$BB$27+'[3]Total P&C'!$BC$27)/1000/BT44 -> -0.0016752117
D52: Run-off + ReR | J52: =-SUM([1]Retail!$AC$25:$AI$25,[1]Retail!$BE$25:$BG$25)/1000/J44 -> 0.51205032 | K52: =-SUM([1]Retail!$AC$26:$AI$26,[1]Retail!$BE$26:$BG$26)/1000/K44 -> -0.036869802 | L52: =-SUM([1]Retail!$AC$27:$AI$27,[1]Retail!$BE$27:$BG$27)/1000/L44 -> #DIV/0! | N52: =-SUM([1]SME!$AC$25:$AI$25,[1]SME!$BE$25:$BG$25)/1000/N44 -> 0.14471971 | O52: =-SUM([1]SME!$AC$26:$AI$26,[1]SME!$BE$26:$BG$26)/1000/O44 -> 0.027887206 | P52: =-SUM([1]SME!$AC$27:$AI$27,[1]SME!$BE$27:$BG$27)/1000/P44 -> -0.0029714256 | R52: =-SUM([1]MidCorp!$AC$25:$AI$25,[1]MidCorp!$BE$25:$BG$25)/1000/R44 -> 0.11310329 | S52: =-SUM([1]MidCorp!$AC$26:$AI$26,[1]MidCorp!$BE$26:$BG$26)/1000/S44 -> -0.019485581 | T52: =-SUM([1]MidCorp!$AC$27:$AI$27,[1]MidCorp!$BE$27:$BG$27)/1000/T44 -> -0.0032364679 | V52: =-SUM([1]MGA!$AC$25:$AI$25,[1]MGA!$BE$25:$BG$25)/1000/V44 -> -0.24671052 | W52: =-SUM([1]MGA!$AC$26:$AI$26,[1]MGA!$BE$26:$BG$26)/1000/W44 -> -0.017509538 | X52: =-SUM([1]MGA!$AC$27:$AI$27,[1]MGA!$BE$27:$BG$27)/1000/X44 -> -0.026930267 | Z52: =-SUM([1]Bancassurance!$AC$25:$AI$25,[1]Bancassurance!$BE$25:$BG$25)/1000/Z44 -> 0 | AA52: =-SUM([1]Bancassurance!$AC$26:$AI$26,[1]Bancassurance!$BE$26:$BG$26)/1000/AA44 -> #DIV/0! | AB52: =-SUM([1]Bancassurance!$AC$27:$AI$27,[1]Bancassurance!$BE$27:$BG$27)/1000/AB44 -> #DIV/0! | AD52: =-SUM([1]Specials!$AC$25:$AI$25,[1]Specials!$BE$25:$BG$25)/1000/AD44 -> 0 | AE52: =-SUM([1]Specials!$AC$26:$AI$26,[1]Specials!$BE$26:$BG$26)/1000/AE44 -> 0 | AF52: =-SUM([1]Specials!$AC$27:$AI$27,[1]Specials!$BE$27:$BG$27)/1000/AF44 -> #DIV/0! | AH52: =-SUM('[1]Total P&C'!$AC$25:$AI$25,'[1]Total P&C'!$BE$25:$BG$25)/1000/AH44 -> 0.030051724 | AI52: =-SUM('[1]Total P&C'!$AC$26:$AI$26,'[1]Total P&C'!$BE$26:$BG$26)/1000/AI44 -> -0.010931339 | AJ52: =-SUM('[1]Total P&C'!$AC$27:$AI$27,'[1]Total P&C'!$BE$27:$BG$27)/1000/AJ44 -> -0.0099830611 | AN52: Run-off + ReR | AT52: =-SUM([2]Retail!$AC$25:$AI$25,[2]Retail!$BE$25:$BG$25)/1000/AT44 -> -0.068314051 | AU52: =-SUM([2]Retail!$AC$26:$AI$26,[2]Retail!$BE$26:$BG$26)/1000/AU44 -> -0.14268922 | AV52: =-SUM([2]Retail!$AC$27:$AI$27,[2]Retail!$BE$27:$BG$27)/1000/AV44 -> -0.0040814162 | AX52: =-SUM([2]SME!$AC$25:$AI$25,[2]SME!$BE$25:$BG$25)/1000/AX44 -> -0.037907513 | AY52: =-SUM([2]SME!$AC$26:$AI$26,[2]SME!$BE$26:$BG$26)/1000/AY44 -> -0.16203164 | AZ52: =-SUM([2]SME!$AC$27:$AI$27,[2]SME!$BE$27:$BG$27)/1000/AZ44 -> -0.0046425161 | BB52: =-SUM([2]MidCorp!$AC$25:$AI$25,[2]MidCorp!$BE$25:$BG$25)/1000/BB44 -> -0.043128607 | BC52: =-SUM([2]MidCorp!$AC$26:$AI$26,[2]MidCorp!$BE$26:$BG$26)/1000/BC44 -> 0.084905974 | BD52: =-SUM([2]MidCorp!$AC$27:$AI$27,[2]MidCorp!$BE$27:$BG$27)/1000/BD44 -> -0.0020746539 | BJ52: =-SUM([2]Specials!$AC$25:$AI$25,[2]Specials!$BE$25:$BG$25)/1000/BJ44 -> #DIV/0! | BK52: =-SUM([2]Specials!$AC$26:$AI$26,[2]Specials!$BE$26:$BG$26)/1000/BK44 -> #DIV/0! | BL52: =-SUM([2]Specials!$AC$27:$AI$27,[2]Specials!$BE$27:$BG$27)/1000/BL44 -> #DIV/0! | BN52: =-SUM('[2]Total P&C'!$AC$25:$AI$25,'[2]Total P&C'!$BE$25:$BG$25)/1000/BN44 -> -0.054064911 | BO52: =-SUM('[2]Total P&C'!$AC$26:$AI$26,'[2]Total P&C'!$BE$26:$BG$26)/1000/BO44 -> -0.060342127 | BP52: =-SUM('[2]Total P&C'!$AC$27:$AI$27,'[2]Total P&C'!$BE$27:$BG$27)/1000/BP44 -> -0.0035285585 | BR52: =-SUM('[3]Total P&C'!$AC$25:$AI$25,'[3]Total P&C'!$BE$25:$BG$25)/1000/BR44 -> 0.01461846 | BS52: =-SUM('[3]Total P&C'!$AC$26:$AI$26,'[3]Total P&C'!$BE$26:$BG$26)/1000/BS44 -> -0.020643625 | BT52: =-SUM('[3]Total P&C'!$AC$27:$AI$27,'[3]Total P&C'!$BE$27:$BG$27)/1000/BT44 -> -0.0088142192
D53: Discounting Run-off | J53: =-SUM([1]Retail!$AJ$25:$AK$25,[1]Retail!$BH$25:$BI$25)/1000/J44 -> -0.012331467 | K53: =-SUM([1]Retail!$AJ$26:$AK$26,[1]Retail!$BH$26:$BI$26)/1000/K44 -> 0.00039570095 | L53: =-SUM([1]Retail!$AJ$27:$AK$27,[1]Retail!$BH$27:$BI$27)/1000/L44 -> #DIV/0! | N53: =-SUM([1]SME!$AJ$25:$AK$25,[1]SME!$BH$25:$BI$25)/1000/N44 -> -0.0064868027 | O53: =-SUM([1]SME!$AJ$26:$AK$26,[1]SME!$BH$26:$BI$26)/1000/O44 -> -0.00093266774 | P53: =-SUM([1]SME!$AJ$27:$AK$27,[1]SME!$BH$27:$BI$27)/1000/P44 -> 0 | R53: =-SUM([1]MidCorp!$AJ$25:$AK$25,[1]MidCorp!$BH$25:$BI$25)/1000/R44 -> -0.0046169775 | S53: =-SUM([1]MidCorp!$AJ$26:$AK$26,[1]MidCorp!$BH$26:$BI$26)/1000/S44 -> 0.0010065434 | T53: =-SUM([1]MidCorp!$AJ$27:$AK$27,[1]MidCorp!$BH$27:$BI$27)/1000/T44 -> 0 | V53: =-SUM([1]MGA!$AJ$25:$AK$25,[1]MGA!$BH$25:$BI$25)/1000/V44 -> 0.0035779424 | W53: =-SUM([1]MGA!$AJ$26:$AK$26,[1]MGA!$BH$26:$BI$26)/1000/W44 -> -0.0057404521 | X53: =-SUM([1]MGA!$AJ$27:$AK$27,[1]MGA!$BH$27:$BI$27)/1000/X44 -> 0 | Z53: =-SUM([1]Bancassurance!$AJ$25:$AK$25,[1]Bancassurance!$BH$25:$BI$25)/1000/Z44 -> 0 | AA53: =-SUM([1]Bancassurance!$AJ$26:$AK$26,[1]Bancassurance!$BH$26:$BI$26)/1000/AA44 -> #DIV/0! | AB53: =-SUM([1]Bancassurance!$AJ$27:$AK$27,[1]Bancassurance!$BH$27:$BI$27)/1000/AB44 -> #DIV/0! | AD53: =-SUM([1]Specials!$AJ$25:$AK$25,[1]Specials!$BH$25:$BI$25)/1000/AD44 -> 0 | AE53: =-SUM([1]Specials!$AJ$26:$AK$26,[1]Specials!$BH$26:$BI$26)/1000/AE44 -> 0 | AF53: =-SUM([1]Specials!$AJ$27:$AK$27,[1]Specials!$BH$27:$BI$27)/1000/AF44 -> #DIV/0! | AH53: =-SUM('[1]Total P&C'!$AJ$25:$AK$25,'[1]Total P&C'!$BH$25:$BI$25)/1000/AH44 -> -0.0028912325 | AI53: =-SUM('[1]Total P&C'!$AJ$26:$AK$26,'[1]Total P&C'!$BH$26:$BI$26)/1000/AI44 -> -0.00091193102 | AJ53: =-SUM('[1]Total P&C'!$AJ$27:$AK$27,'[1]Total P&C'!$BH$27:$BI$27)/1000/AJ44 -> 0 | AN53: Discounting Run-off | AT53: =-SUM([2]Retail!$AJ$25:$AK$25,[2]Retail!$BH$25:$BI$25)/1000/AT44 -> -0.0014426821 | AU53: =-SUM([2]Retail!$AJ$26:$AK$26,[2]Retail!$BH$26:$BI$26)/1000/AU44 -> 0.0060241276 | AV53: =-SUM([2]Retail!$AJ$27:$AK$27,[2]Retail!$BH$27:$BI$27)/1000/AV44 -> 0 | AX53: =-SUM([2]SME!$AJ$25:$AK$25,[2]SME!$BH$25:$BI$25)/1000/AX44 -> -0.0032453635 | AY53: =-SUM([2]SME!$AJ$26:$AK$26,[2]SME!$BH$26:$BI$26)/1000/AY44 -> 0.0042857847 | AZ53: =-SUM([2]SME!$AJ$27:$AK$27,[2]SME!$BH$27:$BI$27)/1000/AZ44 -> 0 | BB53: =-SUM([2]MidCorp!$AJ$25:$AK$25,[2]MidCorp!$BH$25:$BI$25)/1000/BB44 -> -0.0028533144 | BC53: =-SUM([2]MidCorp!$AJ$26:$AK$26,[2]MidCorp!$BH$26:$BI$26)/1000/BC44 -> 0.0065583356 | BD53: =-SUM([2]MidCorp!$AJ$27:$AK$27,[2]MidCorp!$BH$27:$BI$27)/1000/BD44 -> 0 | BJ53: =-SUM([2]Specials!$AJ$25:$AK$25,[2]Specials!$BH$25:$BI$25)/1000/BJ44 -> #DIV/0! | BK53: =-SUM([2]Specials!$AJ$26:$AK$26,[2]Specials!$BH$26:$BI$26)/1000/BK44 -> #DIV/0! | BL53: =-SUM([2]Specials!$AJ$27:$AK$27,[2]Specials!$BH$27:$BI$27)/1000/BL44 -> #DIV/0! | BN53: =-SUM('[2]Total P&C'!$AJ$25:$AK$25,'[2]Total P&C'!$BH$25:$BI$25)/1000/BN44 -> -0.0022601533 | BO53: =-SUM('[2]Total P&C'!$AJ$26:$AK$26,'[2]Total P&C'!$BH$26:$BI$26)/1000/BO44 -> 0.0059027403 | BP53: =-SUM('[2]Total P&C'!$AJ$27:$AK$27,'[2]Total P&C'!$BH$27:$BI$27)/1000/BP44 -> 0 | BR53: =-SUM('[3]Total P&C'!$AJ$25:$AK$25,'[3]Total P&C'!$BH$25:$BI$25)/1000/BR44 -> -0.0027754455 | BS53: =-SUM('[3]Total P&C'!$AJ$26:$AK$26,'[3]Total P&C'!$BH$26:$BI$26)/1000/BS44 -> 0.00042757477 | BT53: =-SUM('[3]Total P&C'!$AJ$27:$AK$27,'[3]Total P&C'!$BH$27:$BI$27)/1000/BT44 -> 0
D54: Expense ratio + ReR | J54: =+J55+J56+J57 -> 0.35639232 | K54: =+K55+K56+K57 -> 0.61864944 | L54: =+L55+L56+L57 -> #DIV/0! | N54: =+N55+N56+N57 -> 0.27418022 | O54: =+O55+O56+O57 -> 0.2755138 | P54: =+P55+P56+P57 -> 0.27797925 | R54: =+R55+R56+R57 -> 0.2598609 | S54: =+S55+S56+S57 -> 0.25145688 | T54: =+T55+T56+T57 -> 0.27450272 | V54: =+V55+V56+V57 -> 0.32496048 | W54: =+W55+W56+W57 -> 0.31829904 | X54: =+X55+X56+X57 -> 0.31846299 | Z54: =+Z55+Z56+Z57 -> 0.15005275 | AA54: =+AA55+AA56+AA57 -> #DIV/0! | AB54: =+AB55+AB56+AB57 -> #DIV/0! | AD54: =+AD55+AD56+AD57 -> 0 | AE54: =+AE55+AE56+AE57 -> 0 | AF54: =+AF55+AF56+AF57 -> #DIV/0! | AH54: =+AH55+AH56+AH57 -> 0.27985697 | AI54: =+AI55+AI56+AI57 -> 0.27731851 | AJ54: =+AJ55+AJ56+AJ57 -> 0.28963715 | AN54: Expense ratio + ReR | AT54: =+AT55+AT56+AT57 -> 0.36444124 | AU54: =+AU55+AU56+AU57 -> 0.34912554 | AV54: =+AV55+AV56+AV57 -> 0.36105493 | AX54: =+AX55+AX56+AX57 -> 0.38023328 | AY54: =+AY55+AY56+AY57 -> 0.35387586 | AZ54: =+AZ55+AZ56+AZ57 -> 0.37659246 | BB54: =+BB55+BB56+BB57 -> 0.34524755 | BC54: =+BC55+BC56+BC57 -> 0.29225653 | BD54: =+BD55+BD56+BD57 -> 0.34336831 | BJ54: =+BJ55+BJ56+BJ57 -> #DIV/0! | BK54: =+BK55+BK56+BK57 -> #DIV/0! | BL54: =+BL55+BL56+BL57 -> #DIV/0! | BN54: =+BN55+BN56+BN57 -> 0.36116222 | BO54: =+BO55+BO56+BO57 -> 0.32853417 | BP54: =+BP55+BP56+BP57 -> 0.35828829 | BR54: =+BR55+BR56+BR57 -> 0.29477442 | BS54: =+BS55+BS56+BS57 -> 0.28738557 | BT54: =+BT55+BT56+BT57 -> 0.30206914
D55: Commission | J55: =-SUM([1]Retail!$AL$25:$AN$25,[1]Retail!$BJ$25)/1000/J44 -> 0.18216026 | K55: =-SUM([1]Retail!$AL$26:$AN$26,[1]Retail!$BJ$26)/1000/K44 -> 0.1877431 | L55: =-SUM([1]Retail!$AL$27:$AN$27,[1]Retail!$BJ$27)/1000/L44 -> #DIV/0! | N55: =-SUM([1]SME!$AL$25:$AN$25,[1]SME!$BJ$25)/1000/N44 -> 0.16509465 | O55: =-SUM([1]SME!$AL$26:$AN$26,[1]SME!$BJ$26)/1000/O44 -> 0.16327408 | P55: =-SUM([1]SME!$AL$27:$AN$27,[1]SME!$BJ$27)/1000/P44 -> 0.16289831 | R55: =-SUM([1]MidCorp!$AL$25:$AN$25,[1]MidCorp!$BJ$25)/1000/R44 -> 0.14389628 | S55: =-SUM([1]MidCorp!$AL$26:$AN$26,[1]MidCorp!$BJ$26)/1000/S44 -> 0.13934411 | T55: =-SUM([1]MidCorp!$AL$27:$AN$27,[1]MidCorp!$BJ$27)/1000/T44 -> 0.13982706 | V55: =-SUM([1]MGA!$AL$25:$AN$25,[1]MGA!$BJ$25)/1000/V44 -> 0.26105758 | W55: =-SUM([1]MGA!$AL$26:$AN$26,[1]MGA!$BJ$26)/1000/W44 -> 0.26018558 | X55: =-SUM([1]MGA!$AL$27:$AN$27,[1]MGA!$BJ$27)/1000/X44 -> 0.24733687 | Z55: =-SUM([1]Bancassurance!$AL$25:$AN$25,[1]Bancassurance!$BJ$25)/1000/Z44 -> 0.15005275 | AA55: =-SUM([1]Bancassurance!$AL$26:$AN$26,[1]Bancassurance!$BJ$26)/1000/AA44 -> #DIV/0! | AB55: =-SUM([1]Bancassurance!$AL$27:$AN$27,[1]Bancassurance!$BJ$27)/1000/AB44 -> #DIV/0! | AD55: =-SUM([1]Specials!$AL$25:$AN$25,[1]Specials!$BJ$25)/1000/AD44 -> 0 | AE55: =-SUM([1]Specials!$AL$26:$AN$26,[1]Specials!$BJ$26)/1000/AE44 -> 0 | AF55: =-SUM([1]Specials!$AL$27:$AN$27,[1]Specials!$BJ$27)/1000/AF44 -> #DIV/0! | AH55: =-SUM('[1]Total P&C'!$AL$25:$AN$25,'[1]Total P&C'!$BJ$25)/1000/AH44 -> 0.17783474 | AI55: =-SUM('[1]Total P&C'!$AL$26:$AN$26,'[1]Total P&C'!$BJ$26)/1000/AI44 -> 0.17238085 | AJ55: =-SUM('[1]Total P&C'!$AL$27:$AN$27,'[1]Total P&C'!$BJ$27)/1000/AJ44 -> 0.17436736 | AN55: Commission | AT55: =-SUM([2]Retail!$AL$25:$AN$25,[2]Retail!$BJ$25)/1000/AT44 -> 0.17425211 | AU55: =-SUM([2]Retail!$AL$26:$AN$26,[2]Retail!$BJ$26)/1000/AU44 -> 0.17390707 | AV55: =-SUM([2]Retail!$AL$27:$AN$27,[2]Retail!$BJ$27)/1000/AV44 -> 0.1737852 | AX55: =-SUM([2]SME!$AL$25:$AN$25,[2]SME!$BJ$25)/1000/AX44 -> 0.20384165 | AY55: =-SUM([2]SME!$AL$26:$AN$26,[2]SME!$BJ$26)/1000/AY44 -> 0.20138377 | AZ55: =-SUM([2]SME!$AL$27:$AN$27,[2]SME!$BJ$27)/1000/AZ44 -> 0.20591219 | BB55: =-SUM([2]MidCorp!$AL$25:$AN$25,[2]MidCorp!$BJ$25)/1000/BB44 -> 0.15348332 | BC55: =-SUM([2]MidCorp!$AL$26:$AN$26,[2]MidCorp!$BJ$26)/1000/BC44 -> 0.15380972 | BD55: =-SUM([2]MidCorp!$AL$27:$AN$27,[2]MidCorp!$BJ$27)/1000/BD44 -> 0.1537693 | BJ55: =-SUM([2]Specials!$AL$25:$AN$25,[2]Specials!$BJ$25)/1000/BJ44 -> #DIV/0! | BK55: =-SUM([2]Specials!$AL$26:$AN$26,[2]Specials!$BJ$26)/1000/BK44 -> #DIV/0! | BL55: =-SUM([2]Specials!$AL$27:$AN$27,[2]Specials!$BJ$27)/1000/BL44 -> #DIV/0! | BN55: =-SUM('[2]Total P&C'!$AL$25:$AN$25,'[2]Total P&C'!$BJ$25)/1000/BN44 -> 0.17313605 | BO55: =-SUM('[2]Total P&C'!$AL$26:$AN$26,'[2]Total P&C'!$BJ$26)/1000/BO44 -> 0.17142526 | BP55: =-SUM('[2]Total P&C'!$AL$27:$AN$27,'[2]Total P&C'!$BJ$27)/1000/BP44 -> 0.17354572 | BR55: =-SUM('[3]Total P&C'!$AL$25:$AN$25,'[3]Total P&C'!$BJ$25)/1000/BR44 -> 0.17697265 | BS55: =-SUM('[3]Total P&C'!$AL$26:$AN$26,'[3]Total P&C'!$BJ$26)/1000/BS44 -> 0.17219302 | BT55: =-SUM('[3]Total P&C'!$AL$27:$AN$27,'[3]Total P&C'!$BJ$27)/1000/BT44 -> 0.17421857
D56: Acquisition | J56: =-SUM([1]Retail!$AO$25:$AP$25)/1000/J44 -> 0.0068670417 | K56: =-SUM([1]Retail!$AO$26:$AP$26)/1000/K44 -> 0.078313406 | L56: =-SUM([1]Retail!$AO$27:$AP$27)/1000/L44 -> #DIV/0! | N56: =-SUM([1]SME!$AO$25:$AP$25)/1000/N44 -> 0.04485418 | O56: =-SUM([1]SME!$AO$26:$AP$26)/1000/O44 -> 0.055399479 | P56: =-SUM([1]SME!$AO$27:$AP$27)/1000/P44 -> 0.04269035 | R56: =-SUM([1]MidCorp!$AO$25:$AP$25)/1000/R44 -> 0.025355933 | S56: =-SUM([1]MidCorp!$AO$26:$AP$26)/1000/S44 -> 0.032058123 | T56: =-SUM([1]MidCorp!$AO$27:$AP$27)/1000/T44 -> 0.026438577 | V56: =-SUM([1]MGA!$AO$25:$AP$25)/1000/V44 -> 0.0196839 | W56: =-SUM([1]MGA!$AO$26:$AP$26)/1000/W44 -> 0.014761641 | X56: =-SUM([1]MGA!$AO$27:$AP$27)/1000/X44 -> 0.021581074 | Z56: =-SUM([1]Bancassurance!$AO$25:$AP$25)/1000/Z44 -> 0 | AA56: =-SUM([1]Bancassurance!$AO$26:$AP$26)/1000/AA44 -> #DIV/0! | AB56: =-SUM([1]Bancassurance!$AO$27:$AP$27)/1000/AB44 -> #DIV/0! | AD56: =-SUM([1]Specials!$AO$25:$AP$25)/1000/AD44 -> 0 | AE56: =-SUM([1]Specials!$AO$26:$AP$26)/1000/AE44 -> 0 | AF56: =-SUM([1]Specials!$AO$27:$AP$27)/1000/AF44 -> #DIV/0! | AH56: =-SUM('[1]Total P&C'!$AO$25:$AP$25)/1000/AH44 -> 0.026772851 | AI56: =-SUM('[1]Total P&C'!$AO$26:$AP$26)/1000/AI44 -> 0.033134811 | AJ56: =-SUM('[1]Total P&C'!$AO$27:$AP$27)/1000/AJ44 -> 0.027748082 | AN56: Acquisition | AT56: =-SUM([2]Retail!$AO$25:$AP$25)/1000/AT44 -> 0.10805368 | AU56: =-SUM([2]Retail!$AO$26:$AP$26)/1000/AU44 -> 0.10203357 | AV56: =-SUM([2]Retail!$AO$27:$AP$27)/1000/AV44 -> 0.10426665 | AX56: =-SUM([2]SME!$AO$25:$AP$25)/1000/AX44 -> 0.083306491 | AY56: =-SUM([2]SME!$AO$26:$AP$26)/1000/AY44 -> 0.074971085 | AZ56: =-SUM([2]SME!$AO$27:$AP$27)/1000/AZ44 -> 0.069696513 | BB56: =-SUM([2]MidCorp!$AO$25:$AP$25)/1000/BB44 -> 0.08205997 | BC56: =-SUM([2]MidCorp!$AO$26:$AP$26)/1000/BC44 -> 0.054886276 | BD56: =-SUM([2]MidCorp!$AO$27:$AP$27)/1000/BD44 -> 0.072739138 | BJ56: =-SUM([2]Specials!$AO$25:$AP$25)/1000/BJ44 -> #DIV/0! | BK56: =-SUM([2]Specials!$AO$26:$AP$26)/1000/BK44 -> #DIV/0! | BL56: =-SUM([2]Specials!$AO$27:$AP$27)/1000/BL44 -> #DIV/0! | BN56: =-SUM('[2]Total P&C'!$AO$25:$AP$25)/1000/BN44 -> 0.094638051 | BO56: =-SUM('[2]Total P&C'!$AO$26:$AP$26)/1000/BO44 -> 0.079200096 | BP56: =-SUM('[2]Total P&C'!$AO$27:$AP$27)/1000/BP44 -> 0.086954925 | BR56: =-SUM('[3]Total P&C'!$AO$25:$AP$25)/1000/BR44 -> 0.03922439 | BS56: =-SUM('[3]Total P&C'!$AO$26:$AP$26)/1000/BS44 -> 0.042189498 | BT56: =-SUM('[3]Total P&C'!$AO$27:$AP$27)/1000/BT44 -> 0.038469812
D57: Administration | J57: =-SUM([1]Retail!$AQ$25:$AR$25)/1000/J44 -> 0.16736501 | K57: =-SUM([1]Retail!$AQ$26:$AR$26)/1000/K44 -> 0.35259293 | L57: =-SUM([1]Retail!$AQ$27:$AR$27)/1000/L44 -> #DIV/0! | N57: =-SUM([1]SME!$AQ$25:$AR$25)/1000/N44 -> 0.064231387 | O57: =-SUM([1]SME!$AQ$26:$AR$26)/1000/O44 -> 0.056840244 | P57: =-SUM([1]SME!$AQ$27:$AR$27)/1000/P44 -> 0.072390596 | R57: =-SUM([1]MidCorp!$AQ$25:$AR$25)/1000/R44 -> 0.090608694 | S57: =-SUM([1]MidCorp!$AQ$26:$AR$26)/1000/S44 -> 0.080054643 | T57: =-SUM([1]MidCorp!$AQ$27:$AR$27)/1000/T44 -> 0.10823708 | V57: =-SUM([1]MGA!$AQ$25:$AR$25)/1000/V44 -> 0.044219005 | W57: =-SUM([1]MGA!$AQ$26:$AR$26)/1000/W44 -> 0.043351824 | X57: =-SUM([1]MGA!$AQ$27:$AR$27)/1000/X44 -> 0.049545044 | Z57: =-SUM([1]Bancassurance!$AQ$25:$AR$25)/1000/Z44 -> 0 | AA57: =-SUM([1]Bancassurance!$AQ$26:$AR$26)/1000/AA44 -> #DIV/0! | AB57: =-SUM([1]Bancassurance!$AQ$27:$AR$27)/1000/AB44 -> #DIV/0! | AD57: =-SUM([1]Specials!$AQ$25:$AR$25)/1000/AD44 -> 0 | AE57: =-SUM([1]Specials!$AQ$26:$AR$26)/1000/AE44 -> 0 | AF57: =-SUM([1]Specials!$AQ$27:$AR$27)/1000/AF44 -> #DIV/0! | AH57: =-SUM('[1]Total P&C'!$AQ$25:$AR$25)/1000/AH44 -> 0.075249378 | AI57: =-SUM('[1]Total P&C'!$AQ$26:$AR$26)/1000/AI44 -> 0.071802848 | AJ57: =-SUM('[1]Total P&C'!$AQ$27:$AR$27)/1000/AJ44 -> 0.087521704 | AN57: Administration | AT57: =-SUM([2]Retail!$AQ$25:$AR$25)/1000/AT44 -> 0.082135445 | AU57: =-SUM([2]Retail!$AQ$26:$AR$26)/1000/AU44 -> 0.073184897 | AV57: =-SUM([2]Retail!$AQ$27:$AR$27)/1000/AV44 -> 0.083003083 | AX57: =-SUM([2]SME!$AQ$25:$AR$25)/1000/AX44 -> 0.093085133 | AY57: =-SUM([2]SME!$AQ$26:$AR$26)/1000/AY44 -> 0.077521004 | AZ57: =-SUM([2]SME!$AQ$27:$AR$27)/1000/AZ44 -> 0.10098376 | BB57: =-SUM([2]MidCorp!$AQ$25:$AR$25)/1000/BB44 -> 0.10970425 | BC57: =-SUM([2]MidCorp!$AQ$26:$AR$26)/1000/BC44 -> 0.083560544 | BD57: =-SUM([2]MidCorp!$AQ$27:$AR$27)/1000/BD44 -> 0.11685987 | BJ57: =-SUM([2]Specials!$AQ$25:$AR$25)/1000/BJ44 -> #DIV/0! | BK57: =-SUM([2]Specials!$AQ$26:$AR$26)/1000/BK44 -> #DIV/0! | BL57: =-SUM([2]Specials!$AQ$27:$AR$27)/1000/BL44 -> #DIV/0! | BN57: =-SUM('[2]Total P&C'!$AQ$25:$AR$25)/1000/BN44 -> 0.093388116 | BO57: =-SUM('[2]Total P&C'!$AQ$26:$AR$26)/1000/BO44 -> 0.077908812 | BP57: =-SUM('[2]Total P&C'!$AQ$27:$AR$27)/1000/BP44 -> 0.097787652 | BR57: =-SUM('[3]Total P&C'!$AQ$25:$AR$25)/1000/BR44 -> 0.078577375 | BS57: =-SUM('[3]Total P&C'!$AQ$26:$AR$26)/1000/BS44 -> 0.073003049 | BT57: =-SUM('[3]Total P&C'!$AQ$27:$AR$27)/1000/BT44 -> 0.089380758
D58: Insurance Service Result | J58: =+[1]Retail!$BK$25/1000 -> 0.02465275 | K58: =+[1]Retail!$BK$26/1000 -> -0.26292925 | L58: =+[1]Retail!$BK$27/1000 -> -0.15019562 | N58: =+[1]SME!$BK$25/1000 -> 1.5023436 | O58: =+[1]SME!$BK$26/1000 -> 2.0017062 | P58: =+[1]SME!$BK$27/1000 -> 2.0209197 | R58: =+[1]MidCorp!$BK$25/1000 -> 0.95317758 | S58: =+[1]MidCorp!$BK$26/1000 -> 3.7341246 | T58: =+[1]MidCorp!$BK$27/1000 -> 2.2203331 | V58: =+[1]MGA!$BK$25/1000 -> 3.8835972 | W58: =+[1]MGA!$BK$26/1000 -> 0.82732591 | X58: =+[1]MGA!$BK$27/1000 -> 1.7429643 | Z58: =+[1]Bancassurance!$BK$25/1000 -> 0.03735553 | AA58: =+[1]Bancassurance!$BK$26/1000 -> -0.01245234 | AB58: =+[1]Bancassurance!$BK$27/1000 -> 0 | AD58: =+[1]Specials!$BK$25/1000 -> 0.13687647 | AE58: =+[1]Specials!$BK$26/1000 -> 0.11896381 | AF58: =+[1]Specials!$BK$27/1000 -> 0 | AH58: =+'[1]Total P&C'!$BK$25/1000 -> 6.5380031 | AI58: =+'[1]Total P&C'!$BK$26/1000 -> 6.406739 | AJ58: =+'[1]Total P&C'!$BK$27/1000 -> 5.8340215 | AN58: Insurance Service Result | AT58: =+[2]Retail!$BK$25/1000 -> -0.26272266 | AU58: =+[2]Retail!$BK$26/1000 -> -0.47910035 | AV58: =+[2]Retail!$BK$27/1000 -> -0.61494745 | AX58: =+[2]SME!$BK$25/1000 -> -0.45702817 | AY58: =+[2]SME!$BK$26/1000 -> 0.18321829 | AZ58: =+[2]SME!$BK$27/1000 -> -0.069487834 | BB58: =+[2]MidCorp!$BK$25/1000 -> 0.65710696 | BC58: =+[2]MidCorp!$BK$26/1000 -> -0.16329659 | BD58: =+[2]MidCorp!$BK$27/1000 -> -0.002451913 | BJ58: =+[2]Specials!$BK$25/1000 -> 0 | BK58: =+[2]Specials!$BK$26/1000 -> 0 | BL58: =+[2]Specials!$BK$27/1000 -> 0 | BN58: =+'[2]Total P&C'!$BK$25/1000 -> -0.06264387 | BO58: =+'[2]Total P&C'!$BK$26/1000 -> -0.45917865 | BP58: =+'[2]Total P&C'!$BK$27/1000 -> -0.6868872 | BR58: =+'[3]Total P&C'!$BK$25/1000 -> 6.4753593 | BS58: =+'[3]Total P&C'!$BK$26/1000 -> 5.9475603 | BT58: =+'[3]Total P&C'!$BK$27/1000 -> 5.1471343
B60: PROPERTY Fire & Engineering | D60: GWP | J60: =+[1]Retail!$C$33/1000+[1]Retail!$C$37/1000 -> 1.3005752 | K60: =+[1]Retail!$C$34/1000+[1]Retail!$C$38/1000 -> 1.5206208 | L60: =+[1]Retail!$C$35/1000+[1]Retail!$C$39/1000 -> 0 | N60: =+[1]SME!$C$33/1000+[1]SME!$C$37/1000 -> 20.009173 | O60: =+[1]SME!$C$34/1000+[1]SME!$C$38/1000 -> 20.047579 | P60: =+[1]SME!$C$35/1000+[1]SME!$C$39/1000 -> 18.08401 | R60: =+[1]MidCorp!$C$33/1000+[1]MidCorp!$C$37/1000 -> 104.34539 | S60: =+[1]MidCorp!$C$34/1000+[1]MidCorp!$C$38/1000 -> 106.73346 | T60: =+[1]MidCorp!$C$35/1000+[1]MidCorp!$C$39/1000 -> 108.02706 | V60: =+[1]MGA!$C$33/1000+[1]MGA!$C$37/1000 -> 3.5544188 | W60: =+[1]MGA!$C$34/1000+[1]MGA!$C$38/1000 -> 3.1188244 | X60: =+[1]MGA!$C$35/1000+[1]MGA!$C$39/1000 -> 6.51719 | Z60: =+[1]Bancassurance!$C$33/1000+[1]Bancassurance!$C$37/1000 -> 0.04201758 | AA60: =+[1]Bancassurance!$C$34/1000+[1]Bancassurance!$C$38/1000 -> 0 | AB60: =+[1]Bancassurance!$C$35/1000+[1]Bancassurance!$C$39/1000 -> 0.27317 | AD60: =+[1]Specials!$C$33/1000+[1]Specials!$C$37/1000 -> 0.00106913 | AE60: =+[1]Specials!$C$34/1000+[1]Specials!$C$38/1000 -> -0.002583 | AF60: =+[1]Specials!$C$35/1000+[1]Specials!$C$39/1000 -> 0 | AH60: =+'[1]Total P&C'!$C$33/1000+'[1]Total P&C'!$C$37/1000 -> 129.25264 | AI60: =+'[1]Total P&C'!$C$34/1000+'[1]Total P&C'!$C$38/1000 -> 131.4179 | AJ60: =+'[1]Total P&C'!$C$35/1000+'[1]Total P&C'!$C$39/1000 -> 132.90143 | AL60: PROPERTY Fire & Engineering | AN60: GWP | AT60: =+[2]Retail!$C$33/1000+[2]Retail!$C$37/1000 -> 12.459517 | AU60: =+[2]Retail!$C$34/1000+[2]Retail!$C$38/1000 -> 12.835577 | AV60: =+[2]Retail!$C$35/1000+[2]Retail!$C$39/1000 -> 13.131484 | AX60: =+[2]SME!$C$33/1000+[2]SME!$C$37/1000 -> 5.968003 | AY60: =+[2]SME!$C$34/1000+[2]SME!$C$38/1000 -> 6.1407779 | AZ60: =+[2]SME!$C$35/1000+[2]SME!$C$39/1000 -> 6.2543069 | BB60: =+[2]MidCorp!$C$33/1000+[2]MidCorp!$C$37/1000 -> 25.857972 | BC60: =+[2]MidCorp!$C$34/1000+[2]MidCorp!$C$38/1000 -> 25.263488 | BD60: =+[2]MidCorp!$C$35/1000+[2]MidCorp!$C$39/1000 -> 28.327357 | BJ60: =+[2]Specials!$C$33/1000+[2]Specials!$C$37/1000 -> 0 | BK60: =+[2]Specials!$C$34/1000+[2]Specials!$C$38/1000 -> 0 | BL60: =+[2]Specials!$C$35/1000+[2]Specials!$C$39/1000 -> 0 | BN60: =+'[2]Total P&C'!$C$33/1000+'[2]Total P&C'!$C$37/1000 -> 44.285492 | BO60: =+'[2]Total P&C'!$C$34/1000+'[2]Total P&C'!$C$38/1000 -> 44.239843 | BP60: =+'[2]Total P&C'!$C$35/1000+'[2]Total P&C'!$C$39/1000 -> 47.713147 | BR60: =+'[3]Total P&C'!$C$33/1000+'[3]Total P&C'!$C$37/1000 -> 173.53814 | BS60: =+'[3]Total P&C'!$C$34/1000+'[3]Total P&C'!$C$38/1000 -> 175.65774 | BT60: =+'[3]Total P&C'!$C$35/1000+'[3]Total P&C'!$C$39/1000 -> 180.61458
D61: Insurance Service Revenue | J61: =+[1]Retail!$N$33/1000+[1]Retail!$N$37/1000 -> 1.3175103 | K61: =+[1]Retail!$N$34/1000+[1]Retail!$N$38/1000 -> 1.5505957 | L61: =+[1]Retail!$N$35/1000+[1]Retail!$N$39/1000 -> 0 | N61: =+[1]SME!$N$33/1000+[1]SME!$N$37/1000 -> 9.6528134 | O61: =+[1]SME!$N$34/1000+[1]SME!$N$38/1000 -> 9.7543117 | P61: =+[1]SME!$N$35/1000+[1]SME!$N$39/1000 -> 9.4373127 | R61: =+[1]MidCorp!$N$33/1000+[1]MidCorp!$N$37/1000 -> 42.170181 | S61: =+[1]MidCorp!$N$34/1000+[1]MidCorp!$N$38/1000 -> 41.458528 | T61: =+[1]MidCorp!$N$35/1000+[1]MidCorp!$N$39/1000 -> 55.411311 | V61: =+[1]MGA!$N$33/1000+[1]MGA!$N$37/1000 -> 3.2371441 | W61: =+[1]MGA!$N$34/1000+[1]MGA!$N$38/1000 -> 2.8898964 | X61: =+[1]MGA!$N$35/1000+[1]MGA!$N$39/1000 -> 6.224 | Z61: =+[1]Bancassurance!$N$33/1000+[1]Bancassurance!$N$37/1000 -> 0.02622394 | AA61: =+[1]Bancassurance!$N$34/1000+[1]Bancassurance!$N$38/1000 -> 0 | AB61: =+[1]Bancassurance!$N$35/1000+[1]Bancassurance!$N$39/1000 -> 0.30894008 | AD61: =+[1]Specials!$N$33/1000+[1]Specials!$N$37/1000 -> 0.01822823 | AE61: =+[1]Specials!$N$34/1000+[1]Specials!$N$38/1000 -> 0.01627471 | AF61: =+[1]Specials!$N$35/1000+[1]Specials!$N$39/1000 -> 0 | AH61: =+'[1]Total P&C'!$N$33/1000+'[1]Total P&C'!$N$37/1000 -> 56.422101 | AI61: =+'[1]Total P&C'!$N$34/1000+'[1]Total P&C'!$N$38/1000 -> 55.669607 | AJ61: =+'[1]Total P&C'!$N$35/1000+'[1]Total P&C'!$N$39/1000 -> 71.381564 | AN61: Insurance Service Revenue | AT61: =+[2]Retail!$N$33/1000+[2]Retail!$N$37/1000 -> 12.519301 | AU61: =+[2]Retail!$N$34/1000+[2]Retail!$N$38/1000 -> 12.809171 | AV61: =+[2]Retail!$N$35/1000+[2]Retail!$N$39/1000 -> 13.142971 | AX61: =+[2]SME!$N$33/1000+[2]SME!$N$37/1000 -> 4.0744001 | AY61: =+[2]SME!$N$34/1000+[2]SME!$N$38/1000 -> 4.2556116 | AZ61: =+[2]SME!$N$35/1000+[2]SME!$N$39/1000 -> 4.3161256 | BB61: =+[2]MidCorp!$N$33/1000+[2]MidCorp!$N$37/1000 -> 15.069942 | BC61: =+[2]MidCorp!$N$34/1000+[2]MidCorp!$N$38/1000 -> 14.546895 | BD61: =+[2]MidCorp!$N$35/1000+[2]MidCorp!$N$39/1000 -> 17.992432 | BJ61: =+[2]Specials!$N$33/1000+[2]Specials!$N$37/1000 -> 0 | BK61: =+[2]Specials!$N$34/1000+[2]Specials!$N$38/1000 -> 0 | BL61: =+[2]Specials!$N$35/1000+[2]Specials!$N$39/1000 -> 0 | BN61: =+'[2]Total P&C'!$N$33/1000+'[2]Total P&C'!$N$37/1000 -> 31.663642 | BO61: =+'[2]Total P&C'!$N$34/1000+'[2]Total P&C'!$N$38/1000 -> 31.611678 | BP61: =+'[2]Total P&C'!$N$35/1000+'[2]Total P&C'!$N$39/1000 -> 35.451529 | BR61: =+'[3]Total P&C'!$N$33/1000+'[3]Total P&C'!$N$37/1000 -> 88.085744 | BS61: =+'[3]Total P&C'!$N$34/1000+'[3]Total P&C'!$N$38/1000 -> 87.281285 | BT61: =+'[3]Total P&C'!$N$35/1000+'[3]Total P&C'!$N$39/1000 -> 106.83309
D62: CoR | J62: =+J63+J68+J69+J70+J71 -> 0.42429403 | K62: =+K63+K68+K69+K70+K71 -> 1.0924877 | L62: =+L63+L68+L69+L70+L71 -> #DIV/0! | N62: =+N63+N68+N69+N70+N71 -> 1.0366788 | O62: =+O63+O68+O69+O70+O71 -> 0.76977275 | P62: =+P63+P68+P69+P70+P71 -> 0.96263033 | R62: =+R63+R68+R69+R70+R71 -> 0.82238814 | S62: =+S63+S68+S69+S70+S71 -> 0.8957987 | T62: =+T63+T68+T69+T70+T71 -> 0.90116834 | V62: =+V63+V68+V69+V70+V71 -> 0.96460533 | W62: =+W63+W68+W69+W70+W71 -> 1.1619465 | X62: =+X63+X68+X69+X70+X71 -> 0.93077027 | Z62: =+Z63+Z68+Z69+Z70+Z71 -> 24.298363 | AA62: =+AA63+AA68+AA69+AA70+AA71 -> #DIV/0! | AB62: =+AB63+AB68+AB69+AB70+AB71 -> 1.6711655 | AD62: =+AD63+AD68+AD69+AD70+AD71 -> -0.1676109 | AE62: =+AE63+AE68+AE69+AE70+AE71 -> 3.160935 | AF62: =+AF63+AF68+AF69+AF70+AF71 -> #DIV/0! | AH62: =+AH63+AH68+AH69+AH70+AH71 -> 0.86850445 | AI62: =+AI63+AI68+AI69+AI70+AI71 -> 0.90781003 | AJ62: =+AJ63+AJ68+AJ69+AJ70+AJ71 -> 0.91798083 | AN62: CoR | AT62: =+AT63+AT68+AT69+AT70+AT71 -> 0.91666078 | AU62: =+AU63+AU68+AU69+AU70+AU71 -> 0.87258372 | AV62: =+AV63+AV68+AV69+AV70+AV71 -> 0.97414081 | AX62: =+AX63+AX68+AX69+AX70+AX71 -> 1.0394292 | AY62: =+AY63+AY68+AY69+AY70+AY71 -> 0.47538967 | AZ62: =+AZ63+AZ68+AZ69+AZ70+AZ71 -> 1.1275744 | BB62: =+BB63+BB68+BB69+BB70+BB71 -> 1.0273764 | BC62: =+BC63+BC68+BC69+BC70+BC71 -> 1.0748851 | BD62: =+BD63+BD68+BD69+BD70+BD71 -> 0.98790851 | BJ62: =+BJ63+BJ68+BJ69+BJ70+BJ71 -> #DIV/0! | BK62: =+BK63+BK68+BK69+BK70+BK71 -> #DIV/0! | BL62: =+BL63+BL68+BL69+BL70+BL71 -> #DIV/0! | BN62: =+BN63+BN68+BN69+BN70+BN71 -> 0.9851521 | BO62: =+BO63+BO68+BO69+BO70+BO71 -> 0.91220685 | BP62: =+BP63+BP68+BP69+BP70+BP71 -> 0.99980834 | BR62: =+BR63+BR68+BR69+BR70+BR71 -> 0.91043507 | BS62: =+BS63+BS68+BS69+BS70+BS71 -> 0.90940248 | BT62: =+BT63+BT68+BT69+BT70+BT71 -> 0.94513449
D63: L.R + ReR AY | J63: =+J64+J65+J66+J67 -> 0.086337677 | K63: =+K64+K65+K66+K67 -> 0.67322426 | L63: =+L64+L65+L66+L67 -> #DIV/0! | N63: =+N64+N65+N66+N67 -> 0.44309615 | O63: =+O64+O65+O66+O67 -> 0.56122322 | P63: =+P64+P65+P66+P67 -> 0.58128024 | R63: =+R64+R65+R66+R67 -> 0.65289784 | S63: =+S64+S65+S66+S67 -> 0.66687152 | T63: =+T64+T65+T66+T67 -> 0.69101455 | V63: =+V64+V65+V66+V67 -> 0.85188281 | W63: =+W64+W65+W66+W67 -> 0.59103758 | X63: =+X64+X65+X66+X67 -> 0.57285449 | Z63: =+Z64+Z65+Z66+Z67 -> 6.1024606 | AA63: =+AA64+AA65+AA66+AA67 -> #DIV/0! | AB63: =+AB64+AB65+AB66+AB67 -> 0.43782378 | AD63: =+AD64+AD65+AD66+AD67 -> 0.78309194 | AE63: =+AE64+AE65+AE66+AE67 -> 0.76741582 | AF63: =+AF64+AF65+AF66+AF67 -> #DIV/0! | AH63: =+AH64+AH65+AH66+AH67 -> 0.61776621 | AI63: =+AI64+AI65+AI66+AI67 -> 0.64880092 | AJ63: =+AJ64+AJ65+AJ66+AJ67 -> 0.66593556 | AN63: L.R + ReR AY | AT63: =+AT64+AT65+AT66+AT67 -> 0.58823692 | AU63: =+AU64+AU65+AU66+AU67 -> 0.6591451 | AV63: =+AV64+AV65+AV66+AV67 -> 0.57847408 | AX63: =+AX64+AX65+AX66+AX67 -> 0.5723627 | AY63: =+AY64+AY65+AY66+AY67 -> 0.43105016 | AZ63: =+AZ64+AZ65+AZ66+AZ67 -> 0.60635481 | BB63: =+BB64+BB65+BB66+BB67 -> 0.48003672 | BC63: =+BC64+BC65+BC66+BC67 -> 0.54164497 | BD63: =+BD64+BD65+BD66+BD67 -> 0.60445469 | BJ63: =+BJ64+BJ65+BJ66+BJ67 -> #DIV/0! | BK63: =+BK64+BK65+BK66+BK67 -> #DIV/0! | BL63: =+BL64+BL65+BL66+BL67 -> #DIV/0! | BN63: =+BN64+BN65+BN66+BN67 -> 0.53469764 | BO63: =+BO64+BO65+BO66+BO67 -> 0.57436803 | BP63: =+BP64+BP65+BP66+BP67 -> 0.59505421 | BR63: =+BR64+BR65+BR66+BR67 -> 0.58790606 | BS63: =+BS64+BS65+BS66+BS67 -> 0.62184269 | BT63: =+BT64+BT65+BT66+BT67 -> 0.64241427
D64: Attritional | J64: =-SUM([1]Retail!$O$33,[1]Retail!$R$33:$V$33,[1]Retail!$Y$33,[1]Retail!$AB$33,[1]Retail!$AU$33,[1]Retail!$AX$33,[1]Retail!$BA$33,[1]Retail!$BD$33,[1]Retail!$O$37,[1]Retail!$R$37:$V$37,[1]Retail!$Y$37,[1]Retail!$AB$37,[1]Retail!$AU$37,[1]Retail!$AX$37,[1]Retail!$BA$37,[1]Retail!$BD$37)/1000/J61 -> 0.084619854 | K64: =-SUM([1]Retail!$O$34,[1]Retail!$R$34:$V$34,[1]Retail!$Y$34,[1]Retail!$AB$34,[1]Retail!$AU$34,[1]Retail!$AX$34,[1]Retail!$BA$34,[1]Retail!$BD$34,[1]Retail!$O$38,[1]Retail!$R$38:$V$38,[1]Retail!$Y$38,[1]Retail!$AB$38,[1]Retail!$AU$38,[1]Retail!$AX$38,[1]Retail!$BA$38,[1]Retail!$BD$38)/1000/K61 -> 0.38698735 | L64: =-SUM([1]Retail!$O$35,[1]Retail!$R$35:$V$35,[1]Retail!$Y$35,[1]Retail!$AB$35,[1]Retail!$AU$35,[1]Retail!$AX$35,[1]Retail!$BA$35,[1]Retail!$BD$35,[1]Retail!$O$39,[1]Retail!$R$39:$V$39,[1]Retail!$Y$39,[1]Retail!$AB$39,[1]Retail!$AU$39,[1]Retail!$AX$39,[1]Retail!$BA$39,[1]Retail!$BD$39)/1000/L61 -> #DIV/0! | N64: =-SUM([1]SME!$O$33,[1]SME!$R$33:$V$33,[1]SME!$Y$33,[1]SME!$AB$33,[1]SME!$AU$33,[1]SME!$AX$33,[1]SME!$BA$33,[1]SME!$BD$33,[1]SME!$O$37,[1]SME!$R$37:$V$37,[1]SME!$Y$37,[1]SME!$AB$37,[1]SME!$AU$37,[1]SME!$AX$37,[1]SME!$BA$37,[1]SME!$BD$37)/1000/N61 -> 0.30631329 | O64: =-SUM([1]SME!$O$34,[1]SME!$R$34:$V$34,[1]SME!$Y$34,[1]SME!$AB$34,[1]SME!$AU$34,[1]SME!$AX$34,[1]SME!$BA$34,[1]SME!$BD$34,[1]SME!$O$38,[1]SME!$R$38:$V$38,[1]SME!$Y$38,[1]SME!$AB$38,[1]SME!$AU$38,[1]SME!$AX$38,[1]SME!$BA$38,[1]SME!$BD$38)/1000/O61 -> 0.28728672 | P64: =-SUM([1]SME!$O$35,[1]SME!$R$35:$V$35,[1]SME!$Y$35,[1]SME!$AB$35,[1]SME!$AU$35,[1]SME!$AX$35,[1]SME!$BA$35,[1]SME!$BD$35,[1]SME!$O$39,[1]SME!$R$39:$V$39,[1]SME!$Y$39,[1]SME!$AB$39,[1]SME!$AU$39,[1]SME!$AX$39,[1]SME!$BA$39,[1]SME!$BD$39)/1000/P61 -> 0.27026151 | R64: =-SUM([1]MidCorp!$O$33,[1]MidCorp!$R$33:$V$33,[1]MidCorp!$Y$33,[1]MidCorp!$AB$33,[1]MidCorp!$AU$33,[1]MidCorp!$AX$33,[1]MidCorp!$BA$33,[1]MidCorp!$BD$33,[1]MidCorp!$O$37,[1]MidCorp!$R$37:$V$37,[1]MidCorp!$Y$37,[1]MidCorp!$AB$37,[1]MidCorp!$AU$37,[1]MidCorp!$AX$37,[1]MidCorp!$BA$37,[1]MidCorp!$BD$37)/1000/R61 -> 0.28843353 | S64: =-SUM([1]MidCorp!$O$34,[1]MidCorp!$R$34:$V$34,[1]MidCorp!$Y$34,[1]MidCorp!$AB$34,[1]MidCorp!$AU$34,[1]MidCorp!$AX$34,[1]MidCorp!$BA$34,[1]MidCorp!$BD$34,[1]MidCorp!$O$38,[1]MidCorp!$R$38:$V$38,[1]MidCorp!$Y$38,[1]MidCorp!$AB$38,[1]MidCorp!$AU$38,[1]MidCorp!$AX$38,[1]MidCorp!$BA$38,[1]MidCorp!$BD$38)/1000/S61 -> 0.32178496 | T64: =-SUM([1]MidCorp!$O$35,[1]MidCorp!$R$35:$V$35,[1]MidCorp!$Y$35,[1]MidCorp!$AB$35,[1]MidCorp!$AU$35,[1]MidCorp!$AX$35,[1]MidCorp!$BA$35,[1]MidCorp!$BD$35,[1]MidCorp!$O$39,[1]MidCorp!$R$39:$V$39,[1]MidCorp!$Y$39,[1]MidCorp!$AB$39,[1]MidCorp!$AU$39,[1]MidCorp!$AX$39,[1]MidCorp!$BA$39,[1]MidCorp!$BD$39)/1000/T61 -> 0.30113888 | V64: =-SUM([1]MGA!$O$33,[1]MGA!$R$33:$V$33,[1]MGA!$Y$33,[1]MGA!$AB$33,[1]MGA!$AU$33,[1]MGA!$AX$33,[1]MGA!$BA$33,[1]MGA!$BD$33,[1]MGA!$O$37,[1]MGA!$R$37:$V$37,[1]MGA!$Y$37,[1]MGA!$AB$37,[1]MGA!$AU$37,[1]MGA!$AX$37,[1]MGA!$BA$37,[1]MGA!$BD$37)/1000/V61 -> 0.54587951 | W64: =-SUM([1]MGA!$O$34,[1]MGA!$R$34:$V$34,[1]MGA!$Y$34,[1]MGA!$AB$34,[1]MGA!$AU$34,[1]MGA!$AX$34,[1]MGA!$BA$34,[1]MGA!$BD$34,[1]MGA!$O$38,[1]MGA!$R$38:$V$38,[1]MGA!$Y$38,[1]MGA!$AB$38,[1]MGA!$AU$38,[1]MGA!$AX$38,[1]MGA!$BA$38,[1]MGA!$BD$38)/1000/W61 -> 0.38516205 | X64: =-SUM([1]MGA!$O$35,[1]MGA!$R$35:$V$35,[1]MGA!$Y$35,[1]MGA!$AB$35,[1]MGA!$AU$35,[1]MGA!$AX$35,[1]MGA!$BA$35,[1]MGA!$BD$35,[1]MGA!$O$39,[1]MGA!$R$39:$V$39,[1]MGA!$Y$39,[1]MGA!$AB$39,[1]MGA!$AU$39,[1]MGA!$AX$39,[1]MGA!$BA$39,[1]MGA!$BD$39)/1000/X61 -> 0.33847755 | Z64: =-SUM([1]Bancassurance!$O$33,[1]Bancassurance!$R$33:$V$33,[1]Bancassurance!$Y$33,[1]Bancassurance!$AB$33,[1]Bancassurance!$AU$33,[1]Bancassurance!$AX$33,[1]Bancassurance!$BA$33,[1]Bancassurance!$BD$33,[1]Bancassurance!$O$37,[1]Bancassurance!$R$37:$V$37,[1]Bancassurance!$Y$37,[1]Bancassurance!$AB$37,[1]Bancassurance!$AU$37,[1]Bancassurance!$AX$37,[1]Bancassurance!$BA$37,[1]Bancassurance!$BD$37)/1000/Z61 -> 5.3121522 | AA64: =-SUM([1]Bancassurance!$O$34,[1]Bancassurance!$R$34:$V$34,[1]Bancassurance!$Y$34,[1]Bancassurance!$AB$34,[1]Bancassurance!$AU$34,[1]Bancassurance!$AX$34,[1]Bancassurance!$BA$34,[1]Bancassurance!$BD$34,[1]Bancassurance!$O$38,[1]Bancassurance!$R$38:$V$38,[1]Bancassurance!$Y$38,[1]Bancassurance!$AB$38,[1]Bancassurance!$AU$38,[1]Bancassurance!$AX$38,[1]Bancassurance!$BA$38,[1]Bancassurance!$BD$38)/1000/AA61 -> #DIV/0! | AB64: =-SUM([1]Bancassurance!$O$35,[1]Bancassurance!$R$35:$V$35,[1]Bancassurance!$Y$35,[1]Bancassurance!$AB$35,[1]Bancassurance!$AU$35,[1]Bancassurance!$AX$35,[1]Bancassurance!$BA$35,[1]Bancassurance!$BD$35,[1]Bancassurance!$O$39,[1]Bancassurance!$R$39:$V$39,[1]Bancassurance!$Y$39,[1]Bancassurance!$AB$39,[1]Bancassurance!$AU$39,[1]Bancassurance!$AX$39,[1]Bancassurance!$BA$39,[1]Bancassurance!$BD$39)/1000/AB61 -> 0.13896769 | AD64: =-SUM([1]Specials!$O$33,[1]Specials!$R$33:$V$33,[1]Specials!$Y$33,[1]Specials!$AB$33,[1]Specials!$AU$33,[1]Specials!$AX$33,[1]Specials!$BA$33,[1]Specials!$BD$33,[1]Specials!$O$37,[1]Specials!$R$37:$V$37,[1]Specials!$Y$37,[1]Specials!$AB$37,[1]Specials!$AU$37,[1]Specials!$AX$37,[1]Specials!$BA$37,[1]Specials!$BD$37)/1000/AD61 -> 0.055460678 | AE64: =-SUM([1]Specials!$O$34,[1]Specials!$R$34:$V$34,[1]Specials!$Y$34,[1]Specials!$AB$34,[1]Specials!$AU$34,[1]Specials!$AX$34,[1]Specials!$BA$34,[1]Specials!$BD$34,[1]Specials!$O$38,[1]Specials!$R$38:$V$38,[1]Specials!$Y$38,[1]Specials!$AB$38,[1]Specials!$AU$38,[1]Specials!$AX$38,[1]Specials!$BA$38,[1]Specials!$BD$38)/1000/AE61 -> 0.0004473198 | AF64: =-SUM([1]Specials!$O$35,[1]Specials!$R$35:$V$35,[1]Specials!$Y$35,[1]Specials!$AB$35,[1]Specials!$AU$35,[1]Specials!$AX$35,[1]Specials!$BA$35,[1]Specials!$BD$35,[1]Specials!$O$39,[1]Specials!$R$39:$V$39,[1]Specials!$Y$39,[1]Specials!$AB$39,[1]Specials!$AU$39,[1]Specials!$AX$39,[1]Specials!$BA$39,[1]Specials!$BD$39)/1000/AF61 -> #DIV/0! | AH64: =-SUM('[1]Total P&C'!$O$33,'[1]Total P&C'!$R$33:$V$33,'[1]Total P&C'!$Y$33,'[1]Total P&C'!$AB$33,'[1]Total P&C'!$AU$33,'[1]Total P&C'!$AX$33,'[1]Total P&C'!$BA$33,'[1]Total P&C'!$BD$33,'[1]Total P&C'!$O$37,'[1]Total P&C'!$R$37:$V$37,'[1]Total P&C'!$Y$37,'[1]Total P&C'!$AB$37,'[1]Total P&C'!$AU$37,'[1]Total P&C'!$AX$37,'[1]Total P&C'!$BA$37,'[1]Total P&C'!$BD$37)/1000/AH61 -> 0.30376348 | AI64: =-SUM('[1]Total P&C'!$O$34,'[1]Total P&C'!$R$34:$V$34,'[1]Total P&C'!$Y$34,'[1]Total P&C'!$AB$34,'[1]Total P&C'!$AU$34,'[1]Total P&C'!$AX$34,'[1]Total P&C'!$BA$34,'[1]Total P&C'!$BD$34,'[1]Total P&C'!$O$38,'[1]Total P&C'!$R$38:$V$38,'[1]Total P&C'!$Y$38,'[1]Total P&C'!$AB$38,'[1]Total P&C'!$AU$38,'[1]Total P&C'!$AX$38,'[1]Total P&C'!$BA$38,'[1]Total P&C'!$BD$38)/1000/AI61 -> 0.32475321 | AJ64: =-SUM('[1]Total P&C'!$O$35,'[1]Total P&C'!$R$35:$V$35,'[1]Total P&C'!$Y$35,'[1]Total P&C'!$AB$35,'[1]Total P&C'!$AU$35,'[1]Total P&C'!$AX$35,'[1]Total P&C'!$BA$35,'[1]Total P&C'!$BD$35,'[1]Total P&C'!$O$39,'[1]Total P&C'!$R$39:$V$39,'[1]Total P&C'!$Y$39,'[1]Total P&C'!$AB$39,'[1]Total P&C'!$AU$39,'[1]Total P&C'!$AX$39,'[1]Total P&C'!$BA$39,'[1]Total P&C'!$BD$39)/1000/AJ61 -> 0.3004379 | AN64: Attritional | AT64: =-SUM([2]Retail!$O$33,[2]Retail!$R$33:$V$33,[2]Retail!$Y$33,[2]Retail!$AB$33,[2]Retail!$AU$33,[2]Retail!$AX$33,[2]Retail!$BA$33,[2]Retail!$BD$33,[2]Retail!$O$37,[2]Retail!$R$37:$V$37,[2]Retail!$Y$37,[2]Retail!$AB$37,[2]Retail!$AU$37,[2]Retail!$AX$37,[2]Retail!$BA$37,[2]Retail!$BD$37)/1000/AT61 -> 0.45233935 | AU64: =-SUM([2]Retail!$O$34,[2]Retail!$R$34:$V$34,[2]Retail!$Y$34,[2]Retail!$AB$34,[2]Retail!$AU$34,[2]Retail!$AX$34,[2]Retail!$BA$34,[2]Retail!$BD$34,[2]Retail!$O$38,[2]Retail!$R$38:$V$38,[2]Retail!$Y$38,[2]Retail!$AB$38,[2]Retail!$AU$38,[2]Retail!$AX$38,[2]Retail!$BA$38,[2]Retail!$BD$38)/1000/AU61 -> 0.51725816 | AV64: =-SUM([2]Retail!$O$35,[2]Retail!$R$35:$V$35,[2]Retail!$Y$35,[2]Retail!$AB$35,[2]Retail!$AU$35,[2]Retail!$AX$35,[2]Retail!$BA$35,[2]Retail!$BD$35,[2]Retail!$O$39,[2]Retail!$R$39:$V$39,[2]Retail!$Y$39,[2]Retail!$AB$39,[2]Retail!$AU$39,[2]Retail!$AX$39,[2]Retail!$BA$39,[2]Retail!$BD$39)/1000/AV61 -> 0.36284435 | AX64: =-SUM([2]SME!$O$33,[2]SME!$R$33:$V$33,[2]SME!$Y$33,[2]SME!$AB$33,[2]SME!$AU$33,[2]SME!$AX$33,[2]SME!$BA$33,[2]SME!$BD$33,[2]SME!$O$37,[2]SME!$R$37:$V$37,[2]SME!$Y$37,[2]SME!$AB$37,[2]SME!$AU$37,[2]SME!$AX$37,[2]SME!$BA$37,[2]SME!$BD$37)/1000/AX61 -> 0.30858229 | AY64: =-SUM([2]SME!$O$34,[2]SME!$R$34:$V$34,[2]SME!$Y$34,[2]SME!$AB$34,[2]SME!$AU$34,[2]SME!$AX$34,[2]SME!$BA$34,[2]SME!$BD$34,[2]SME!$O$38,[2]SME!$R$38:$V$38,[2]SME!$Y$38,[2]SME!$AB$38,[2]SME!$AU$38,[2]SME!$AX$38,[2]SME!$BA$38,[2]SME!$BD$38)/1000/AY61 -> 0.30081172 | AZ64: =-SUM([2]SME!$O$35,[2]SME!$R$35:$V$35,[2]SME!$Y$35,[2]SME!$AB$35,[2]SME!$AU$35,[2]SME!$AX$35,[2]SME!$BA$35,[2]SME!$BD$35,[2]SME!$O$39,[2]SME!$R$39:$V$39,[2]SME!$Y$39,[2]SME!$AB$39,[2]SME!$AU$39,[2]SME!$AX$39,[2]SME!$BA$39,[2]SME!$BD$39)/1000/AZ61 -> 0.32227933 | BB64: =-SUM([2]MidCorp!$O$33,[2]MidCorp!$R$33:$V$33,[2]MidCorp!$Y$33,[2]MidCorp!$AB$33,[2]MidCorp!$AU$33,[2]MidCorp!$AX$33,[2]MidCorp!$BA$33,[2]MidCorp!$BD$33,[2]MidCorp!$O$37,[2]MidCorp!$R$37:$V$37,[2]MidCorp!$Y$37,[2]MidCorp!$AB$37,[2]MidCorp!$AU$37,[2]MidCorp!$AX$37,[2]MidCorp!$BA$37,[2]MidCorp!$BD$37)/1000/BB61 -> 0.23130088 | BC64: =-SUM([2]MidCorp!$O$34,[2]MidCorp!$R$34:$V$34,[2]MidCorp!$Y$34,[2]MidCorp!$AB$34,[2]MidCorp!$AU$34,[2]MidCorp!$AX$34,[2]MidCorp!$BA$34,[2]MidCorp!$BD$34,[2]MidCorp!$O$38,[2]MidCorp!$R$38:$V$38,[2]MidCorp!$Y$38,[2]MidCorp!$AB$38,[2]MidCorp!$AU$38,[2]MidCorp!$AX$38,[2]MidCorp!$BA$38,[2]MidCorp!$BD$38)/1000/BC61 -> 0.35055755 | BD64: =-SUM([2]MidCorp!$O$35,[2]MidCorp!$R$35:$V$35,[2]MidCorp!$Y$35,[2]MidCorp!$AB$35,[2]MidCorp!$AU$35,[2]MidCorp!$AX$35,[2]MidCorp!$BA$35,[2]MidCorp!$BD$35,[2]MidCorp!$O$39,[2]MidCorp!$R$39:$V$39,[2]MidCorp!$Y$39,[2]MidCorp!$AB$39,[2]MidCorp!$AU$39,[2]MidCorp!$AX$39,[2]MidCorp!$BA$39,[2]MidCorp!$BD$39)/1000/BD61 -> 0.32835875 | BJ64: =-SUM([2]Specials!$O$33,[2]Specials!$R$33:$V$33,[2]Specials!$Y$33,[2]Specials!$AB$33,[2]Specials!$AU$33,[2]Specials!$AX$33,[2]Specials!$BA$33,[2]Specials!$BD$33,[2]Specials!$O$37,[2]Specials!$R$37:$V$37,[2]Specials!$Y$37,[2]Specials!$AB$37,[2]Specials!$AU$37,[2]Specials!$AX$37,[2]Specials!$BA$37,[2]Specials!$BD$37)/1000/BJ61 -> #DIV/0! | BK64: =-SUM([2]Specials!$O$34,[2]Specials!$R$34:$V$34,[2]Specials!$Y$34,[2]Specials!$AB$34,[2]Specials!$AU$34,[2]Specials!$AX$34,[2]Specials!$BA$34,[2]Specials!$BD$34,[2]Specials!$O$38,[2]Specials!$R$38:$V$38,[2]Specials!$Y$38,[2]Specials!$AB$38,[2]Specials!$AU$38,[2]Specials!$AX$38,[2]Specials!$BA$38,[2]Specials!$BD$38)/1000/BK61 -> #DIV/0! | BL64: =-SUM([2]Specials!$O$35,[2]Specials!$R$35:$V$35,[2]Specials!$Y$35,[2]Specials!$AB$35,[2]Specials!$AU$35,[2]Specials!$AX$35,[2]Specials!$BA$35,[2]Specials!$BD$35,[2]Specials!$O$39,[2]Specials!$R$39:$V$39,[2]Specials!$Y$39,[2]Specials!$AB$39,[2]Specials!$AU$39,[2]Specials!$AX$39,[2]Specials!$BA$39,[2]Specials!$BD$39)/1000/BL61 -> #DIV/0! | BN64: =-SUM('[2]Total P&C'!$O$33,'[2]Total P&C'!$R$33:$V$33,'[2]Total P&C'!$Y$33,'[2]Total P&C'!$AB$33,'[2]Total P&C'!$AU$33,'[2]Total P&C'!$AX$33,'[2]Total P&C'!$BA$33,'[2]Total P&C'!$BD$33,'[2]Total P&C'!$O$37,'[2]Total P&C'!$R$37:$V$37,'[2]Total P&C'!$Y$37,'[2]Total P&C'!$AB$37,'[2]Total P&C'!$AU$37,'[2]Total P&C'!$AX$37,'[2]Total P&C'!$BA$37,'[2]Total P&C'!$BD$37)/1000/BN61 -> 0.32864036 | BO64: =-SUM('[2]Total P&C'!$O$34,'[2]Total P&C'!$R$34:$V$34,'[2]Total P&C'!$Y$34,'[2]Total P&C'!$AB$34,'[2]Total P&C'!$AU$34,'[2]Total P&C'!$AX$34,'[2]Total P&C'!$BA$34,'[2]Total P&C'!$BD$34,'[2]Total P&C'!$O$38,'[2]Total P&C'!$R$38:$V$38,'[2]Total P&C'!$Y$38,'[2]Total P&C'!$AB$38,'[2]Total P&C'!$AU$38,'[2]Total P&C'!$AX$38,'[2]Total P&C'!$BA$38,'[2]Total P&C'!$BD$38)/1000/BO61 -> 0.41140841 | BP64: =-SUM('[2]Total P&C'!$O$35,'[2]Total P&C'!$R$35:$V$35,'[2]Total P&C'!$Y$35,'[2]Total P&C'!$AB$35,'[2]Total P&C'!$AU$35,'[2]Total P&C'!$AX$35,'[2]Total P&C'!$BA$35,'[2]Total P&C'!$BD$35,'[2]Total P&C'!$O$39,'[2]Total P&C'!$R$39:$V$39,'[2]Total P&C'!$Y$39,'[2]Total P&C'!$AB$39,'[2]Total P&C'!$AU$39,'[2]Total P&C'!$AX$39,'[2]Total P&C'!$BA$39,'[2]Total P&C'!$BD$39)/1000/BP61 -> 0.34040347 | BR64: =-SUM('[3]Total P&C'!$O$33,'[3]Total P&C'!$R$33:$V$33,'[3]Total P&C'!$Y$33,'[3]Total P&C'!$AB$33,'[3]Total P&C'!$AU$33,'[3]Total P&C'!$AX$33,'[3]Total P&C'!$BA$33,'[3]Total P&C'!$BD$33,'[3]Total P&C'!$O$37,'[3]Total P&C'!$R$37:$V$37,'[3]Total P&C'!$Y$37,'[3]Total P&C'!$AB$37,'[3]Total P&C'!$AU$37,'[3]Total P&C'!$AX$37,'[3]Total P&C'!$BA$37,'[3]Total P&C'!$BD$37)/1000/BR61 -> 0.31270582 | BS64: =-SUM('[3]Total P&C'!$O$34,'[3]Total P&C'!$R$34:$V$34,'[3]Total P&C'!$Y$34,'[3]Total P&C'!$AB$34,'[3]Total P&C'!$AU$34,'[3]Total P&C'!$AX$34,'[3]Total P&C'!$BA$34,'[3]Total P&C'!$BD$34,'[3]Total P&C'!$O$38,'[3]Total P&C'!$R$38:$V$38,'[3]Total P&C'!$Y$38,'[3]Total P&C'!$AB$38,'[3]Total P&C'!$AU$38,'[3]Total P&C'!$AX$38,'[3]Total P&C'!$BA$38,'[3]Total P&C'!$BD$38)/1000/BS61 -> 0.35613813 | BT64: =-SUM('[3]Total P&C'!$O$35,'[3]Total P&C'!$R$35:$V$35,'[3]Total P&C'!$Y$35,'[3]Total P&C'!$AB$35,'[3]Total P&C'!$AU$35,'[3]Total P&C'!$AX$35,'[3]Total P&C'!$BA$35,'[3]Total P&C'!$BD$35,'[3]Total P&C'!$O$39,'[3]Total P&C'!$R$39:$V$39,'[3]Total P&C'!$Y$39,'[3]Total P&C'!$AB$39,'[3]Total P&C'!$AU$39,'[3]Total P&C'!$AX$39,'[3]Total P&C'!$BA$39,'[3]Total P&C'!$BD$39)/1000/BT61 -> 0.31370009
D65: Nat Cat | J65: =-([1]Retail!$P$33+[1]Retail!$W$33+[1]Retail!$AV$33+[1]Retail!$AY$33+[1]Retail!$P$37+[1]Retail!$W$37+[1]Retail!$AV$37+[1]Retail!$AY$37)/1000/J61 -> 0 | K65: =-([1]Retail!$P$34+[1]Retail!$W$34+[1]Retail!$AV$34+[1]Retail!$AY$34+[1]Retail!$P$38+[1]Retail!$W$38+[1]Retail!$AV$38+[1]Retail!$AY$38)/1000/K61 -> 0 | L65: =-([1]Retail!$P$35+[1]Retail!$W$35+[1]Retail!$AV$35+[1]Retail!$AY$35+[1]Retail!$P$39+[1]Retail!$W$39+[1]Retail!$AV$39+[1]Retail!$AY$39)/1000/L61 -> #DIV/0! | N65: =-([1]SME!$P$33+[1]SME!$W$33+[1]SME!$AV$33+[1]SME!$AY$33+[1]SME!$P$37+[1]SME!$W$37+[1]SME!$AV$37+[1]SME!$AY$37)/1000/N61 -> 0.00018637054 | O65: =-([1]SME!$P$34+[1]SME!$W$34+[1]SME!$AV$34+[1]SME!$AY$34+[1]SME!$P$38+[1]SME!$W$38+[1]SME!$AV$38+[1]SME!$AY$38)/1000/O61 -> 0 | P65: =-([1]SME!$P$35+[1]SME!$W$35+[1]SME!$AV$35+[1]SME!$AY$35+[1]SME!$P$39+[1]SME!$W$39+[1]SME!$AV$39+[1]SME!$AY$39)/1000/P61 -> 0.068293426 | R65: =-([1]MidCorp!$P$33+[1]MidCorp!$W$33+[1]MidCorp!$AV$33+[1]MidCorp!$AY$33+[1]MidCorp!$P$37+[1]MidCorp!$W$37+[1]MidCorp!$AV$37+[1]MidCorp!$AY$37)/1000/R61 -> 0.014119558 | S65: =-([1]MidCorp!$P$34+[1]MidCorp!$W$34+[1]MidCorp!$AV$34+[1]MidCorp!$AY$34+[1]MidCorp!$P$38+[1]MidCorp!$W$38+[1]MidCorp!$AV$38+[1]MidCorp!$AY$38)/1000/S61 -> 0 | T65: =-([1]MidCorp!$P$35+[1]MidCorp!$W$35+[1]MidCorp!$AV$35+[1]MidCorp!$AY$35+[1]MidCorp!$P$39+[1]MidCorp!$W$39+[1]MidCorp!$AV$39+[1]MidCorp!$AY$39)/1000/T61 -> 0.06114644 | V65: =-([1]MGA!$P$33+[1]MGA!$W$33+[1]MGA!$AV$33+[1]MGA!$AY$33+[1]MGA!$P$37+[1]MGA!$W$37+[1]MGA!$AV$37+[1]MGA!$AY$37)/1000/V61 -> 0.001625581 | W65: =-([1]MGA!$P$34+[1]MGA!$W$34+[1]MGA!$AV$34+[1]MGA!$AY$34+[1]MGA!$P$38+[1]MGA!$W$38+[1]MGA!$AV$38+[1]MGA!$AY$38)/1000/W61 -> 0 | X65: =-([1]MGA!$P$35+[1]MGA!$W$35+[1]MGA!$AV$35+[1]MGA!$AY$35+[1]MGA!$P$39+[1]MGA!$W$39+[1]MGA!$AV$39+[1]MGA!$AY$39)/1000/X61 -> 0.083227126 | Z65: =-([1]Bancassurance!$P$33+[1]Bancassurance!$W$33+[1]Bancassurance!$AV$33+[1]Bancassurance!$AY$33+[1]Bancassurance!$P$37+[1]Bancassurance!$W$37+[1]Bancassurance!$AV$37+[1]Bancassurance!$AY$37)/1000/Z61 -> 0 | AA65: =-([1]Bancassurance!$P$34+[1]Bancassurance!$W$34+[1]Bancassurance!$AV$34+[1]Bancassurance!$AY$34+[1]Bancassurance!$P$38+[1]Bancassurance!$W$38+[1]Bancassurance!$AV$38+[1]Bancassurance!$AY$38)/1000/AA61 -> #DIV/0! | AB65: =-([1]Bancassurance!$P$35+[1]Bancassurance!$W$35+[1]Bancassurance!$AV$35+[1]Bancassurance!$AY$35+[1]Bancassurance!$P$39+[1]Bancassurance!$W$39+[1]Bancassurance!$AV$39+[1]Bancassurance!$AY$39)/1000/AB61 -> 0.17637626 | AD65: =-([1]Specials!$P$33+[1]Specials!$W$33+[1]Specials!$AV$33+[1]Specials!$AY$33+[1]Specials!$P$37+[1]Specials!$W$37+[1]Specials!$AV$37+[1]Specials!$AY$37)/1000/AD61 -> 0 | AE65: =-([1]Specials!$P$34+[1]Specials!$W$34+[1]Specials!$AV$34+[1]Specials!$AY$34+[1]Specials!$P$38+[1]Specials!$W$38+[1]Specials!$AV$38+[1]Specials!$AY$38)/1000/AE61 -> 0 | AF65: =-([1]Specials!$P$35+[1]Specials!$W$35+[1]Specials!$AV$35+[1]Specials!$AY$35+[1]Specials!$P$39+[1]Specials!$W$39+[1]Specials!$AV$39+[1]Specials!$AY$39)/1000/AF61 -> #DIV/0! | AH65: =-('[1]Total P&C'!$P$33+'[1]Total P&C'!$W$33+'[1]Total P&C'!$AV$33+'[1]Total P&C'!$AY$33+'[1]Total P&C'!$P$37+'[1]Total P&C'!$W$37+'[1]Total P&C'!$AV$37+'[1]Total P&C'!$AY$37)/1000/AH61 -> 0.010678184 | AI65: =-('[1]Total P&C'!$P$34+'[1]Total P&C'!$W$34+'[1]Total P&C'!$AV$34+'[1]Total P&C'!$AY$34+'[1]Total P&C'!$P$38+'[1]Total P&C'!$W$38+'[1]Total P&C'!$AV$38+'[1]Total P&C'!$AY$38)/1000/AI61 -> 0 | AJ65: =-('[1]Total P&C'!$P$35+'[1]Total P&C'!$W$35+'[1]Total P&C'!$AV$35+'[1]Total P&C'!$AY$35+'[1]Total P&C'!$P$39+'[1]Total P&C'!$W$39+'[1]Total P&C'!$AV$39+'[1]Total P&C'!$AY$39)/1000/AJ61 -> 0.064515344 | AN65: Nat Cat | AT65: =-([2]Retail!$P$33+[2]Retail!$W$33+[2]Retail!$AV$33+[2]Retail!$AY$33+[2]Retail!$P$37+[2]Retail!$W$37+[2]Retail!$AV$37+[2]Retail!$AY$37)/1000/AT61 -> 0.011302778 | AU65: =-([2]Retail!$P$34+[2]Retail!$W$34+[2]Retail!$AV$34+[2]Retail!$AY$34+[2]Retail!$P$38+[2]Retail!$W$38+[2]Retail!$AV$38+[2]Retail!$AY$38)/1000/AU61 -> 0 | AV65: =-([2]Retail!$P$35+[2]Retail!$W$35+[2]Retail!$AV$35+[2]Retail!$AY$35+[2]Retail!$P$39+[2]Retail!$W$39+[2]Retail!$AV$39+[2]Retail!$AY$39)/1000/AV61 -> 0.068877998 | AX65: =-([2]SME!$P$33+[2]SME!$W$33+[2]SME!$AV$33+[2]SME!$AY$33+[2]SME!$P$37+[2]SME!$W$37+[2]SME!$AV$37+[2]SME!$AY$37)/1000/AX61 -> 0.0039802694 | AY65: =-([2]SME!$P$34+[2]SME!$W$34+[2]SME!$AV$34+[2]SME!$AY$34+[2]SME!$P$38+[2]SME!$W$38+[2]SME!$AV$38+[2]SME!$AY$38)/1000/AY61 -> 0 | AZ65: =-([2]SME!$P$35+[2]SME!$W$35+[2]SME!$AV$35+[2]SME!$AY$35+[2]SME!$P$39+[2]SME!$W$39+[2]SME!$AV$39+[2]SME!$AY$39)/1000/AZ61 -> 0.068688997 | BB65: =-([2]MidCorp!$P$33+[2]MidCorp!$W$33+[2]MidCorp!$AV$33+[2]MidCorp!$AY$33+[2]MidCorp!$P$37+[2]MidCorp!$W$37+[2]MidCorp!$AV$37+[2]MidCorp!$AY$37)/1000/BB61 -> 0.0045492532 | BC65: =-([2]MidCorp!$P$34+[2]MidCorp!$W$34+[2]MidCorp!$AV$34+[2]MidCorp!$AY$34+[2]MidCorp!$P$38+[2]MidCorp!$W$38+[2]MidCorp!$AV$38+[2]MidCorp!$AY$38)/1000/BC61 -> 0 | BD65: =-([2]MidCorp!$P$35+[2]MidCorp!$W$35+[2]MidCorp!$AV$35+[2]MidCorp!$AY$35+[2]MidCorp!$P$39+[2]MidCorp!$W$39+[2]MidCorp!$AV$39+[2]MidCorp!$AY$39)/1000/BD61 -> 0.047084857 | BJ65: =-([2]Specials!$P$33+[2]Specials!$W$33+[2]Specials!$AV$33+[2]Specials!$AY$33+[2]Specials!$P$37+[2]Specials!$W$37+[2]Specials!$AV$37+[2]Specials!$AY$37)/1000/BJ61 -> #DIV/0! | BK65: =-([2]Specials!$P$34+[2]Specials!$W$34+[2]Specials!$AV$34+[2]Specials!$AY$34+[2]Specials!$P$38+[2]Specials!$W$38+[2]Specials!$AV$38+[2]Specials!$AY$38)/1000/BK61 -> #DIV/0! | BL65: =-([2]Specials!$P$35+[2]Specials!$W$35+[2]Specials!$AV$35+[2]Specials!$AY$35+[2]Specials!$P$39+[2]Specials!$W$39+[2]Specials!$AV$39+[2]Specials!$AY$39)/1000/BL61 -> #DIV/0! | BN65: =-('[2]Total P&C'!$P$33+'[2]Total P&C'!$W$33+'[2]Total P&C'!$AV$33+'[2]Total P&C'!$AY$33+'[2]Total P&C'!$P$37+'[2]Total P&C'!$W$37+'[2]Total P&C'!$AV$37+'[2]Total P&C'!$AY$37)/1000/BN61 -> 0.0071462739 | BO65: =-('[2]Total P&C'!$P$34+'[2]Total P&C'!$W$34+'[2]Total P&C'!$AV$34+'[2]Total P&C'!$AY$34+'[2]Total P&C'!$P$38+'[2]Total P&C'!$W$38+'[2]Total P&C'!$AV$38+'[2]Total P&C'!$AY$38)/1000/BO61 -> 0 | BP65: =-('[2]Total P&C'!$P$35+'[2]Total P&C'!$W$35+'[2]Total P&C'!$AV$35+'[2]Total P&C'!$AY$35+'[2]Total P&C'!$P$39+'[2]Total P&C'!$W$39+'[2]Total P&C'!$AV$39+'[2]Total P&C'!$AY$39)/1000/BP61 -> 0.057794488 | BR65: =-('[3]Total P&C'!$P$33+'[3]Total P&C'!$W$33+'[3]Total P&C'!$AV$33+'[3]Total P&C'!$AY$33+'[3]Total P&C'!$P$37+'[3]Total P&C'!$W$37+'[3]Total P&C'!$AV$37+'[3]Total P&C'!$AY$37)/1000/BR61 -> 0.0094085899 | BS65: =-('[3]Total P&C'!$P$34+'[3]Total P&C'!$W$34+'[3]Total P&C'!$AV$34+'[3]Total P&C'!$AY$34+'[3]Total P&C'!$P$38+'[3]Total P&C'!$W$38+'[3]Total P&C'!$AV$38+'[3]Total P&C'!$AY$38)/1000/BS61 -> 0 | BT65: =-('[3]Total P&C'!$P$35+'[3]Total P&C'!$W$35+'[3]Total P&C'!$AV$35+'[3]Total P&C'!$AY$35+'[3]Total P&C'!$P$39+'[3]Total P&C'!$W$39+'[3]Total P&C'!$AV$39+'[3]Total P&C'!$AY$39)/1000/BT61 -> 0.062285093
D66: Large Losses | J66: =-([1]Retail!$Q$33+[1]Retail!$X$33+[1]Retail!$AW$33+[1]Retail!$AZ$33+[1]Retail!$Q$37+[1]Retail!$X$37+[1]Retail!$AW$37+[1]Retail!$AZ$37)/1000/J61 -> 0 | K66: =-([1]Retail!$Q$34+[1]Retail!$X$34+[1]Retail!$AW$34+[1]Retail!$AZ$34+[1]Retail!$Q$38+[1]Retail!$X$38+[1]Retail!$AW$38+[1]Retail!$AZ$38)/1000/K61 -> 0.035849106 | L66: =-([1]Retail!$Q$35+[1]Retail!$X$35+[1]Retail!$AW$35+[1]Retail!$AZ$35+[1]Retail!$Q$39+[1]Retail!$X$39+[1]Retail!$AW$39+[1]Retail!$AZ$39)/1000/L61 -> #DIV/0! | N66: =-([1]SME!$Q$33+[1]SME!$X$33+[1]SME!$AW$33+[1]SME!$AZ$33+[1]SME!$Q$37+[1]SME!$X$37+[1]SME!$AW$37+[1]SME!$AZ$37)/1000/N61 -> 0.065746895 | O66: =-([1]SME!$Q$34+[1]SME!$X$34+[1]SME!$AW$34+[1]SME!$AZ$34+[1]SME!$Q$38+[1]SME!$X$38+[1]SME!$AW$38+[1]SME!$AZ$38)/1000/O61 -> 0.20919699 | P66: =-([1]SME!$Q$35+[1]SME!$X$35+[1]SME!$AW$35+[1]SME!$AZ$35+[1]SME!$Q$39+[1]SME!$X$39+[1]SME!$AW$39+[1]SME!$AZ$39)/1000/P61 -> 0.16455743 | R66: =-([1]MidCorp!$Q$33+[1]MidCorp!$X$33+[1]MidCorp!$AW$33+[1]MidCorp!$AZ$33+[1]MidCorp!$Q$37+[1]MidCorp!$X$37+[1]MidCorp!$AW$37+[1]MidCorp!$AZ$37)/1000/R61 -> 0.26082203 | S66: =-([1]MidCorp!$Q$34+[1]MidCorp!$X$34+[1]MidCorp!$AW$34+[1]MidCorp!$AZ$34+[1]MidCorp!$Q$38+[1]MidCorp!$X$38+[1]MidCorp!$AW$38+[1]MidCorp!$AZ$38)/1000/S61 -> 0.25212782 | T66: =-([1]MidCorp!$Q$35+[1]MidCorp!$X$35+[1]MidCorp!$AW$35+[1]MidCorp!$AZ$35+[1]MidCorp!$Q$39+[1]MidCorp!$X$39+[1]MidCorp!$AW$39+[1]MidCorp!$AZ$39)/1000/T61 -> 0.23823764 | V66: =-([1]MGA!$Q$33+[1]MGA!$X$33+[1]MGA!$AW$33+[1]MGA!$AZ$33+[1]MGA!$Q$37+[1]MGA!$X$37+[1]MGA!$AW$37+[1]MGA!$AZ$37)/1000/V61 -> 0.18403684 | W66: =-([1]MGA!$Q$34+[1]MGA!$X$34+[1]MGA!$AW$34+[1]MGA!$AZ$34+[1]MGA!$Q$38+[1]MGA!$X$38+[1]MGA!$AW$38+[1]MGA!$AZ$38)/1000/W61 -> 0.088933004 | X66: =-([1]MGA!$Q$35+[1]MGA!$X$35+[1]MGA!$AW$35+[1]MGA!$AZ$35+[1]MGA!$Q$39+[1]MGA!$X$39+[1]MGA!$AW$39+[1]MGA!$AZ$39)/1000/X61 -> 0.078669665 | Z66: =-([1]Bancassurance!$Q$33+[1]Bancassurance!$X$33+[1]Bancassurance!$AW$33+[1]Bancassurance!$AZ$33+[1]Bancassurance!$Q$37+[1]Bancassurance!$X$37+[1]Bancassurance!$AW$37+[1]Bancassurance!$AZ$37)/1000/Z61 -> 0 | AA66: =-([1]Bancassurance!$Q$34+[1]Bancassurance!$X$34+[1]Bancassurance!$AW$34+[1]Bancassurance!$AZ$34+[1]Bancassurance!$Q$38+[1]Bancassurance!$X$38+[1]Bancassurance!$AW$38+[1]Bancassurance!$AZ$38)/1000/AA61 -> #DIV/0! | AB66: =-([1]Bancassurance!$Q$35+[1]Bancassurance!$X$35+[1]Bancassurance!$AW$35+[1]Bancassurance!$AZ$35+[1]Bancassurance!$Q$39+[1]Bancassurance!$X$39+[1]Bancassurance!$AW$39+[1]Bancassurance!$AZ$39)/1000/AB61 -> 0.059 | AD66: =-([1]Specials!$Q$33+[1]Specials!$X$33+[1]Specials!$AW$33+[1]Specials!$AZ$33+[1]Specials!$Q$37+[1]Specials!$X$37+[1]Specials!$AW$37+[1]Specials!$AZ$37)/1000/AD61 -> 0 | AE66: =-([1]Specials!$Q$34+[1]Specials!$X$34+[1]Specials!$AW$34+[1]Specials!$AZ$34+[1]Specials!$Q$38+[1]Specials!$X$38+[1]Specials!$AW$38+[1]Specials!$AZ$38)/1000/AE61 -> 0 | AF66: =-([1]Specials!$Q$35+[1]Specials!$X$35+[1]Specials!$AW$35+[1]Specials!$AZ$35+[1]Specials!$Q$39+[1]Specials!$X$39+[1]Specials!$AW$39+[1]Specials!$AZ$39)/1000/AF61 -> #DIV/0! | AH66: =-('[1]Total P&C'!$Q$33+'[1]Total P&C'!$X$33+'[1]Total P&C'!$AW$33+'[1]Total P&C'!$AZ$33+'[1]Total P&C'!$Q$37+'[1]Total P&C'!$X$37+'[1]Total P&C'!$AW$37+'[1]Total P&C'!$AZ$37)/1000/AH61 -> 0.21674678 | AI66: =-('[1]Total P&C'!$Q$34+'[1]Total P&C'!$X$34+'[1]Total P&C'!$AW$34+'[1]Total P&C'!$AZ$34+'[1]Total P&C'!$Q$38+'[1]Total P&C'!$X$38+'[1]Total P&C'!$AW$38+'[1]Total P&C'!$AZ$38)/1000/AI61 -> 0.23003603 | AJ66: =-('[1]Total P&C'!$Q$35+'[1]Total P&C'!$X$35+'[1]Total P&C'!$AW$35+'[1]Total P&C'!$AZ$35+'[1]Total P&C'!$Q$39+'[1]Total P&C'!$X$39+'[1]Total P&C'!$AW$39+'[1]Total P&C'!$AZ$39)/1000/AJ61 -> 0.21380741 | AN66: Large Losses | AT66: =-([2]Retail!$Q$33+[2]Retail!$X$33+[2]Retail!$AW$33+[2]Retail!$AZ$33+[2]Retail!$Q$37+[2]Retail!$X$37+[2]Retail!$AW$37+[2]Retail!$AZ$37)/1000/AT61 -> 0.02555307 | AU66: =-([2]Retail!$Q$34+[2]Retail!$X$34+[2]Retail!$AW$34+[2]Retail!$AZ$34+[2]Retail!$Q$38+[2]Retail!$X$38+[2]Retail!$AW$38+[2]Retail!$AZ$38)/1000/AU61 -> 0.0391927 | AV66: =-([2]Retail!$Q$35+[2]Retail!$X$35+[2]Retail!$AW$35+[2]Retail!$AZ$35+[2]Retail!$Q$39+[2]Retail!$X$39+[2]Retail!$AW$39+[2]Retail!$AZ$39)/1000/AV61 -> 0.043048681 | AX66: =-([2]SME!$Q$33+[2]SME!$X$33+[2]SME!$AW$33+[2]SME!$AZ$33+[2]SME!$Q$37+[2]SME!$X$37+[2]SME!$AW$37+[2]SME!$AZ$37)/1000/AX61 -> 0.1202925 | AY66: =-([2]SME!$Q$34+[2]SME!$X$34+[2]SME!$AW$34+[2]SME!$AZ$34+[2]SME!$Q$38+[2]SME!$X$38+[2]SME!$AW$38+[2]SME!$AZ$38)/1000/AY61 -> 0.037042149 | AZ66: =-([2]SME!$Q$35+[2]SME!$X$35+[2]SME!$AW$35+[2]SME!$AZ$35+[2]SME!$Q$39+[2]SME!$X$39+[2]SME!$AW$39+[2]SME!$AZ$39)/1000/AZ61 -> 0.073780373 | BB66: =-([2]MidCorp!$Q$33+[2]MidCorp!$X$33+[2]MidCorp!$AW$33+[2]MidCorp!$AZ$33+[2]MidCorp!$Q$37+[2]MidCorp!$X$37+[2]MidCorp!$AW$37+[2]MidCorp!$AZ$37)/1000/BB61 -> 0.12185559 | BC66: =-([2]MidCorp!$Q$34+[2]MidCorp!$X$34+[2]MidCorp!$AW$34+[2]MidCorp!$AZ$34+[2]MidCorp!$Q$38+[2]MidCorp!$X$38+[2]MidCorp!$AW$38+[2]MidCorp!$AZ$38)/1000/BC61 -> 0.051475451 | BD66: =-([2]MidCorp!$Q$35+[2]MidCorp!$X$35+[2]MidCorp!$AW$35+[2]MidCorp!$AZ$35+[2]MidCorp!$Q$39+[2]MidCorp!$X$39+[2]MidCorp!$AW$39+[2]MidCorp!$AZ$39)/1000/BD61 -> 0.11750706 | BJ66: =-([2]Specials!$Q$33+[2]Specials!$X$33+[2]Specials!$AW$33+[2]Specials!$AZ$33+[2]Specials!$Q$37+[2]Specials!$X$37+[2]Specials!$AW$37+[2]Specials!$AZ$37)/1000/BJ61 -> #DIV/0! | BK66: =-([2]Specials!$Q$34+[2]Specials!$X$34+[2]Specials!$AW$34+[2]Specials!$AZ$34+[2]Specials!$Q$38+[2]Specials!$X$38+[2]Specials!$AW$38+[2]Specials!$AZ$38)/1000/BK61 -> #DIV/0! | BL66: =-([2]Specials!$Q$35+[2]Specials!$X$35+[2]Specials!$AW$35+[2]Specials!$AZ$35+[2]Specials!$Q$39+[2]Specials!$X$39+[2]Specials!$AW$39+[2]Specials!$AZ$39)/1000/BL61 -> #DIV/0! | BN66: =-('[2]Total P&C'!$Q$33+'[2]Total P&C'!$X$33+'[2]Total P&C'!$AW$33+'[2]Total P&C'!$AZ$33+'[2]Total P&C'!$Q$37+'[2]Total P&C'!$X$37+'[2]Total P&C'!$AW$37+'[2]Total P&C'!$AZ$37)/1000/BN61 -> 0.083577971 | BO66: =-('[2]Total P&C'!$Q$34+'[2]Total P&C'!$X$34+'[2]Total P&C'!$AW$34+'[2]Total P&C'!$AZ$34+'[2]Total P&C'!$Q$38+'[2]Total P&C'!$X$38+'[2]Total P&C'!$AW$38+'[2]Total P&C'!$AZ$38)/1000/BO61 -> 0.044555401 | BP66: =-('[2]Total P&C'!$Q$35+'[2]Total P&C'!$X$35+'[2]Total P&C'!$AW$35+'[2]Total P&C'!$AZ$35+'[2]Total P&C'!$Q$39+'[2]Total P&C'!$X$39+'[2]Total P&C'!$AW$39+'[2]Total P&C'!$AZ$39)/1000/BP61 -> 0.084579449 | BR66: =-('[3]Total P&C'!$Q$33+'[3]Total P&C'!$X$33+'[3]Total P&C'!$AW$33+'[3]Total P&C'!$AZ$33+'[3]Total P&C'!$Q$37+'[3]Total P&C'!$X$37+'[3]Total P&C'!$AW$37+'[3]Total P&C'!$AZ$37)/1000/BR61 -> 0.1688774 | BS66: =-('[3]Total P&C'!$Q$34+'[3]Total P&C'!$X$34+'[3]Total P&C'!$AW$34+'[3]Total P&C'!$AZ$34+'[3]Total P&C'!$Q$38+'[3]Total P&C'!$X$38+'[3]Total P&C'!$AW$38+'[3]Total P&C'!$AZ$38)/1000/BS61 -> 0.16285835 | BT66: =-('[3]Total P&C'!$Q$35+'[3]Total P&C'!$X$35+'[3]Total P&C'!$AW$35+'[3]Total P&C'!$AZ$35+'[3]Total P&C'!$Q$39+'[3]Total P&C'!$X$39+'[3]Total P&C'!$AW$39+'[3]Total P&C'!$AZ$39)/1000/BT61 -> 0.17092436
D67: Others | J67: =-([1]Retail!$AT$33+[1]Retail!$AT$37)/1000/J61 -> 0.0017178234 | K67: =-([1]Retail!$AT$34+[1]Retail!$AT$38)/1000/K61 -> 0.2503878 | L67: =-([1]Retail!$AT$35+[1]Retail!$AT$39)/1000/L61 -> #DIV/0! | N67: =-([1]SME!$AT$33+[1]SME!$AT$37)/1000/N61 -> 0.070849594 | O67: =-([1]SME!$AT$34+[1]SME!$AT$38)/1000/O61 -> 0.064739505 | P67: =-([1]SME!$AT$35+[1]SME!$AT$39)/1000/P61 -> 0.078167883 | R67: =-([1]MidCorp!$AT$33+[1]MidCorp!$AT$37)/1000/R61 -> 0.089522715 | S67: =-([1]MidCorp!$AT$34+[1]MidCorp!$AT$38)/1000/S61 -> 0.092958745 | T67: =-([1]MidCorp!$AT$35+[1]MidCorp!$AT$39)/1000/T61 -> 0.090491596 | V67: =-([1]MGA!$AT$33+[1]MGA!$AT$37)/1000/V61 -> 0.12034088 | W67: =-([1]MGA!$AT$34+[1]MGA!$AT$38)/1000/W61 -> 0.11694252 | X67: =-([1]MGA!$AT$35+[1]MGA!$AT$39)/1000/X61 -> 0.072480154 | Z67: =-([1]Bancassurance!$AT$33+[1]Bancassurance!$AT$37)/1000/Z61 -> 0.7903084 | AA67: =-([1]Bancassurance!$AT$34+[1]Bancassurance!$AT$38)/1000/AA61 -> #DIV/0! | AB67: =-([1]Bancassurance!$AT$35+[1]Bancassurance!$AT$39)/1000/AB61 -> 0.063479826 | AD67: =-([1]Specials!$AT$33+[1]Specials!$AT$37)/1000/AD61 -> 0.72763126 | AE67: =-([1]Specials!$AT$34+[1]Specials!$AT$38)/1000/AE61 -> 0.76696851 | AF67: =-([1]Specials!$AT$35+[1]Specials!$AT$39)/1000/AF61 -> #DIV/0! | AH67: =-('[1]Total P&C'!$AT$33+'[1]Total P&C'!$AT$37)/1000/AH61 -> 0.086577766 | AI67: =-('[1]Total P&C'!$AT$34+'[1]Total P&C'!$AT$38)/1000/AI61 -> 0.094011681 | AJ67: =-('[1]Total P&C'!$AT$35+'[1]Total P&C'!$AT$39)/1000/AJ61 -> 0.0871749 | AN67: Others | AT67: =-([2]Retail!$AT$33+[2]Retail!$AT$37)/1000/AT61 -> 0.099041716 | AU67: =-([2]Retail!$AT$34+[2]Retail!$AT$38)/1000/AU61 -> 0.10269424 | AV67: =-([2]Retail!$AT$35+[2]Retail!$AT$39)/1000/AV61 -> 0.10370305 | AX67: =-([2]SME!$AT$33+[2]SME!$AT$37)/1000/AX61 -> 0.13950764 | AY67: =-([2]SME!$AT$34+[2]SME!$AT$38)/1000/AY61 -> 0.093196293 | AZ67: =-([2]SME!$AT$35+[2]SME!$AT$39)/1000/AZ61 -> 0.14160611 | BB67: =-([2]MidCorp!$AT$33+[2]MidCorp!$AT$37)/1000/BB61 -> 0.12233099 | BC67: =-([2]MidCorp!$AT$34+[2]MidCorp!$AT$38)/1000/BC61 -> 0.13961197 | BD67: =-([2]MidCorp!$AT$35+[2]MidCorp!$AT$39)/1000/BD61 -> 0.11150402 | BJ67: =-([2]Specials!$AT$33+[2]Specials!$AT$37)/1000/BJ61 -> #DIV/0! | BK67: =-([2]Specials!$AT$34+[2]Specials!$AT$38)/1000/BK61 -> #DIV/0! | BL67: =-([2]Specials!$AT$35+[2]Specials!$AT$39)/1000/BL61 -> #DIV/0! | BN67: =-('[2]Total P&C'!$AT$33+'[2]Total P&C'!$AT$37)/1000/BN61 -> 0.11533303 | BO67: =-('[2]Total P&C'!$AT$34+'[2]Total P&C'!$AT$38)/1000/BO61 -> 0.11840422 | BP67: =-('[2]Total P&C'!$AT$35+'[2]Total P&C'!$AT$39)/1000/BP61 -> 0.11227681 | BR67: =-('[3]Total P&C'!$AT$33+'[3]Total P&C'!$AT$37)/1000/BR61 -> 0.096914245 | BS67: =-('[3]Total P&C'!$AT$34+'[3]Total P&C'!$AT$38)/1000/BS61 -> 0.10284621 | BT67: =-('[3]Total P&C'!$AT$35+'[3]Total P&C'!$AT$39)/1000/BT61 -> 0.095504726
D68: Discounting a.y. | J68: =-([1]Retail!$Z$33+[1]Retail!$AA$33+[1]Retail!$BB$33+[1]Retail!$BC$33+[1]Retail!$Z$37+[1]Retail!$AA$37+[1]Retail!$BB$37+[1]Retail!$BC$37)/1000/J61 -> -0.0010734641 | K68: =-([1]Retail!$Z$34+[1]Retail!$AA$34+[1]Retail!$BB$34+[1]Retail!$BC$34+[1]Retail!$Z$38+[1]Retail!$AA$38+[1]Retail!$BB$38+[1]Retail!$BC$38)/1000/K61 -> -0.0086478312 | L68: =-([1]Retail!$Z$35+[1]Retail!$AA$35+[1]Retail!$BB$35+[1]Retail!$BC$35+[1]Retail!$Z$39+[1]Retail!$AA$39+[1]Retail!$BB$39+[1]Retail!$BC$39)/1000/L61 -> #DIV/0! | N68: =-([1]SME!$Z$33+[1]SME!$AA$33+[1]SME!$BB$33+[1]SME!$BC$33+[1]SME!$Z$37+[1]SME!$AA$37+[1]SME!$BB$37+[1]SME!$BC$37)/1000/N61 -> -0.0068244353 | O68: =-([1]SME!$Z$34+[1]SME!$AA$34+[1]SME!$BB$34+[1]SME!$BC$34+[1]SME!$Z$38+[1]SME!$AA$38+[1]SME!$BB$38+[1]SME!$BC$38)/1000/O61 -> -0.0099913949 | P68: =-([1]SME!$Z$35+[1]SME!$AA$35+[1]SME!$BB$35+[1]SME!$BC$35+[1]SME!$Z$39+[1]SME!$AA$39+[1]SME!$BB$39+[1]SME!$BC$39)/1000/P61 -> -0.004300289 | R68: =-([1]MidCorp!$Z$33+[1]MidCorp!$AA$33+[1]MidCorp!$BB$33+[1]MidCorp!$BC$33+[1]MidCorp!$Z$37+[1]MidCorp!$AA$37+[1]MidCorp!$BB$37+[1]MidCorp!$BC$37)/1000/R61 -> -0.012240257 | S68: =-([1]MidCorp!$Z$34+[1]MidCorp!$AA$34+[1]MidCorp!$BB$34+[1]MidCorp!$BC$34+[1]MidCorp!$Z$38+[1]MidCorp!$AA$38+[1]MidCorp!$BB$38+[1]MidCorp!$BC$38)/1000/S61 -> -0.013432555 | T68: =-([1]MidCorp!$Z$35+[1]MidCorp!$AA$35+[1]MidCorp!$BB$35+[1]MidCorp!$BC$35+[1]MidCorp!$Z$39+[1]MidCorp!$AA$39+[1]MidCorp!$BB$39+[1]MidCorp!$BC$39)/1000/T61 -> -0.0057100123 | V68: =-([1]MGA!$Z$33+[1]MGA!$AA$33+[1]MGA!$BB$33+[1]MGA!$BC$33+[1]MGA!$Z$37+[1]MGA!$AA$37+[1]MGA!$BB$37+[1]MGA!$BC$37)/1000/V61 -> -0.0099615028 | W68: =-([1]MGA!$Z$34+[1]MGA!$AA$34+[1]MGA!$BB$34+[1]MGA!$BC$34+[1]MGA!$Z$38+[1]MGA!$AA$38+[1]MGA!$BB$38+[1]MGA!$BC$38)/1000/W61 -> -0.0084117133 | X68: =-([1]MGA!$Z$35+[1]MGA!$AA$35+[1]MGA!$BB$35+[1]MGA!$BC$35+[1]MGA!$Z$39+[1]MGA!$AA$39+[1]MGA!$BB$39+[1]MGA!$BC$39)/1000/X61 -> -0.0034017973 | Z68: =-([1]Bancassurance!$Z$33+[1]Bancassurance!$AA$33+[1]Bancassurance!$BB$33+[1]Bancassurance!$BC$33+[1]Bancassurance!$Z$37+[1]Bancassurance!$AA$37+[1]Bancassurance!$BB$37+[1]Bancassurance!$BC$37)/1000/Z61 -> -0.024863922 | AA68: =-([1]Bancassurance!$Z$34+[1]Bancassurance!$AA$34+[1]Bancassurance!$BB$34+[1]Bancassurance!$BC$34+[1]Bancassurance!$Z$38+[1]Bancassurance!$AA$38+[1]Bancassurance!$BB$38+[1]Bancassurance!$BC$38)/1000/AA61 -> #DIV/0! | AB68: =-([1]Bancassurance!$Z$35+[1]Bancassurance!$AA$35+[1]Bancassurance!$BB$35+[1]Bancassurance!$BC$35+[1]Bancassurance!$Z$39+[1]Bancassurance!$AA$39+[1]Bancassurance!$BB$39+[1]Bancassurance!$BC$39)/1000/AB61 -> -0.0069539593 | AD68: =-([1]Specials!$Z$33+[1]Specials!$AA$33+[1]Specials!$BB$33+[1]Specials!$BC$33+[1]Specials!$Z$37+[1]Specials!$AA$37+[1]Specials!$BB$37+[1]Specials!$BC$37)/1000/AD61 -> -0.0017028532 | AE68: =-([1]Specials!$Z$34+[1]Specials!$AA$34+[1]Specials!$BB$34+[1]Specials!$BC$34+[1]Specials!$Z$38+[1]Specials!$AA$38+[1]Specials!$BB$38+[1]Specials!$BC$38)/1000/AE61 -> 0 | AF68: =-([1]Specials!$Z$35+[1]Specials!$AA$35+[1]Specials!$BB$35+[1]Specials!$BC$35+[1]Specials!$Z$39+[1]Specials!$AA$39+[1]Specials!$BB$39+[1]Specials!$BC$39)/1000/AF61 -> #DIV/0! | AH68: =-('[1]Total P&C'!$Z$33+'[1]Total P&C'!$AA$33+'[1]Total P&C'!$BB$33+'[1]Total P&C'!$BC$33+'[1]Total P&C'!$Z$37+'[1]Total P&C'!$AA$37+'[1]Total P&C'!$BB$37+'[1]Total P&C'!$BC$37)/1000/AH61 -> -0.010924673 | AI68: =-('[1]Total P&C'!$Z$34+'[1]Total P&C'!$AA$34+'[1]Total P&C'!$BB$34+'[1]Total P&C'!$BC$34+'[1]Total P&C'!$Z$38+'[1]Total P&C'!$AA$38+'[1]Total P&C'!$BB$38+'[1]Total P&C'!$BC$38)/1000/AI61 -> -0.012431764 | AJ68: =-('[1]Total P&C'!$Z$35+'[1]Total P&C'!$AA$35+'[1]Total P&C'!$BB$35+'[1]Total P&C'!$BC$35+'[1]Total P&C'!$Z$39+'[1]Total P&C'!$AA$39+'[1]Total P&C'!$BB$39+'[1]Total P&C'!$BC$39)/1000/AJ61 -> -0.0053277564 | AN68: Discounting a.y. | AT68: =-([2]Retail!$Z$33+[2]Retail!$AA$33+[2]Retail!$BB$33+[2]Retail!$BC$33+[2]Retail!$Z$37+[2]Retail!$AA$37+[2]Retail!$BB$37+[2]Retail!$BC$37)/1000/AT61 -> -0.013046385 | AU68: =-([2]Retail!$Z$34+[2]Retail!$AA$34+[2]Retail!$BB$34+[2]Retail!$BC$34+[2]Retail!$Z$38+[2]Retail!$AA$38+[2]Retail!$BB$38+[2]Retail!$BC$38)/1000/AU61 -> -0.014973579 | AV68: =-([2]Retail!$Z$35+[2]Retail!$AA$35+[2]Retail!$BB$35+[2]Retail!$BC$35+[2]Retail!$Z$39+[2]Retail!$AA$39+[2]Retail!$BB$39+[2]Retail!$BC$39)/1000/AV61 -> -0.0063464253 | AX68: =-([2]SME!$Z$33+[2]SME!$AA$33+[2]SME!$BB$33+[2]SME!$BC$33+[2]SME!$Z$37+[2]SME!$AA$37+[2]SME!$BB$37+[2]SME!$BC$37)/1000/AX61 -> -0.012174786 | AY68: =-([2]SME!$Z$34+[2]SME!$AA$34+[2]SME!$BB$34+[2]SME!$BC$34+[2]SME!$Z$38+[2]SME!$AA$38+[2]SME!$BB$38+[2]SME!$BC$38)/1000/AY61 -> -0.0093565211 | AZ68: =-([2]SME!$Z$35+[2]SME!$AA$35+[2]SME!$BB$35+[2]SME!$BC$35+[2]SME!$Z$39+[2]SME!$AA$39+[2]SME!$BB$39+[2]SME!$BC$39)/1000/AZ61 -> -0.0066127944 | BB68: =-([2]MidCorp!$Z$33+[2]MidCorp!$AA$33+[2]MidCorp!$BB$33+[2]MidCorp!$BC$33+[2]MidCorp!$Z$37+[2]MidCorp!$AA$37+[2]MidCorp!$BB$37+[2]MidCorp!$BC$37)/1000/BB61 -> -0.015005039 | BC68: =-([2]MidCorp!$Z$34+[2]MidCorp!$AA$34+[2]MidCorp!$BB$34+[2]MidCorp!$BC$34+[2]MidCorp!$Z$38+[2]MidCorp!$AA$38+[2]MidCorp!$BB$38+[2]MidCorp!$BC$38)/1000/BC61 -> -0.01624796 | BD68: =-([2]MidCorp!$Z$35+[2]MidCorp!$AA$35+[2]MidCorp!$BB$35+[2]MidCorp!$BC$35+[2]MidCorp!$Z$39+[2]MidCorp!$AA$39+[2]MidCorp!$BB$39+[2]MidCorp!$BC$39)/1000/BD61 -> -0.010883175 | BJ68: =-([2]Specials!$Z$33+[2]Specials!$AA$33+[2]Specials!$BB$33+[2]Specials!$BC$33+[2]Specials!$Z$37+[2]Specials!$AA$37+[2]Specials!$BB$37+[2]Specials!$BC$37)/1000/BJ61 -> #DIV/0! | BK68: =-([2]Specials!$Z$34+[2]Specials!$AA$34+[2]Specials!$BB$34+[2]Specials!$BC$34+[2]Specials!$Z$38+[2]Specials!$AA$38+[2]Specials!$BB$38+[2]Specials!$BC$38)/1000/BK61 -> #DIV/0! | BL68: =-([2]Specials!$Z$35+[2]Specials!$AA$35+[2]Specials!$BB$35+[2]Specials!$BC$35+[2]Specials!$Z$39+[2]Specials!$AA$39+[2]Specials!$BB$39+[2]Specials!$BC$39)/1000/BL61 -> #DIV/0! | BN68: =-('[2]Total P&C'!$Z$33+'[2]Total P&C'!$AA$33+'[2]Total P&C'!$BB$33+'[2]Total P&C'!$BC$33+'[2]Total P&C'!$Z$37+'[2]Total P&C'!$AA$37+'[2]Total P&C'!$BB$37+'[2]Total P&C'!$BC$37)/1000/BN61 -> -0.013866428 | BO68: =-('[2]Total P&C'!$Z$34+'[2]Total P&C'!$AA$34+'[2]Total P&C'!$BB$34+'[2]Total P&C'!$BC$34+'[2]Total P&C'!$Z$38+'[2]Total P&C'!$AA$38+'[2]Total P&C'!$BB$38+'[2]Total P&C'!$BC$38)/1000/BO61 -> -0.01480384 | BP68: =-('[2]Total P&C'!$Z$35+'[2]Total P&C'!$AA$35+'[2]Total P&C'!$BB$35+'[2]Total P&C'!$BC$35+'[2]Total P&C'!$Z$39+'[2]Total P&C'!$AA$39+'[2]Total P&C'!$BB$39+'[2]Total P&C'!$BC$39)/1000/BP61 -> -0.0086813555 | BR68: =-('[3]Total P&C'!$Z$33+'[3]Total P&C'!$AA$33+'[3]Total P&C'!$BB$33+'[3]Total P&C'!$BC$33+'[3]Total P&C'!$Z$37+'[3]Total P&C'!$AA$37+'[3]Total P&C'!$BB$37+'[3]Total P&C'!$BC$37)/1000/BR61 -> -0.011982128 | BS68: =-('[3]Total P&C'!$Z$34+'[3]Total P&C'!$AA$34+'[3]Total P&C'!$BB$34+'[3]Total P&C'!$BC$34+'[3]Total P&C'!$Z$38+'[3]Total P&C'!$AA$38+'[3]Total P&C'!$BB$38+'[3]Total P&C'!$BC$38)/1000/BS61 -> -0.013290886 | BT68: =-('[3]Total P&C'!$Z$35+'[3]Total P&C'!$AA$35+'[3]Total P&C'!$BB$35+'[3]Total P&C'!$BC$35+'[3]Total P&C'!$Z$39+'[3]Total P&C'!$AA$39+'[3]Total P&C'!$BB$39+'[3]Total P&C'!$BC$39)/1000/BT61 -> -0.0064406158
D69: Run-off + ReR | J69: =-SUM([1]Retail!$AC$33:$AI$33,[1]Retail!$BE$33:$BG$33,[1]Retail!$AC$37:$AI$37,[1]Retail!$BE$37:$BG$37)/1000/J61 -> -0.0056902932 | K69: =-SUM([1]Retail!$AC$34:$AI$34,[1]Retail!$BE$34:$BG$34,[1]Retail!$AC$38:$AI$38,[1]Retail!$BE$38:$BG$38)/1000/K61 -> -0.087631649 | L69: =-SUM([1]Retail!$AC$35:$AI$35,[1]Retail!$BE$35:$BG$35,[1]Retail!$AC$39:$AI$39,[1]Retail!$BE$39:$BG$39)/1000/L61 -> #DIV/0! | N69: =-SUM([1]SME!$AC$33:$AI$33,[1]SME!$BE$33:$BG$33,[1]SME!$AC$37:$AI$37,[1]SME!$BE$37:$BG$37)/1000/N61 -> 0.26692142 | O69: =-SUM([1]SME!$AC$34:$AI$34,[1]SME!$BE$34:$BG$34,[1]SME!$AC$38:$AI$38,[1]SME!$BE$38:$BG$38)/1000/O61 -> -0.1681299 | P69: =-SUM([1]SME!$AC$35:$AI$35,[1]SME!$BE$35:$BG$35,[1]SME!$AC$39:$AI$39,[1]SME!$BE$39:$BG$39)/1000/P61 -> -0.022571271 | R69: =-SUM([1]MidCorp!$AC$33:$AI$33,[1]MidCorp!$BE$33:$BG$33,[1]MidCorp!$AC$37:$AI$37,[1]MidCorp!$BE$37:$BG$37)/1000/R61 -> -0.055824286 | S69: =-SUM([1]MidCorp!$AC$34:$AI$34,[1]MidCorp!$BE$34:$BG$34,[1]MidCorp!$AC$38:$AI$38,[1]MidCorp!$BE$38:$BG$38)/1000/S61 -> 0.014814153 | T69: =-SUM([1]MidCorp!$AC$35:$AI$35,[1]MidCorp!$BE$35:$BG$35,[1]MidCorp!$AC$39:$AI$39,[1]MidCorp!$BE$39:$BG$39)/1000/T61 -> -0.018961564 | V69: =-SUM([1]MGA!$AC$33:$AI$33,[1]MGA!$BE$33:$BG$33,[1]MGA!$AC$37:$AI$37,[1]MGA!$BE$37:$BG$37)/1000/V61 -> -0.35311617 | W69: =-SUM([1]MGA!$AC$34:$AI$34,[1]MGA!$BE$34:$BG$34,[1]MGA!$AC$38:$AI$38,[1]MGA!$BE$38:$BG$38)/1000/W61 -> 0.043431778 | X69: =-SUM([1]MGA!$AC$35:$AI$35,[1]MGA!$BE$35:$BG$35,[1]MGA!$AC$39:$AI$39,[1]MGA!$BE$39:$BG$39)/1000/X61 -> -0.069393506 | Z69: =-SUM([1]Bancassurance!$AC$33:$AI$33,[1]Bancassurance!$BE$33:$BG$33,[1]Bancassurance!$AC$37:$AI$37,[1]Bancassurance!$BE$37:$BG$37)/1000/Z61 -> -0.068803544 | AA69: =-SUM([1]Bancassurance!$AC$34:$AI$34,[1]Bancassurance!$BE$34:$BG$34,[1]Bancassurance!$AC$38:$AI$38,[1]Bancassurance!$BE$38:$BG$38)/1000/AA61 -> #DIV/0! | AB69: =-SUM([1]Bancassurance!$AC$35:$AI$35,[1]Bancassurance!$BE$35:$BG$35,[1]Bancassurance!$AC$39:$AI$39,[1]Bancassurance!$BE$39:$BG$39)/1000/AB61 -> -0.010756838 | AD69: =-SUM([1]Specials!$AC$33:$AI$33,[1]Specials!$BE$33:$BG$33,[1]Specials!$AC$37:$AI$37,[1]Specials!$BE$37:$BG$37)/1000/AD61 -> -1.0923748 | AE69: =-SUM([1]Specials!$AC$34:$AI$34,[1]Specials!$BE$34:$BG$34,[1]Specials!$AC$38:$AI$38,[1]Specials!$BE$38:$BG$38)/1000/AE61 -> 2.2455282 | AF69: =-SUM([1]Specials!$AC$35:$AI$35,[1]Specials!$BE$35:$BG$35,[1]Specials!$AC$39:$AI$39,[1]Specials!$BE$39:$BG$39)/1000/AF61 -> #DIV/0! | AH69: =-SUM('[1]Total P&C'!$AC$33:$AI$33,'[1]Total P&C'!$BE$33:$BG$33,'[1]Total P&C'!$AC$37:$AI$37,'[1]Total P&C'!$BE$37:$BG$37)/1000/AH61 -> -0.016835227 | AI69: =-SUM('[1]Total P&C'!$AC$34:$AI$34,'[1]Total P&C'!$BE$34:$BG$34,'[1]Total P&C'!$AC$38:$AI$38,'[1]Total P&C'!$BE$38:$BG$38)/1000/AI61 -> -0.017951213 | AJ69: =-SUM('[1]Total P&C'!$AC$35:$AI$35,'[1]Total P&C'!$BE$35:$BG$35,'[1]Total P&C'!$AC$39:$AI$39,'[1]Total P&C'!$BE$39:$BG$39)/1000/AJ61 -> -0.023800623 | AN69: Run-off + ReR | AT69: =-SUM([2]Retail!$AC$33:$AI$33,[2]Retail!$BE$33:$BG$33,[2]Retail!$AC$37:$AI$37,[2]Retail!$BE$37:$BG$37)/1000/AT61 -> -0.057492802 | AU69: =-SUM([2]Retail!$AC$34:$AI$34,[2]Retail!$BE$34:$BG$34,[2]Retail!$AC$38:$AI$38,[2]Retail!$BE$38:$BG$38)/1000/AU61 -> -0.18464274 | AV69: =-SUM([2]Retail!$AC$35:$AI$35,[2]Retail!$BE$35:$BG$35,[2]Retail!$AC$39:$AI$39,[2]Retail!$BE$39:$BG$39)/1000/AV61 -> -0.0085187506 | AX69: =-SUM([2]SME!$AC$33:$AI$33,[2]SME!$BE$33:$BG$33,[2]SME!$AC$37:$AI$37,[2]SME!$BE$37:$BG$37)/1000/AX61 -> -0.03454821 | AY69: =-SUM([2]SME!$AC$34:$AI$34,[2]SME!$BE$34:$BG$34,[2]SME!$AC$38:$AI$38,[2]SME!$BE$38:$BG$38)/1000/AY61 -> -0.42847915 | AZ69: =-SUM([2]SME!$AC$35:$AI$35,[2]SME!$BE$35:$BG$35,[2]SME!$AC$39:$AI$39,[2]SME!$BE$39:$BG$39)/1000/AZ61 -> -0.007584006 | BB69: =-SUM([2]MidCorp!$AC$33:$AI$33,[2]MidCorp!$BE$33:$BG$33,[2]MidCorp!$AC$37:$AI$37,[2]MidCorp!$BE$37:$BG$37)/1000/BB61 -> 0.15085301 | BC69: =-SUM([2]MidCorp!$AC$34:$AI$34,[2]MidCorp!$BE$34:$BG$34,[2]MidCorp!$AC$38:$AI$38,[2]MidCorp!$BE$38:$BG$38)/1000/BC61 -> 0.17087093 | BD69: =-SUM([2]MidCorp!$AC$35:$AI$35,[2]MidCorp!$BE$35:$BG$35,[2]MidCorp!$AC$39:$AI$39,[2]MidCorp!$BE$39:$BG$39)/1000/BD61 -> -0.00563436 | BJ69: =-SUM([2]Specials!$AC$33:$AI$33,[2]Specials!$BE$33:$BG$33,[2]Specials!$AC$37:$AI$37,[2]Specials!$BE$37:$BG$37)/1000/BJ61 -> #DIV/0! | BK69: =-SUM([2]Specials!$AC$34:$AI$34,[2]Specials!$BE$34:$BG$34,[2]Specials!$AC$38:$AI$38,[2]Specials!$BE$38:$BG$38)/1000/BK61 -> #DIV/0! | BL69: =-SUM([2]Specials!$AC$35:$AI$35,[2]Specials!$BE$35:$BG$35,[2]Specials!$AC$39:$AI$39,[2]Specials!$BE$39:$BG$39)/1000/BL61 -> #DIV/0! | BN69: =-SUM('[2]Total P&C'!$AC$33:$AI$33,'[2]Total P&C'!$BE$33:$BG$33,'[2]Total P&C'!$AC$37:$AI$37,'[2]Total P&C'!$BE$37:$BG$37)/1000/BN61 -> 0.044619415 | BO69: =-SUM('[2]Total P&C'!$AC$34:$AI$34,'[2]Total P&C'!$BE$34:$BG$34,'[2]Total P&C'!$AC$38:$AI$38,'[2]Total P&C'!$BE$38:$BG$38)/1000/BO61 -> -0.053869958 | BP69: =-SUM('[2]Total P&C'!$AC$35:$AI$35,'[2]Total P&C'!$BE$35:$BG$35,'[2]Total P&C'!$AC$39:$AI$39,'[2]Total P&C'!$BE$39:$BG$39)/1000/BP61 -> -0.0069410563 | BR69: =-SUM('[3]Total P&C'!$AC$33:$AI$33,'[3]Total P&C'!$BE$33:$BG$33,'[3]Total P&C'!$AC$37:$AI$37,'[3]Total P&C'!$BE$37:$BG$37)/1000/BR61 -> 0.0052554966 | BS69: =-SUM('[3]Total P&C'!$AC$34:$AI$34,'[3]Total P&C'!$BE$34:$BG$34,'[3]Total P&C'!$AC$38:$AI$38,'[3]Total P&C'!$BE$38:$BG$38)/1000/BS61 -> -0.030960322 | BT69: =-SUM('[3]Total P&C'!$AC$35:$AI$35,'[3]Total P&C'!$BE$35:$BG$35,'[3]Total P&C'!$AC$39:$AI$39,'[3]Total P&C'!$BE$39:$BG$39)/1000/BT61 -> -0.018205939
